Workbook

Sheet Start_Here
A1: Project HEATWISE — Urban Heat Islands and Heat Domes: a monitoring-and-control simulation
A2: SPCE0019 Project Simulation | Interactive what-if workbook | Open data: ECA&D daily observations, London Heathrow, May–September 1979–2023
B4: Scenario | C4: It is spring 2026. A London heat resilience programme (fictional: Project HEATWISE) has completed risk identification, assessment and mitigation planning. Your group is the programme's Risk & Assurance team, responsible for step 4: MONITORING AND CONTROL. Replay real summers — above all the July 2022 heat dome — as if they were live, decide when to act, and turn what monitoring reveals into new or changed requirements.
B5: Core idea | C5: Monitoring and control is not the end of the risk process — it is a feedback loop. Live key risk indicators detect new and changing risks; each detection is the first step of requirements engineering (elicit → analyse → specify → validate). New requirements are then modelled, simulated and optimised (thresholds, tipping points, algorithm drift) and fed back into identification.
B6: The loop | C6: 1 IDENTIFY → 2 ASSESS → 3 MITIGATE → 4 MONITOR & CONTROL → (trigger) → REQUIREMENTS ENGINEERING → MODEL · SIMULATE · OPTIMISE → back to 1 IDENTIFY
B7: Four lenses | C7: DATA: quality flags, sensor drift, single-station bias. AI: a forecasting model that drifts as the climate shifts. SUSTAINABILITY: cooling that adds carbon (maladaptation) vs nature-based solutions. DIVERSITY & INCLUSION: who is exposed, and who the monitoring misses.
B8: How to use | C8: 1) Explore what-if scenarios in the HEATWISE dashboard: https://sbegucl.github.io/heatwise/ 2) Press Record scenario and paste each row into Scenario_Log. 3) Shortlist, score and vote in Decision_Matrix, and record your decision. 4) Complete Risk_Register and Req_Feedback. The other sheets hold the same model as the dashboard for checking figures, tracing formulas and running Solver on Optimise.
B9: Colour key | C9: Blue bold text on yellow = input you may change. Black = formula. Green = link from another sheet. Red/amber/green fills = status. Don't overwrite black cells — copy the workbook first if you want to experiment structurally.
B10: Spot the incident | C10: Look at 19 July 2022 on Monitor_Control with QA policy 'Use raw'. The recorded maximum is lower than the daily mean — physically impossible — and the source flags it as suspect. What would your monitoring system have done on the most dangerous day of the summer?
B11: Honesty about the model | C11: This is a teaching model. The UHI uplifts, group profiles, capacity and intervention effects are assumptions for groups to evidence or challenge. The alert logic is simplified: UKHSA's real heat-health alerts are impact-based. Heathrow is an airport station, not the city centre — that limitation is part of the exercise.
B12: Recalculation | C12: Excel recalculates automatically. If values look stale, press F9. The workbook uses only standard functions (no macros), so it also works in LibreOffice and most online spreadsheet tools that open .xlsx.
B14: Sheet map
B15: Scenario_Log | C15: Paste target for every scenario recorded from the dashboard, scored against the six board targets.
B16: Decision_Matrix | C16: Group weights, shortlist, scores, vote, final decision, relaxed target and dissent log.
B17: Control_Panel | C17: All what-if levers and the live KRI dashboard.
B18: Monitor_Control | C18: The daily feedback loop for the chosen year and neighbourhood: observe, QA, compare, detect, act.
B19: AI_Model | C19: Transparent OLS forecaster; training window; leakage check.
B20: Tipping_Points | C20: Threshold and climate-shift sweeps; stock-and-flow tipping model.
B21: Equity_Lens | C21: Neighbourhood typologies, representation gap, group exposure ranking.
B22: Sustainability | C22: Cooling degree-days, AC electricity, carbon and AI compute.
B23: Optimise | C23: Intervention portfolio, budget, deaths averted, carbon trade-off.
B24: Risk_Register | C24: Module template extended with KRIs, triggers and requirement links.
B25: Req_Feedback | C25: Change requests generated by triggers; disagreement log.
B26: Annual_Trend | C26: 1979–2023 moving baseline and model drift by year.
... B29: Sources_Licence | C29: Data provenance, licences and evidence for defaults.

Sheet Scenario_Log
A1: Scenario_Log — every what-if scenario your group tests
A2: Run scenarios in the HEATWISE dashboard (https://sbegucl.github.io/heatwise/). Press Record scenario, copy the row, then click the first empty cell in column B here and paste. Rows 5–6 are examples: keep them for comparison or delete them.
B3: SCENARIO | E3: SETTINGS | L3: INTERVENTION LEVELS (0–1) | S3: DEATHS (London-wide) | V3: COOLING CARBON | Y3: REPRESENTATION GAP (Inner London) | AB3: AI HOT-DAY RECALL % | AE3: TIPPING DAYS (Inner London) | AH3: TARGETS MET
A4: ID | B4: Recorded by | C4: Scenario name | D4: Year | E4: Mitigation | F4: Hot-day °C | G4: Warm-night °C | H4: Capacity °C·d | I4: QA policy | J4: Sensor drift °C/30d | K4: AI trained to | L4: Greening | M4: Cool roofs | N4: Cooling centres | O4: Sensors | P4: MLOps retrain | Q4: AC subsidy | R4: Cost £m | S4: Deaths +0°C | T4: Deaths +1°C | U4: Deaths +2°C | V4: Carbon tCO₂e +0°C | W4: Carbon tCO₂e +1°C | X4: Carbon tCO₂e +2°C | Y4: Rep. gap days +0°C | Z4: Rep. gap days +1°C | AA4: Rep. gap days +2°C | AB4: AI recall % +0°C | AC4: AI recall % +1°C | AD4: AI recall % +2°C | AE4: Tipping days +0°C | AF4: Tipping days +1°C | AG4: Tipping days +2°C | AH4: Targets met +0°C | AI4: Targets met +1°C | AJ4: Targets met +2°C
A5: =IF(B5="","","S"&TEXT(ROW()-4,"00")) -> S01 | B5: Example | C5: Baseline: no portfolio | D5: 2022 | E5: Baseline | F5: 28 | G5: 18 | H5: 40 | I5: Use raw | J5: 0 | K5: 1998 | L5: 0 | M5: 0 | N5: 0 | O5: 0 | P5: 0 | Q5: 0 | R5: 0 | S5: 387 | T5: 528 | U5: 695 | V5: 4160 | W5: 6016 | X5: 8466 | Y5: 19 | Z5: 15 | AA5: 22 | AB5: 37 | AC5: 36 | AD5: 46 | AE5: 3 | AF5: 6 | AG5: 10 | AH5: =IF(B5="","",(R5<=Budget)+(S5<Deaths_Appetite)+(V5<=Carbon_Budget)+(Y5=0)+(AB5>=Recall_Target*100)+(AE5=0)) -> 2 | AI5: =IF(B5="","",(R5<=Budget)+(T5<Deaths_Appetite)+(W5<=Carbon_Budget)+(Z5=0)+(AC5>=Recall_Target*100)+(AF5=0)) -> 2 | AJ5: =IF(B5="","",(R5<=Budget)+(U5<Deaths_Appetite)+(X5<=Carbon_Budget)+(AA5=0)+(AD5>=Recall_Target*100)+(AG5=0)) -> 2
A6: =IF(B6="","","S"&TEXT(ROW()-4,"00")) -> S02 | B6: Example | C6: Default portfolio: five measures at 50%, no AC | D6: 2022 | E6: With interventions | F6: 28 | G6: 18 | H6: 40 | I6: Use raw | J6: 0 | K6: 1998 | L6: 0.5 | M6: 0.5 | N6: 0.5 | O6: 0.5 | P6: 0.5 | Q6: 0 | R6: 35.3 | S6: 292 | T6: 404 | U6: 541 | V6: 2413 | W6: 4082 | X6: 6294 | Y6: 15 | Z6: 6 | AA6: 15 | AB6: 65 | AC6: 66 | AD6: 66 | AE6: 1 | AF6: 5 | AG6: 8 | AH6: =IF(B6="","",(R6<=Budget)+(S6<Deaths_Appetite)+(V6<=Carbon_Budget)+(Y6=0)+(AB6>=Recall_Target*100)+(AE6=0)) -> 2 | AI6: =IF(B6="","",(R6<=Budget)+(T6<Deaths_Appetite)+(W6<=Carbon_Budget)+(Z6=0)+(AC6>=Recall_Target*100)+(AF6=0)) -> 2 | AJ6: =IF(B6="","",(R6<=Budget)+(U6<Deaths_Appetite)+(X6<=Carbon_Budget)+(AA6=0)+(AD6>=Recall_Target*100)+(AG6=0)) -> 2
A7: =IF(B7="","","S"&TEXT(ROW()-4,"00")) | AH7: =IF(B7="","",(R7<=Budget)+(S7<Deaths_Appetite)+(V7<=Carbon_Budget)+(Y7=0)+(AB7>=Recall_Target*100)+(AE7=0)) | AI7: =IF(B7="","",(R7<=Budget)+(T7<Deaths_Appetite)+(W7<=Carbon_Budget)+(Z7=0)+(AC7>=Recall_Target*100)+(AF7=0)) | AJ7: =IF(B7="","",(R7<=Budget)+(U7<Deaths_Appetite)+(X7<=Carbon_Budget)+(AA7=0)+(AD7>=Recall_Target*100)+(AG7=0))
A8: =IF(B8="","","S"&TEXT(ROW()-4,"00")) | AH8: =IF(B8="","",(R8<=Budget)+(S8<Deaths_Appetite)+(V8<=Carbon_Budget)+(Y8=0)+(AB8>=Recall_Target*100)+(AE8=0)) | AI8: =IF(B8="","",(R8<=Budget)+(T8<Deaths_Appetite)+(W8<=Carbon_Budget)+(Z8=0)+(AC8>=Recall_Target*100)+(AF8=0)) | AJ8: =IF(B8="","",(R8<=Budget)+(U8<Deaths_Appetite)+(X8<=Carbon_Budget)+(AA8=0)+(AD8>=Recall_Target*100)+(AG8=0))
A9: =IF(B9="","","S"&TEXT(ROW()-4,"00")) | AH9: =IF(B9="","",(R9<=Budget)+(S9<Deaths_Appetite)+(V9<=Carbon_Budget)+(Y9=0)+(AB9>=Recall_Target*100)+(AE9=0)) | AI9: =IF(B9="","",(R9<=Budget)+(T9<Deaths_Appetite)+(W9<=Carbon_Budget)+(Z9=0)+(AC9>=Recall_Target*100)+(AF9=0)) | AJ9: =IF(B9="","",(R9<=Budget)+(U9<Deaths_Appetite)+(X9<=Carbon_Budget)+(AA9=0)+(AD9>=Recall_Target*100)+(AG9=0))
A10: =IF(B10="","","S"&TEXT(ROW()-4,"00")) | AH10: =IF(B10="","",(R10<=Budget)+(S10<Deaths_Appetite)+(V10<=Carbon_Budget)+(Y10=0)+(AB10>=Recall_Target*100)+(AE10=0)) | AI10: =IF(B10="","",(R10<=Budget)+(T10<Deaths_Appetite)+(W10<=Carbon_Budget)+(Z10=0)+(AC10>=Recall_Target*100)+(AF10=0)) | AJ10: =IF(B10="","",(R10<=Budget)+(U10<Deaths_Appetite)+(X10<=Carbon_Budget)+(AA10=0)+(AD10>=Recall_Target*100)+(AG10=0))
A11: =IF(B11="","","S"&TEXT(ROW()-4,"00")) | AH11: =IF(B11="","",(R11<=Budget)+(S11<Deaths_Appetite)+(V11<=Carbon_Budget)+(Y11=0)+(AB11>=Recall_Target*100)+(AE11=0)) | AI11: =IF(B11="","",(R11<=Budget)+(T11<Deaths_Appetite)+(W11<=Carbon_Budget)+(Z11=0)+(AC11>=Recall_Target*100)+(AF11=0)) | AJ11: =IF(B11="","",(R11<=Budget)+(U11<Deaths_Appetite)+(X11<=Carbon_Budget)+(AA11=0)+(AD11>=Recall_Target*100)+(AG11=0))
A12: =IF(B12="","","S"&TEXT(ROW()-4,"00")) | AH12: =IF(B12="","",(R12<=Budget)+(S12<Deaths_Appetite)+(V12<=Carbon_Budget)+(Y12=0)+(AB12>=Recall_Target*100)+(AE12=0)) | AI12: =IF(B12="","",(R12<=Budget)+(T12<Deaths_Appetite)+(W12<=Carbon_Budget)+(Z12=0)+(AC12>=Recall_Target*100)+(AF12=0)) | AJ12: =IF(B12="","",(R12<=Budget)+(U12<Deaths_Appetite)+(X12<=Carbon_Budget)+(AA12=0)+(AD12>=Recall_Target*100)+(AG12=0))
A13: =IF(B13="","","S"&TEXT(ROW()-4,"00")) | AH13: =IF(B13="","",(R13<=Budget)+(S13<Deaths_Appetite)+(V13<=Carbon_Budget)+(Y13=0)+(AB13>=Recall_Target*100)+(AE13=0)) | AI13: =IF(B13="","",(R13<=Budget)+(T13<Deaths_Appetite)+(W13<=Carbon_Budget)+(Z13=0)+(AC13>=Recall_Target*100)+(AF13=0)) | AJ13: =IF(B13="","",(R13<=Budget)+(U13<Deaths_Appetite)+(X13<=Carbon_Budget)+(AA13=0)+(AD13>=Recall_Target*100)+(AG13=0))
A14: =IF(B14="","","S"&TEXT(ROW()-4,"00")) | AH14: =IF(B14="","",(R14<=Budget)+(S14<Deaths_Appetite)+(V14<=Carbon_Budget)+(Y14=0)+(AB14>=Recall_Target*100)+(AE14=0)) | AI14: =IF(B14="","",(R14<=Budget)+(T14<Deaths_Appetite)+(W14<=Carbon_Budget)+(Z14=0)+(AC14>=Recall_Target*100)+(AF14=0)) | AJ14: =IF(B14="","",(R14<=Budget)+(U14<Deaths_Appetite)+(X14<=Carbon_Budget)+(AA14=0)+(AD14>=Recall_Target*100)+(AG14=0))
A15: =IF(B15="","","S"&TEXT(ROW()-4,"00")) | AH15: =IF(B15="","",(R15<=Budget)+(S15<Deaths_Appetite)+(V15<=Carbon_Budget)+(Y15=0)+(AB15>=Recall_Target*100)+(AE15=0)) | AI15: =IF(B15="","",(R15<=Budget)+(T15<Deaths_Appetite)+(W15<=Carbon_Budget)+(Z15=0)+(AC15>=Recall_Target*100)+(AF15=0)) | AJ15: =IF(B15="","",(R15<=Budget)+(U15<Deaths_Appetite)+(X15<=Carbon_Budget)+(AA15=0)+(AD15>=Recall_Target*100)+(AG15=0))
A16: =IF(B16="","","S"&TEXT(ROW()-4,"00")) | AH16: =IF(B16="","",(R16<=Budget)+(S16<Deaths_Appetite)+(V16<=Carbon_Budget)+(Y16=0)+(AB16>=Recall_Target*100)+(AE16=0)) | AI16: =IF(B16="","",(R16<=Budget)+(T16<Deaths_Appetite)+(W16<=Carbon_Budget)+(Z16=0)+(AC16>=Recall_Target*100)+(AF16=0)) | AJ16: =IF(B16="","",(R16<=Budget)+(U16<Deaths_Appetite)+(X16<=Carbon_Budget)+(AA16=0)+(AD16>=Recall_Target*100)+(AG16=0))
A17: =IF(B17="","","S"&TEXT(ROW()-4,"00")) | AH17: =IF(B17="","",(R17<=Budget)+(S17<Deaths_Appetite)+(V17<=Carbon_Budget)+(Y17=0)+(AB17>=Recall_Target*100)+(AE17=0)) | AI17: =IF(B17="","",(R17<=Budget)+(T17<Deaths_Appetite)+(W17<=Carbon_Budget)+(Z17=0)+(AC17>=Recall_Target*100)+(AF17=0)) | AJ17: =IF(B17="","",(R17<=Budget)+(U17<Deaths_Appetite)+(X17<=Carbon_Budget)+(AA17=0)+(AD17>=Recall_Target*100)+(AG17=0))
A18: =IF(B18="","","S"&TEXT(ROW()-4,"00")) | AH18: =IF(B18="","",(R18<=Budget)+(S18<Deaths_Appetite)+(V18<=Carbon_Budget)+(Y18=0)+(AB18>=Recall_Target*100)+(AE18=0)) | AI18: =IF(B18="","",(R18<=Budget)+(T18<Deaths_Appetite)+(W18<=Carbon_Budget)+(Z18=0)+(AC18>=Recall_Target*100)+(AF18=0)) | AJ18: =IF(B18="","",(R18<=Budget)+(U18<Deaths_Appetite)+(X18<=Carbon_Budget)+(AA18=0)+(AD18>=Recall_Target*100)+(AG18=0))
... A204: =IF(B204="","","S"&TEXT(ROW()-4,"00")) | AH204: =IF(B204="","",(R204<=Budget)+(S204<Deaths_Appetite)+(V204<=Carbon_Budget)+(Y204=0)+(AB204>=Recall_Target*100)+(AE204=0)) | AI204: =IF(B204="","",(R204<=Budget)+(T204<Deaths_Appetite)+(W204<=Carbon_Budget)+(Z204=0)+(AC204>=Recall_Target*100)+(AF204=0)) | AJ204: =IF(B204="","",(R204<=Budget)+(U204<Deaths_Appetite)+(X204<=Carbon_Budget)+(AA204=0)+(AD204>=Recall_Target*100)+(AG204=0))

Sheet Decision_Matrix
A1: Decision_Matrix — shortlist, score, vote and decide
A2: 1) Agree weights. 2) Shortlist up to five scenario IDs from Scenario_Log. 3) Each member votes. 4) Record the decision, the target you relax and the dissent.
B4: 1. Board targets and your group's weights
B5: Board target | C5: Limit | D5: Weight (0–5) | F5: Warming | G5: Weight
B6: Excess deaths (London-wide) | C6: ="< "&Deaths_Appetite -> < 150 | D6: 1 | F6: +0°C | G6: 0.5 | I6: Limits come from the Control_Panel risk-appetite cells. Weights are a group decision: say why in your recommendation.
B7: Portfolio cost £m | C7: ="≤ "&Budget -> ≤ 50 | D7: 1 | F7: +1°C | G7: 0.3
B8: Cooling carbon tCO₂e | C8: ="≤ "&TEXT(Carbon_Budget,"#,##0") -> ≤ 20,000 | D8: 1 | F8: +2°C | G8: 0.2
B9: Representation gap days | C9: ="0" -> 0 | D9: 1 | F9: Total | G9: =SUM(G6:G8) -> 1
B10: AI hot-day recall % | C10: ="≥ "&Recall_Target*100 -> ≥ 80 | D10: 1
B11: Tipping days | C11: ="0" -> 0 | D11: 1
B13: 2. Shortlist (up to five scenarios)
B14: Scenario ID | C14: Name | D14: Recorded by | E14: Mitigation | F14: Cost £m | G14: Deaths +0 | H14: Deaths +1 | I14: Deaths +2 | J14: Carbon +0 | K14: Carbon +1 | L14: Carbon +2 | M14: Gap +0 | N14: Gap +1 | O14: Gap +2 | P14: Recall +0 | Q14: Recall +1 | R14: Recall +2 | S14: Tipping +0 | T14: Tipping +1 | U14: Tipping +2 | V14: Met +0 | W14: Met +1 | X14: Met +2 | Y14: Weighted score | Z14: Votes | AA14: Rank
B15: S01 | C15: =IF($B15="","",IFERROR(INDEX(Scenario_Log!$C$5:$C$204,MATCH($B15,Scenario_Log!$A$5:$A$204,0)),"ID not found")) -> Baseline: no portfolio | D15: =IF($B15="","",IFERROR(INDEX(Scenario_Log!$B$5:$B$204,MATCH($B15,Scenario_Log!$A$5:$A$204,0)),"ID not found")) -> Example | E15: =IF($B15="","",IFERROR(INDEX(Scenario_Log!$E$5:$E$204,MATCH($B15,Scenario_Log!$A$5:$A$204,0)),"ID not found")) -> Baseline | F15: =IF($B15="","",IFERROR(INDEX(Scenario_Log!$R$5:$R$204,MATCH($B15,Scenario_Log!$A$5:$A$204,0)),"ID not found")) -> 0 | G15: =IF($B15="","",IFERROR(INDEX(Scenario_Log!$S$5:$S$204,MATCH($B15,Scenario_Log!$A$5:$A$204,0)),"ID not found")) -> 387 | H15: =IF($B15="","",IFERROR(INDEX(Scenario_Log!$T$5:$T$204,MATCH($B15,Scenario_Log!$A$5:$A$204,0)),"ID not found")) -> 528 | I15: =IF($B15="","",IFERROR(INDEX(Scenario_Log!$U$5:$U$204,MATCH($B15,Scenario_Log!$A$5:$A$204,0)),"ID not found")) -> 695 | J15: =IF($B15="","",IFERROR(INDEX(Scenario_Log!$V$5:$V$204,MATCH($B15,Scenario_Log!$A$5:$A$204,0)),"ID not found")) -> 4160 | K15: =IF($B15="","",IFERROR(INDEX(Scenario_Log!$W$5:$W$204,MATCH($B15,Scenario_Log!$A$5:$A$204,0)),"ID not found")) -> 6016 | L15: =IF($B15="","",IFERROR(INDEX(Scenario_Log!$X$5:$X$204,MATCH($B15,Scenario_Log!$A$5:$A$204,0)),"ID not found")) -> 8466 | M15: =IF($B15="","",IFERROR(INDEX(Scenario_Log!$Y$5:$Y$204,MATCH($B15,Scenario_Log!$A$5:$A$204,0)),"ID not found")) -> 19 | N15: =IF($B15="","",IFERROR(INDEX(Scenario_Log!$Z$5:$Z$204,MATCH($B15,Scenario_Log!$A$5:$A$204,0)),"ID not found")) -> 15 | O15: =IF($B15="","",IFERROR(INDEX(Scenario_Log!$AA$5:$AA$204,MATCH($B15,Scenario_Log!$A$5:$A$204,0)),"ID not found")) -> 22 | P15: =IF($B15="","",IFERROR(INDEX(Scenario_Log!$AB$5:$AB$204,MATCH($B15,Scenario_Log!$A$5:$A$204,0)),"ID not found")) -> 37 | Q15: =IF($B15="","",IFERROR(INDEX(Scenario_Log!$AC$5:$AC$204,MATCH($B15,Scenario_Log!$A$5:$A$204,0)),"ID not found")) -> 36 | R15: =IF($B15="","",IFERROR(INDEX(Scenario_Log!$AD$5:$AD$204,MATCH($B15,Scenario_Log!$A$5:$A$204,0)),"ID not found")) -> 46 | S15: =IF($B15="","",IFERROR(INDEX(Scenario_Log!$AE$5:$AE$204,MATCH($B15,Scenario_Log!$A$5:$A$204,0)),"ID not found")) -> 3 | T15: =IF($B15="","",IFERROR(INDEX(Scenario_Log!$AF$5:$AF$204,MATCH($B15,Scenario_Log!$A$5:$A$204,0)),"ID not found")) -> 6 | U15: =IF($B15="","",IFERROR(INDEX(Scenario_Log!$AG$5:$AG$204,MATCH($B15,Scenario_Log!$A$5:$A$204,0)),"ID not found")) -> 10 | V15: =IF($B15="","",IFERROR((F15<=Budget)+(G15<Deaths_Appetite)+(J15<=Carbon_Budget)+(M15=0)+(P15>=Recall_Target*100)+(S15=0),"")) -> 2 | W15: =IF($B15="","",IFERROR((F15<=Budget)+(H15<Deaths_Appetite)+(K15<=Carbon_Budget)+(N15=0)+(Q15>=Recall_Target*100)+(T15=0),"")) -> 2 | X15: =IF($B15="","",IFERROR((F15<=Budget)+(I15<Deaths_Appetite)+(L15<=Carbon_Budget)+(O15=0)+(R15>=Recall_Target*100)+(U15=0),"")) -> 2 | Y15: =IF($B15="","",IFERROR(($G$6*($D$6*(G15<Deaths_Appetite)+$D$7*(F15<=Budget)+$D$8*(J15<=Carbon_Budget)+$D$9*(M15=0)+$D$10*(P15>=Recall_Target*100)+$D$11*(S15=0))+$G$7*($D$6*(H15<Deaths_Appetite)+$D$7*(F15<=Budget)+$D$8*(K15<=Carbon_Budget)+$D$9*(N15=0)+$D$10*(Q15>=Recall_Target*100)+$D$11*(T15=0))+$G$8*($D$6*(I15<Deaths_Appetite)+$D$7*(F15<=Budget)+$D$8*(L15<=Carbon_Budget)+$D$9*(O15=0)+$D$10*(R15>=Recall_Target*100)+$D$11*(U15=0)))/(SUM($D$6:$D$11)*$G$9),"")) -> 0.33333333 | Z15: =IF($B15="","",COUNTIF($D$24:$D$29,$B15)) -> 0 | AA15: =IF(OR($B15="",NOT(ISNUMBER(Y15))),"",RANK(Y15,$Y$15:$Y$19)) -> 1
B16: S02 | C16: =IF($B16="","",IFERROR(INDEX(Scenario_Log!$C$5:$C$204,MATCH($B16,Scenario_Log!$A$5:$A$204,0)),"ID not found")) -> Default portfolio: five measures at 50%, no AC | D16: =IF($B16="","",IFERROR(INDEX(Scenario_Log!$B$5:$B$204,MATCH($B16,Scenario_Log!$A$5:$A$204,0)),"ID not found")) -> Example | E16: =IF($B16="","",IFERROR(INDEX(Scenario_Log!$E$5:$E$204,MATCH($B16,Scenario_Log!$A$5:$A$204,0)),"ID not found")) -> With interventions | F16: =IF($B16="","",IFERROR(INDEX(Scenario_Log!$R$5:$R$204,MATCH($B16,Scenario_Log!$A$5:$A$204,0)),"ID not found")) -> 35.3 | G16: =IF($B16="","",IFERROR(INDEX(Scenario_Log!$S$5:$S$204,MATCH($B16,Scenario_Log!$A$5:$A$204,0)),"ID not found")) -> 292 | H16: =IF($B16="","",IFERROR(INDEX(Scenario_Log!$T$5:$T$204,MATCH($B16,Scenario_Log!$A$5:$A$204,0)),"ID not found")) -> 404 | I16: =IF($B16="","",IFERROR(INDEX(Scenario_Log!$U$5:$U$204,MATCH($B16,Scenario_Log!$A$5:$A$204,0)),"ID not found")) -> 541 | J16: =IF($B16="","",IFERROR(INDEX(Scenario_Log!$V$5:$V$204,MATCH($B16,Scenario_Log!$A$5:$A$204,0)),"ID not found")) -> 2413 | K16: =IF($B16="","",IFERROR(INDEX(Scenario_Log!$W$5:$W$204,MATCH($B16,Scenario_Log!$A$5:$A$204,0)),"ID not found")) -> 4082 | L16: =IF($B16="","",IFERROR(INDEX(Scenario_Log!$X$5:$X$204,MATCH($B16,Scenario_Log!$A$5:$A$204,0)),"ID not found")) -> 6294 | M16: =IF($B16="","",IFERROR(INDEX(Scenario_Log!$Y$5:$Y$204,MATCH($B16,Scenario_Log!$A$5:$A$204,0)),"ID not found")) -> 15 | N16: =IF($B16="","",IFERROR(INDEX(Scenario_Log!$Z$5:$Z$204,MATCH($B16,Scenario_Log!$A$5:$A$204,0)),"ID not found")) -> 6 | O16: =IF($B16="","",IFERROR(INDEX(Scenario_Log!$AA$5:$AA$204,MATCH($B16,Scenario_Log!$A$5:$A$204,0)),"ID not found")) -> 15 | P16: =IF($B16="","",IFERROR(INDEX(Scenario_Log!$AB$5:$AB$204,MATCH($B16,Scenario_Log!$A$5:$A$204,0)),"ID not found")) -> 65 | Q16: =IF($B16="","",IFERROR(INDEX(Scenario_Log!$AC$5:$AC$204,MATCH($B16,Scenario_Log!$A$5:$A$204,0)),"ID not found")) -> 66 | R16: =IF($B16="","",IFERROR(INDEX(Scenario_Log!$AD$5:$AD$204,MATCH($B16,Scenario_Log!$A$5:$A$204,0)),"ID not found")) -> 66 | S16: =IF($B16="","",IFERROR(INDEX(Scenario_Log!$AE$5:$AE$204,MATCH($B16,Scenario_Log!$A$5:$A$204,0)),"ID not found")) -> 1 | T16: =IF($B16="","",IFERROR(INDEX(Scenario_Log!$AF$5:$AF$204,MATCH($B16,Scenario_Log!$A$5:$A$204,0)),"ID not found")) -> 5 | U16: =IF($B16="","",IFERROR(INDEX(Scenario_Log!$AG$5:$AG$204,MATCH($B16,Scenario_Log!$A$5:$A$204,0)),"ID not found")) -> 8 | V16: =IF($B16="","",IFERROR((F16<=Budget)+(G16<Deaths_Appetite)+(J16<=Carbon_Budget)+(M16=0)+(P16>=Recall_Target*100)+(S16=0),"")) -> 2 | W16: =IF($B16="","",IFERROR((F16<=Budget)+(H16<Deaths_Appetite)+(K16<=Carbon_Budget)+(N16=0)+(Q16>=Recall_Target*100)+(T16=0),"")) -> 2 | X16: =IF($B16="","",IFERROR((F16<=Budget)+(I16<Deaths_Appetite)+(L16<=Carbon_Budget)+(O16=0)+(R16>=Recall_Target*100)+(U16=0),"")) -> 2 | Y16: =IF($B16="","",IFERROR(($G$6*($D$6*(G16<Deaths_Appetite)+$D$7*(F16<=Budget)+$D$8*(J16<=Carbon_Budget)+$D$9*(M16=0)+$D$10*(P16>=Recall_Target*100)+$D$11*(S16=0))+$G$7*($D$6*(H16<Deaths_Appetite)+$D$7*(F16<=Budget)+$D$8*(K16<=Carbon_Budget)+$D$9*(N16=0)+$D$10*(Q16>=Recall_Target*100)+$D$11*(T16=0))+$G$8*($D$6*(I16<Deaths_Appetite)+$D$7*(F16<=Budget)+$D$8*(L16<=Carbon_Budget)+$D$9*(O16=0)+$D$10*(R16>=Recall_Target*100)+$D$11*(U16=0)))/(SUM($D$6:$D$11)*$G$9),"")) -> 0.33333333 | Z16: =IF($B16="","",COUNTIF($D$24:$D$29,$B16)) -> 0 | AA16: =IF(OR($B16="",NOT(ISNUMBER(Y16))),"",RANK(Y16,$Y$15:$Y$19)) -> 1
C17: =IF($B17="","",IFERROR(INDEX(Scenario_Log!$C$5:$C$204,MATCH($B17,Scenario_Log!$A$5:$A$204,0)),"ID not found")) | D17: =IF($B17="","",IFERROR(INDEX(Scenario_Log!$B$5:$B$204,MATCH($B17,Scenario_Log!$A$5:$A$204,0)),"ID not found")) | E17: =IF($B17="","",IFERROR(INDEX(Scenario_Log!$E$5:$E$204,MATCH($B17,Scenario_Log!$A$5:$A$204,0)),"ID not found")) | F17: =IF($B17="","",IFERROR(INDEX(Scenario_Log!$R$5:$R$204,MATCH($B17,Scenario_Log!$A$5:$A$204,0)),"ID not found")) | G17: =IF($B17="","",IFERROR(INDEX(Scenario_Log!$S$5:$S$204,MATCH($B17,Scenario_Log!$A$5:$A$204,0)),"ID not found")) | H17: =IF($B17="","",IFERROR(INDEX(Scenario_Log!$T$5:$T$204,MATCH($B17,Scenario_Log!$A$5:$A$204,0)),"ID not found")) | I17: =IF($B17="","",IFERROR(INDEX(Scenario_Log!$U$5:$U$204,MATCH($B17,Scenario_Log!$A$5:$A$204,0)),"ID not found")) | J17: =IF($B17="","",IFERROR(INDEX(Scenario_Log!$V$5:$V$204,MATCH($B17,Scenario_Log!$A$5:$A$204,0)),"ID not found")) | K17: =IF($B17="","",IFERROR(INDEX(Scenario_Log!$W$5:$W$204,MATCH($B17,Scenario_Log!$A$5:$A$204,0)),"ID not found")) | L17: =IF($B17="","",IFERROR(INDEX(Scenario_Log!$X$5:$X$204,MATCH($B17,Scenario_Log!$A$5:$A$204,0)),"ID not found")) | M17: =IF($B17="","",IFERROR(INDEX(Scenario_Log!$Y$5:$Y$204,MATCH($B17,Scenario_Log!$A$5:$A$204,0)),"ID not found")) | N17: =IF($B17="","",IFERROR(INDEX(Scenario_Log!$Z$5:$Z$204,MATCH($B17,Scenario_Log!$A$5:$A$204,0)),"ID not found")) | O17: =IF($B17="","",IFERROR(INDEX(Scenario_Log!$AA$5:$AA$204,MATCH($B17,Scenario_Log!$A$5:$A$204,0)),"ID not found")) | P17: =IF($B17="","",IFERROR(INDEX(Scenario_Log!$AB$5:$AB$204,MATCH($B17,Scenario_Log!$A$5:$A$204,0)),"ID not found")) | Q17: =IF($B17="","",IFERROR(INDEX(Scenario_Log!$AC$5:$AC$204,MATCH($B17,Scenario_Log!$A$5:$A$204,0)),"ID not found")) | R17: =IF($B17="","",IFERROR(INDEX(Scenario_Log!$AD$5:$AD$204,MATCH($B17,Scenario_Log!$A$5:$A$204,0)),"ID not found")) | S17: =IF($B17="","",IFERROR(INDEX(Scenario_Log!$AE$5:$AE$204,MATCH($B17,Scenario_Log!$A$5:$A$204,0)),"ID not found")) | T17: =IF($B17="","",IFERROR(INDEX(Scenario_Log!$AF$5:$AF$204,MATCH($B17,Scenario_Log!$A$5:$A$204,0)),"ID not found")) | U17: =IF($B17="","",IFERROR(INDEX(Scenario_Log!$AG$5:$AG$204,MATCH($B17,Scenario_Log!$A$5:$A$204,0)),"ID not found")) | V17: =IF($B17="","",IFERROR((F17<=Budget)+(G17<Deaths_Appetite)+(J17<=Carbon_Budget)+(M17=0)+(P17>=Recall_Target*100)+(S17=0),"")) | W17: =IF($B17="","",IFERROR((F17<=Budget)+(H17<Deaths_Appetite)+(K17<=Carbon_Budget)+(N17=0)+(Q17>=Recall_Target*100)+(T17=0),"")) | X17: =IF($B17="","",IFERROR((F17<=Budget)+(I17<Deaths_Appetite)+(L17<=Carbon_Budget)+(O17=0)+(R17>=Recall_Target*100)+(U17=0),"")) | Y17: =IF($B17="","",IFERROR(($G$6*($D$6*(G17<Deaths_Appetite)+$D$7*(F17<=Budget)+$D$8*(J17<=Carbon_Budget)+$D$9*(M17=0)+$D$10*(P17>=Recall_Target*100)+$D$11*(S17=0))+$G$7*($D$6*(H17<Deaths_Appetite)+$D$7*(F17<=Budget)+$D$8*(K17<=Carbon_Budget)+$D$9*(N17=0)+$D$10*(Q17>=Recall_Target*100)+$D$11*(T17=0))+$G$8*($D$6*(I17<Deaths_Appetite)+$D$7*(F17<=Budget)+$D$8*(L17<=Carbon_Budget)+$D$9*(O17=0)+$D$10*(R17>=Recall_Target*100)+$D$11*(U17=0)))/(SUM($D$6:$D$11)*$G$9),"")) | Z17: =IF($B17="","",COUNTIF($D$24:$D$29,$B17)) | AA17: =IF(OR($B17="",NOT(ISNUMBER(Y17))),"",RANK(Y17,$Y$15:$Y$19))
C18: =IF($B18="","",IFERROR(INDEX(Scenario_Log!$C$5:$C$204,MATCH($B18,Scenario_Log!$A$5:$A$204,0)),"ID not found")) | D18: =IF($B18="","",IFERROR(INDEX(Scenario_Log!$B$5:$B$204,MATCH($B18,Scenario_Log!$A$5:$A$204,0)),"ID not found")) | E18: =IF($B18="","",IFERROR(INDEX(Scenario_Log!$E$5:$E$204,MATCH($B18,Scenario_Log!$A$5:$A$204,0)),"ID not found")) | F18: =IF($B18="","",IFERROR(INDEX(Scenario_Log!$R$5:$R$204,MATCH($B18,Scenario_Log!$A$5:$A$204,0)),"ID not found")) | G18: =IF($B18="","",IFERROR(INDEX(Scenario_Log!$S$5:$S$204,MATCH($B18,Scenario_Log!$A$5:$A$204,0)),"ID not found")) | H18: =IF($B18="","",IFERROR(INDEX(Scenario_Log!$T$5:$T$204,MATCH($B18,Scenario_Log!$A$5:$A$204,0)),"ID not found")) | I18: =IF($B18="","",IFERROR(INDEX(Scenario_Log!$U$5:$U$204,MATCH($B18,Scenario_Log!$A$5:$A$204,0)),"ID not found")) | J18: =IF($B18="","",IFERROR(INDEX(Scenario_Log!$V$5:$V$204,MATCH($B18,Scenario_Log!$A$5:$A$204,0)),"ID not found")) | K18: =IF($B18="","",IFERROR(INDEX(Scenario_Log!$W$5:$W$204,MATCH($B18,Scenario_Log!$A$5:$A$204,0)),"ID not found")) | L18: =IF($B18="","",IFERROR(INDEX(Scenario_Log!$X$5:$X$204,MATCH($B18,Scenario_Log!$A$5:$A$204,0)),"ID not found")) | M18: =IF($B18="","",IFERROR(INDEX(Scenario_Log!$Y$5:$Y$204,MATCH($B18,Scenario_Log!$A$5:$A$204,0)),"ID not found")) | N18: =IF($B18="","",IFERROR(INDEX(Scenario_Log!$Z$5:$Z$204,MATCH($B18,Scenario_Log!$A$5:$A$204,0)),"ID not found")) | O18: =IF($B18="","",IFERROR(INDEX(Scenario_Log!$AA$5:$AA$204,MATCH($B18,Scenario_Log!$A$5:$A$204,0)),"ID not found")) | P18: =IF($B18="","",IFERROR(INDEX(Scenario_Log!$AB$5:$AB$204,MATCH($B18,Scenario_Log!$A$5:$A$204,0)),"ID not found")) | Q18: =IF($B18="","",IFERROR(INDEX(Scenario_Log!$AC$5:$AC$204,MATCH($B18,Scenario_Log!$A$5:$A$204,0)),"ID not found")) | R18: =IF($B18="","",IFERROR(INDEX(Scenario_Log!$AD$5:$AD$204,MATCH($B18,Scenario_Log!$A$5:$A$204,0)),"ID not found")) | S18: =IF($B18="","",IFERROR(INDEX(Scenario_Log!$AE$5:$AE$204,MATCH($B18,Scenario_Log!$A$5:$A$204,0)),"ID not found")) | T18: =IF($B18="","",IFERROR(INDEX(Scenario_Log!$AF$5:$AF$204,MATCH($B18,Scenario_Log!$A$5:$A$204,0)),"ID not found")) | U18: =IF($B18="","",IFERROR(INDEX(Scenario_Log!$AG$5:$AG$204,MATCH($B18,Scenario_Log!$A$5:$A$204,0)),"ID not found")) | V18: =IF($B18="","",IFERROR((F18<=Budget)+(G18<Deaths_Appetite)+(J18<=Carbon_Budget)+(M18=0)+(P18>=Recall_Target*100)+(S18=0),"")) | W18: =IF($B18="","",IFERROR((F18<=Budget)+(H18<Deaths_Appetite)+(K18<=Carbon_Budget)+(N18=0)+(Q18>=Recall_Target*100)+(T18=0),"")) | X18: =IF($B18="","",IFERROR((F18<=Budget)+(I18<Deaths_Appetite)+(L18<=Carbon_Budget)+(O18=0)+(R18>=Recall_Target*100)+(U18=0),"")) | Y18: =IF($B18="","",IFERROR(($G$6*($D$6*(G18<Deaths_Appetite)+$D$7*(F18<=Budget)+$D$8*(J18<=Carbon_Budget)+$D$9*(M18=0)+$D$10*(P18>=Recall_Target*100)+$D$11*(S18=0))+$G$7*($D$6*(H18<Deaths_Appetite)+$D$7*(F18<=Budget)+$D$8*(K18<=Carbon_Budget)+$D$9*(N18=0)+$D$10*(Q18>=Recall_Target*100)+$D$11*(T18=0))+$G$8*($D$6*(I18<Deaths_Appetite)+$D$7*(F18<=Budget)+$D$8*(L18<=Carbon_Budget)+$D$9*(O18=0)+$D$10*(R18>=Recall_Target*100)+$D$11*(U18=0)))/(SUM($D$6:$D$11)*$G$9),"")) | Z18: =IF($B18="","",COUNTIF($D$24:$D$29,$B18)) | AA18: =IF(OR($B18="",NOT(ISNUMBER(Y18))),"",RANK(Y18,$Y$15:$Y$19))
C19: =IF($B19="","",IFERROR(INDEX(Scenario_Log!$C$5:$C$204,MATCH($B19,Scenario_Log!$A$5:$A$204,0)),"ID not found")) | D19: =IF($B19="","",IFERROR(INDEX(Scenario_Log!$B$5:$B$204,MATCH($B19,Scenario_Log!$A$5:$A$204,0)),"ID not found")) | E19: =IF($B19="","",IFERROR(INDEX(Scenario_Log!$E$5:$E$204,MATCH($B19,Scenario_Log!$A$5:$A$204,0)),"ID not found")) | F19: =IF($B19="","",IFERROR(INDEX(Scenario_Log!$R$5:$R$204,MATCH($B19,Scenario_Log!$A$5:$A$204,0)),"ID not found")) | G19: =IF($B19="","",IFERROR(INDEX(Scenario_Log!$S$5:$S$204,MATCH($B19,Scenario_Log!$A$5:$A$204,0)),"ID not found")) | H19: =IF($B19="","",IFERROR(INDEX(Scenario_Log!$T$5:$T$204,MATCH($B19,Scenario_Log!$A$5:$A$204,0)),"ID not found")) | I19: =IF($B19="","",IFERROR(INDEX(Scenario_Log!$U$5:$U$204,MATCH($B19,Scenario_Log!$A$5:$A$204,0)),"ID not found")) | J19: =IF($B19="","",IFERROR(INDEX(Scenario_Log!$V$5:$V$204,MATCH($B19,Scenario_Log!$A$5:$A$204,0)),"ID not found")) | K19: =IF($B19="","",IFERROR(INDEX(Scenario_Log!$W$5:$W$204,MATCH($B19,Scenario_Log!$A$5:$A$204,0)),"ID not found")) | L19: =IF($B19="","",IFERROR(INDEX(Scenario_Log!$X$5:$X$204,MATCH($B19,Scenario_Log!$A$5:$A$204,0)),"ID not found")) | M19: =IF($B19="","",IFERROR(INDEX(Scenario_Log!$Y$5:$Y$204,MATCH($B19,Scenario_Log!$A$5:$A$204,0)),"ID not found")) | N19: =IF($B19="","",IFERROR(INDEX(Scenario_Log!$Z$5:$Z$204,MATCH($B19,Scenario_Log!$A$5:$A$204,0)),"ID not found")) | O19: =IF($B19="","",IFERROR(INDEX(Scenario_Log!$AA$5:$AA$204,MATCH($B19,Scenario_Log!$A$5:$A$204,0)),"ID not found")) | P19: =IF($B19="","",IFERROR(INDEX(Scenario_Log!$AB$5:$AB$204,MATCH($B19,Scenario_Log!$A$5:$A$204,0)),"ID not found")) | Q19: =IF($B19="","",IFERROR(INDEX(Scenario_Log!$AC$5:$AC$204,MATCH($B19,Scenario_Log!$A$5:$A$204,0)),"ID not found")) | R19: =IF($B19="","",IFERROR(INDEX(Scenario_Log!$AD$5:$AD$204,MATCH($B19,Scenario_Log!$A$5:$A$204,0)),"ID not found")) | S19: =IF($B19="","",IFERROR(INDEX(Scenario_Log!$AE$5:$AE$204,MATCH($B19,Scenario_Log!$A$5:$A$204,0)),"ID not found")) | T19: =IF($B19="","",IFERROR(INDEX(Scenario_Log!$AF$5:$AF$204,MATCH($B19,Scenario_Log!$A$5:$A$204,0)),"ID not found")) | U19: =IF($B19="","",IFERROR(INDEX(Scenario_Log!$AG$5:$AG$204,MATCH($B19,Scenario_Log!$A$5:$A$204,0)),"ID not found")) | V19: =IF($B19="","",IFERROR((F19<=Budget)+(G19<Deaths_Appetite)+(J19<=Carbon_Budget)+(M19=0)+(P19>=Recall_Target*100)+(S19=0),"")) | W19: =IF($B19="","",IFERROR((F19<=Budget)+(H19<Deaths_Appetite)+(K19<=Carbon_Budget)+(N19=0)+(Q19>=Recall_Target*100)+(T19=0),"")) | X19: =IF($B19="","",IFERROR((F19<=Budget)+(I19<Deaths_Appetite)+(L19<=Carbon_Budget)+(O19=0)+(R19>=Recall_Target*100)+(U19=0),"")) | Y19: =IF($B19="","",IFERROR(($G$6*($D$6*(G19<Deaths_Appetite)+$D$7*(F19<=Budget)+$D$8*(J19<=Carbon_Budget)+$D$9*(M19=0)+$D$10*(P19>=Recall_Target*100)+$D$11*(S19=0))+$G$7*($D$6*(H19<Deaths_Appetite)+$D$7*(F19<=Budget)+$D$8*(K19<=Carbon_Budget)+$D$9*(N19=0)+$D$10*(Q19>=Recall_Target*100)+$D$11*(T19=0))+$G$8*($D$6*(I19<Deaths_Appetite)+$D$7*(F19<=Budget)+$D$8*(L19<=Carbon_Budget)+$D$9*(O19=0)+$D$10*(R19>=Recall_Target*100)+$D$11*(U19=0)))/(SUM($D$6:$D$11)*$G$9),"")) | Z19: =IF($B19="","",COUNTIF($D$24:$D$29,$B19)) | AA19: =IF(OR($B19="",NOT(ISNUMBER(Y19))),"",RANK(Y19,$Y$15:$Y$19))
B20: No scenario meets every target at +2°C: the weighted score shows which trade-off your weights favour, not the right answer.
B22: 3. Group vote
B23: Member (initials) | C23: Role this round | D23: Vote (scenario ID) | E23: Why
B31: 4. Decision
B32: Chosen scenario ID
B33: Chosen scenario name | C33: =IF(C32="","",IFERROR(INDEX(Scenario_Log!$C$5:$C$204,MATCH(C32,Scenario_Log!$A$5:$A$204,0)),"ID not found"))
B34: Target we recommend relaxing
B35: Why this trade-off
B36: Residual risk and who carries it
B37: Copilot challenge: strongest objection and our response
B39: 5. Dissent log (at least two entries)
B40: Who | C40: Disagreed about | D40: Evidence tested in the dashboard | G40: How it was resolved

Sheet Control_Panel
A1: Control Panel — what-if levers (Project HEATWISE)
A2: Blue text on yellow = inputs you change. Black = formulas. Green = links from other sheets. Every output in the workbook recalculates from these levers.
B4: A. Scenario | G4: Live monitoring dashboard (selected year and area)
B5: Monitoring year (1979–2023) | C5: 2022 | D5: year | E5: 2022 = July heat dome (40.2°C recorded at Heathrow on 18 Jul in this series). | G5: Key risk indicator | H5: Value | I5: Status
B6: Neighbourhood typology monitored | C6: Inner London: dense, low green | E6: Drives the urban heat island (UHI) uplift applied to the reference station. Edit uplifts on Equity_Lens. | G6: Hot days | H6: =KPI_HotDays -> 41
B7: Mitigation scenario | C7: Baseline | E7: 'With interventions' applies the levels set on the Optimise sheet. | G7: Heatwave days (Met Office-style) | H7: =KPI_HWDays -> 21 | I7: =IF(KPI_HWDays>0,"RED","GREEN") -> RED
B8: Climate shift added to observations | C8: 0 | D8: °C | E8: What-if warming applied uniformly. Try 0.5–3.0 to probe tipping points. | G8: Longest hot-day run | H8: =KPI_MaxRun -> 9
B9: B. Hazard thresholds (key risk indicators) | G9: Warm nights (no recovery) | H9: =KPI_WarmNights -> 64 | I9: =IF(KPI_WarmNights>=10,"RED",IF(KPI_WarmNights>=3,"AMBER","GREEN")) -> RED
B10: Hot-day threshold (daily max) | C10: 28 | D10: °C | E10: Met Office heatwave threshold for London = 28°C on ≥3 consecutive days. | G10: Amber-or-red alert days | H10: =KPI_Amber -> 19 | I10: =IF(KPI_Red>0,"RED",IF(KPI_Amber>0,"AMBER","GREEN")) -> RED
B11: Consecutive hot days that define a heatwave | C11: 3 | D11: days | E11: Met Office definition: at least three consecutive days. | G11: Peak adjusted daily max °C | H11: =KPI_PeakTX -> 42.2
B12: Warm-night threshold (daily min) | C12: 18 | D12: °C | E12: Assumption: commonly cited legacy London night threshold — verify and justify. | G12: Peak heat-stress stock (°C·days) | H12: =KPI_PeakStock -> 45.575094 | I12: =IF(KPI_TipDays>0,"RED",IF(KPI_PeakStock>0.75*Capacity,"AMBER","GREEN")) -> RED
B13: Red-alert daily max (with warm night) | C13: 35 | D13: °C | E13: Teaching assumption: UKHSA alerts are impact-based, not a single temperature. | G13: Tipping days (capacity exceeded) | H13: =KPI_TipDays -> 3 | I13: =IF(KPI_TipDays>0,"RED","GREEN") -> RED
B14: Mean-temperature threshold for heat mortality | C14: 20 | D14: °C | E14: UKHSA defines heat episodes partly by mean CET ≥ 20°C. Used here for the exposure–response model. | G14: First tipping date | H14: =First_Tip -> 44760
B15: C. Data quality | G15: London-wide excess deaths (model) | H15: =London_Deaths -> 387 | I15: =IF(London_Deaths>Deaths_Appetite,"RED",IF(London_Deaths>0.75*Deaths_Appetite,"AMBER","GREEN")) -> RED
B16: Suspect-observation policy | C16: Use raw | E16: Use raw | Exclude suspect | Impute with model. Suspect = ECA&D flag ≠ 0 or TX < TG. | G16: Suspect observations on hot/warm days | H16: =KPI_SuspectHot -> 5 | I16: =IF(KPI_SuspectHot>0,"AMBER","GREEN") -> AMBER
B17: Injected sensor drift | C17: 0 | D17: °C/30d | E17: Simulates a degrading thermometer (data drift). 0 = off. Try 1.0. | G17: AI drift-alarm events | H17: =KPI_DriftDays -> 2 | I17: =IF(KPI_DriftDays>1,"RED",IF(KPI_DriftDays=1,"AMBER","GREEN")) -> RED
B18: Sensor drift starts on season day | C18: 60 | D18: day | E18: Day 1 = 1 May; day 62 = 1 July; day 79 = 18 July. | G18: First drift alarm | H18: =First_Drift -> 44760
B19: D. AI forecasting model and drift monitoring | G19: AI hot-day recall | H19: =KPI_Recall -> 0.36585366 | I19: =IF(ISNUMBER(KPI_Recall),IF(KPI_Recall<Recall_Target,"RED","GREEN"),"n/a") -> RED
B20: Training window start year | C20: 1979 | D20: year | E20: Model: next-day max temperature from today's max and sea-level pressure (OLS). | G20: AI missed hot days | H20: =KPI_Misses -> 26
B21: Training window end year | C21: 1998 | D21: year | E21: An old window bakes in a cooler climate → concept drift. | G21: Test year inside training window? (leak) | H21: =Leak_Flag -> 0 | I21: =IF(Leak_Flag=1,"AMBER","GREEN") -> GREEN
B22: CUSUM allowance k | C22: 1 | D22: °C | E22: Slack per day before bias accumulates. Calibrated: ~0.5 false alarms per summer in-sample. | G22: Representation-gap days | H22: =KPI_RepGap -> 19 | I22: =IF(KPI_RepGap>0,"RED","GREEN") -> RED
B23: CUSUM decision interval h | C23: 15 | D23: °C | E23: Alarm when cumulative bias exceeds h; CUSUM resets after each alarm. | G23: Cooling carbon tCO₂e (scenario) | H23: =Carbon_Now -> 4160.2612 | I23: =IF(Carbon_Now>Carbon_Budget,"RED","GREEN") -> GREEN
B24: Rolling 7-day MAE tolerance | C24: 4.5 | D24: °C | E24: Alarm when the model's recent error exceeds tolerance (typical MAE ≈ 2°C). | G24: Requirement change requests raised | H24: =Req_CR_Count -> 7 | I24: =IF(Req_CR_Count>0,"AMBER","GREEN") -> AMBER
B25: Required hot-day recall of the AI alert | C25: 0.8 | E25: Share of actual hot days the model must flag (missed alerts harm people).
B26: E. Tipping-point model (stock and flow of heat stress)
B27: Daytime heat-load threshold | C27: 25 | D27: °C | E27: Inflow to the heat-stress stock = max(0, TX_adj − this).
B28: Night-time recovery rate | C28: 0.5 | D28: per °C | E28: Extra outflow = rate × max(0, T_Night − TN_adj). Warm nights → no extra recovery.
B29: Baseline daily recovery (decay) | C29: 0.2 | D29: fraction/day | E29: Share of the stock that dissipates each day. Calibrated so inner London tips only in extreme summers (2003, 2020, 2022).
B30: System capacity (tipping threshold) | C30: 40 | D30: °C·days | E30: Stock above this = services overwhelmed (tipping). Teaching calibration — challenge it.
B31: Steepness of failure curve | C31: 0.15 | E31: P(failure) = 1/(1+exp(−k·(stock − capacity))).
B32: F. Health model calibration
B33: Calibration target: London excess deaths | C33: 387 | D33: deaths | E33: UKHSA Heat mortality monitoring report 2022: London total 387 (95% CI 158–615).
B34: Calibration year | C34: 2022 | D34: year | E34: β is re-derived so the reference-climate model reproduces the target.
B35: G. Risk appetite and constraints
B36: Excess-death appetite (London, per summer) | C36: 150 | D36: deaths | E36: Programme board appetite. Group decision — justify it.
B37: Cooling carbon budget | C37: 20000 | D37: tCO₂e | E37: Net cooling-related emissions allowed per summer.
B38: Intervention budget | C38: 50 | D38: £m | E38: Capital + annual revenue envelope for the Optimise sheet.
B40: H. Derived values (formulas — do not edit)
B41: Base daytime UHI uplift (selected typology) | C41: =INDEX(Equity_Lens!$C$6:$C$9,MATCH(Typology,Equity_Lens!$B$6:$B$9,0)) -> 2 | D41: °C
B42: Base night-time UHI uplift | C42: =INDEX(Equity_Lens!$D$6:$D$9,MATCH(Typology,Equity_Lens!$B$6:$B$9,0)) -> 4 | D42: °C
B43: Population share of selected typology | C43: =INDEX(Equity_Lens!$E$6:$E$9,MATCH(Typology,Equity_Lens!$B$6:$B$9,0)) -> 0.3
B44: Interventions active? (1 = yes) | C44: =IF(Scenario="With interventions",1,0) -> 0
B45: Daytime UHI reduction fraction | C45: =Mit_On*Opt_Day_Frac -> 0
B46: Night-time UHI reduction fraction | C46: =Mit_On*Opt_Night_Frac -> 0
B47: Effective daytime UHI uplift | C47: =UHI_Day_Base-Day_Red_Frac*MAX(0,UHI_Day_Base) -> 2 | D47: °C
B48: Effective night-time UHI uplift | C48: =UHI_Night_Base-Night_Red_Frac*MAX(0,UHI_Night_Base) -> 4 | D48: °C
B49: Health sensitivity reduction | C49: =Mit_On*Opt_Sens_Red -> 0
B50: Neighbourhood sensing active? (1 = yes) | C50: =IF(AND(Mit_On=1,Opt_Sensor_Lvl>=0.5),1,0) -> 0
B51: Rolling retraining governance active? (1 = yes) | C51: =IF(AND(Mit_On=1,Opt_Retrain_Lvl>=0.5),1,0) -> 0
B52: Effective training start year | C52: =IF(Retrain_On=1,MAX(1979,SelYear-20),Train_Start_In) -> 1979 | D52: year
B53: Effective training end year | C53: =IF(Retrain_On=1,MAX(1979,SelYear-1),Train_End_In) -> 1998 | D53: year
B54: Calibrated β (excess deaths per °C·day, London-wide) | C54: =Calib_Target/MAX(0.001,Equity_Lens!$O$10) -> 1.8513203

Sheet Monitor_Control
A1: Monitor_Control — step 4 of risk management as a live feedback loop
A2: Each day: observe → quality-check → compare with thresholds and model → detect drift and tipping → recommend control action → raise requirement change. Scroll right for AI drift columns.
A3: Year: | B3: =SelYear -> 2022 | D3: Hot days | F3: Warm nights | H3: Heatwave days | J3: Longest hot run | L3: Amber+ days | N3: Red days | P3: Peak TX adjusted °C | R3: Peak heat-stress stock
A4: Area: | B4: =Typology -> Inner London: dense, low green | D4: =SUM(N9:N161) -> 41 | F4: =SUM(O9:O161) -> 64 | H4: =SUM(Q9:Q161) -> 21 | J4: =MAX(P9:P161) -> 9 | L4: =COUNTIF(S9:S161,">=2") -> 19 | N4: =COUNTIF(S9:S161,3) -> 6 | P4: =MAX(I9:I161) -> 42.2 | R4: =MAX(T9:T161) -> 45.575094
A5: QA: | B5: =QA_Policy -> Use raw | D5: Tipping days | F5: Suspect obs on hot/warm days | H5: Drift-alarm events | J5: AI hot-day recall | L5: AI missed hot days | N5: AI false alarms | P5: Representation-gap days | R5: Excess deaths (this typology)
D6: =SUM(U9:U161) -> 3 | F6: =SUMPRODUCT((E9:E161=1)*(((N9:N161)+(O9:O161))>0)) -> 5 | H6: =SUMPRODUCT((AD9:AD161=1)*(AD8:AD160<>1)) -> 2 | J6: =IFERROR(COUNTIF(AF9:AF161,"Hit")/(COUNTIF(AF9:AF161,"Hit")+COUNTIF(AF9:AF161,"Miss")),"n/a") -> 0.36585366 | L6: =COUNTIF(AF9:AF161,"Miss") -> 26 | N6: =COUNTIF(AF9:AF161,"False alarm") -> 1 | P6: =SUM(AH9:AH161) -> 19 | R6: =SUM(W9:W161) -> 186.94633
A7: Time | D7: 1. OBSERVE & QUALITY-CHECK | N7: 2. COMPARE WITH THRESHOLDS | T7: 3. TIPPING POINT & IMPACT | X7: 4. AI MODEL MONITORING (DRIFT, RECALL, EQUITY) | AI7: 5. CONTROL
A8: Day | B8: Data row | C8: Date | D8: TX observed °C | E8: Suspect obs | F8: Model forecast (raw) °C | G8: Injected sensor drift °C | H8: TX used (after QA) °C | I8: TX adjusted °C | J8: TN observed °C | K8: TN adjusted °C | L8: TG observed °C | M8: TG adjusted °C | N8: Hot day | O8: Warm night | P8: Hot-day run | Q8: Heatwave day | R8: Alert level | S8: Alert score | T8: Heat-stress stock °C·d | U8: Tipping (stock > capacity) | V8: P(service failure) | W8: Excess deaths (this typology) | X8: Model forecast (adjusted) °C | Y8: Residual °C | Z8: |Residual| °C | AA8: Rolling 7-day MAE °C | AB8: CUSUM+ (under-forecast) | AC8: CUSUM− (over-forecast) | AD8: Drift alarm | AE8: AI flags hot day | AF8: AI outcome | AG8: Reference station hot | AH8: Representation gap | AI8: Recommended control action | AK8: First trigger dates | AN8: T_Day line | AO8: Capacity line | AP8: CUSUM h line
A9: 1 | B9: =2+(SelYear-1979)*153+A9-1 -> 6581 | C9: =INDEX(Data_Heathrow!$A:$A,B9) -> 44682 | D9: =INDEX(Data_Heathrow!$E:$E,B9) -> 17.1 | E9: =INDEX(Data_Heathrow!$Q:$Q,B9) -> 0 | F9: =INDEX(Data_Heathrow!$T:$T,B9) | G9: =IF(AND(Drift_Rate<>0,A9>=Drift_Start),Drift_Rate*(A9-Drift_Start+1)/30,0) -> 0 | H9: =IF(AND(E9=1,QA_Policy="Exclude suspect"),"",IF(AND(E9=1,QA_Policy="Impute with model",ISNUMBER(F9)),F9,D9)+G9) -> 17.1 | I9: =IF(H9="","",H9+Climate_Shift+UHI_Day_Eff) -> 19.1 | J9: =INDEX(Data_Heathrow!$G:$G,B9) -> 10.4 | K9: =J9+Climate_Shift+UHI_Night_Eff -> 14.4 | L9: =IF(INDEX(Data_Heathrow!$I:$I,B9)="","",INDEX(Data_Heathrow!$I:$I,B9)) -> 12.5 | M9: =IF(L9="","",L9+Climate_Shift+(UHI_Day_Eff+UHI_Night_Eff)/2) -> 15.5 | N9: =IF(I9="",0,IF(I9>=T_Day,1,0)) -> 0 | O9: =IF(K9>=T_Night,1,0) -> 0 | P9: =IF(N9=1,1,0) -> 0 | Q9: =IF(P9>=HW_Days,1,0) -> 0 | R9: =IF(AND(N9=1,I9>=T_Red,O9=1),"RED",IF(AND(Q9=1,O9=1),"AMBER",IF(OR(N9=1,O9=1),"YELLOW","GREEN"))) -> GREEN | S9: =IF(R9="RED",3,IF(R9="AMBER",2,IF(R9="YELLOW",1,0))) -> 0 | T9: =MAX(0,0*(1-Decay)+IF(I9="",0,MAX(0,I9-T_Comfort))-Recovery_Rate*MAX(0,T_Night-K9)) -> 0 | U9: =IF(T9>Capacity,1,0) -> 0 | V9: =1/(1+EXP(-Logistic_k*(T9-Capacity))) -> 0.0024726232 | W9: =IF(M9="",0,Beta*Pop_Share_Sel*(1-Sens_Red)*MAX(0,M9-T_Mort)) -> 0 | X9: =IF(ISNUMBER(F9),F9+Coef_B1*(Climate_Shift+0),"") | Y9: =IF(AND(ISNUMBER(X9),H9<>""),H9+Climate_Shift-X9,"") | Z9: =IF(ISNUMBER(Y9),ABS(Y9),"") | AA9: =IF(COUNT(Z9:Z9)=0,"",AVERAGE(Z9:Z9)) | AB9: =IF(FALSE(),0,MAX(0,0+IF(ISNUMBER(Y9),Y9-CUSUM_k,0))) -> 0 | AC9: =IF(FALSE(),0,MAX(0,0+IF(ISNUMBER(Y9),-Y9-CUSUM_k,0))) -> 0 | AD9: =IF(OR(AB9>CUSUM_h,AC9>CUSUM_h,AND(ISNUMBER(AA9),AA9>MAE_Tol)),1,0) -> 0 | AE9: =IF(ISNUMBER(X9),IF(X9+Local_Sensing*UHI_Day_Eff>=T_Day,1,0),0) -> 0 | AF9: =IF(NOT(ISNUMBER(X9)),"n/a",IF(AND(AE9=1,N9=1),"Hit",IF(AND(AE9=0,N9=1),"Miss",IF(AND(AE9=1,N9=0),"False alarm","Correct quiet")))) -> n/a | AG9: =IF(H9="",0,IF(H9+Climate_Shift>=T_Day,1,0)) -> 0 | AH9: =IF(AND(N9=1,AG9=0),1,0) -> 0 | AI9: =IF(U9=1,"ESCALATE: surge health & transport capacity",IF(AD9=1,"Model drift: retrain, recalibrate, raise change request",IF(S9>=2,"Activate heat plan: outreach and cooling centres",IF(AND(E9=1,OR(N9=1,O9=1)),"Data QA: verify sensor before acting",IF(AF9="Miss","Review missed alert: threshold or model",IF(AH9=1,"Equity: local alert not seen at reference station","Monitor")))))) -> Monitor | AK9: First hot day | AL9: =IFERROR(INDEX($C$9:$C$161,MATCH(1,N9:N161,0)),"—") -> 44697 | AN9: =T_Day -> 28 | AO9: =Capacity -> 40 | AP9: =CUSUM_h -> 15
A10: 2 | B10: =2+(SelYear-1979)*153+A10-1 -> 6582 | C10: =INDEX(Data_Heathrow!$A:$A,B10) -> 44683 | D10: =INDEX(Data_Heathrow!$E:$E,B10) -> 16.1 | E10: =INDEX(Data_Heathrow!$Q:$Q,B10) -> 0 | F10: =INDEX(Data_Heathrow!$T:$T,B10) -> 18.201626 | G10: =IF(AND(Drift_Rate<>0,A10>=Drift_Start),Drift_Rate*(A10-Drift_Start+1)/30,0) -> 0 | H10: =IF(AND(E10=1,QA_Policy="Exclude suspect"),"",IF(AND(E10=1,QA_Policy="Impute with model",ISNUMBER(F10)),F10,D10)+G10) -> 16.1 | I10: =IF(H10="","",H10+Climate_Shift+UHI_Day_Eff) -> 18.1 | J10: =INDEX(Data_Heathrow!$G:$G,B10) -> 9 | K10: =J10+Climate_Shift+UHI_Night_Eff -> 13 | L10: =IF(INDEX(Data_Heathrow!$I:$I,B10)="","",INDEX(Data_Heathrow!$I:$I,B10)) -> 13.1 | M10: =IF(L10="","",L10+Climate_Shift+(UHI_Day_Eff+UHI_Night_Eff)/2) -> 16.1 | N10: =IF(I10="",0,IF(I10>=T_Day,1,0)) -> 0 | O10: =IF(K10>=T_Night,1,0) -> 0 | P10: =IF(N10=1,P9+1,0) -> 0 | Q10: =IF(P10>=HW_Days,1,0) -> 0 | R10: =IF(AND(N10=1,I10>=T_Red,O10=1),"RED",IF(AND(Q10=1,O10=1),"AMBER",IF(OR(N10=1,O10=1),"YELLOW","GREEN"))) -> GREEN | S10: =IF(R10="RED",3,IF(R10="AMBER",2,IF(R10="YELLOW",1,0))) -> 0 | T10: =MAX(0,T9*(1-Decay)+IF(I10="",0,MAX(0,I10-T_Comfort))-Recovery_Rate*MAX(0,T_Night-K10)) -> 0 | U10: =IF(T10>Capacity,1,0) -> 0 | V10: =1/(1+EXP(-Logistic_k*(T10-Capacity))) -> 0.0024726232 | W10: =IF(M10="",0,Beta*Pop_Share_Sel*(1-Sens_Red)*MAX(0,M10-T_Mort)) -> 0 | X10: =IF(ISNUMBER(F10),F10+Coef_B1*(Climate_Shift+G9),"") -> 18.201626 | Y10: =IF(AND(ISNUMBER(X10),H10<>""),H10+Climate_Shift-X10,"") -> -2.1016258 | Z10: =IF(ISNUMBER(Y10),ABS(Y10),"") -> 2.1016258 | AA10: =IF(COUNT(Z9:Z10)=0,"",AVERAGE(Z9:Z10)) -> 2.1016258 | AB10: =IF(AD9=1,0,MAX(0,AB9+IF(ISNUMBER(Y10),Y10-CUSUM_k,0))) -> 0 | AC10: =IF(AD9=1,0,MAX(0,AC9+IF(ISNUMBER(Y10),-Y10-CUSUM_k,0))) -> 1.1016258 | AD10: =IF(OR(AB10>CUSUM_h,AC10>CUSUM_h,AND(ISNUMBER(AA10),AA10>MAE_Tol)),1,0) -> 0 | AE10: =IF(ISNUMBER(X10),IF(X10+Local_Sensing*UHI_Day_Eff>=T_Day,1,0),0) -> 0 | AF10: =IF(NOT(ISNUMBER(X10)),"n/a",IF(AND(AE10=1,N10=1),"Hit",IF(AND(AE10=0,N10=1),"Miss",IF(AND(AE10=1,N10=0),"False alarm","Correct quiet")))) -> Correct quiet | AG10: =IF(H10="",0,IF(H10+Climate_Shift>=T_Day,1,0)) -> 0 | AH10: =IF(AND(N10=1,AG10=0),1,0) -> 0 | AI10: =IF(U10=1,"ESCALATE: surge health & transport capacity",IF(AD10=1,"Model drift: retrain, recalibrate, raise change request",IF(S10>=2,"Activate heat plan: outreach and cooling centres",IF(AND(E10=1,OR(N10=1,O10=1)),"Data QA: verify sensor before acting",IF(AF10="Miss","Review missed alert: threshold or model",IF(AH10=1,"Equity: local alert not seen at reference station","Monitor")))))) -> Monitor | AK10: First heatwave day | AL10: =IFERROR(INDEX($C$9:$C$161,MATCH(1,Q9:Q161,0)),"—") -> 44728 | AN10: =T_Day -> 28 | AO10: =Capacity -> 40 | AP10: =CUSUM_h -> 15
A11: 3 | B11: =2+(SelYear-1979)*153+A11-1 -> 6583 | C11: =INDEX(Data_Heathrow!$A:$A,B11) -> 44684 | D11: =INDEX(Data_Heathrow!$E:$E,B11) -> 20 | E11: =INDEX(Data_Heathrow!$Q:$Q,B11) -> 0 | F11: =INDEX(Data_Heathrow!$T:$T,B11) -> 17.310136 | G11: =IF(AND(Drift_Rate<>0,A11>=Drift_Start),Drift_Rate*(A11-Drift_Start+1)/30,0) -> 0 | H11: =IF(AND(E11=1,QA_Policy="Exclude suspect"),"",IF(AND(E11=1,QA_Policy="Impute with model",ISNUMBER(F11)),F11,D11)+G11) -> 20 | I11: =IF(H11="","",H11+Climate_Shift+UHI_Day_Eff) -> 22 | J11: =INDEX(Data_Heathrow!$G:$G,B11) -> 10.6 | K11: =J11+Climate_Shift+UHI_Night_Eff -> 14.6 | L11: =IF(INDEX(Data_Heathrow!$I:$I,B11)="","",INDEX(Data_Heathrow!$I:$I,B11)) -> 13.3 | M11: =IF(L11="","",L11+Climate_Shift+(UHI_Day_Eff+UHI_Night_Eff)/2) -> 16.3 | N11: =IF(I11="",0,IF(I11>=T_Day,1,0)) -> 0 | O11: =IF(K11>=T_Night,1,0) -> 0 | P11: =IF(N11=1,P10+1,0) -> 0 | Q11: =IF(P11>=HW_Days,1,0) -> 0 | R11: =IF(AND(N11=1,I11>=T_Red,O11=1),"RED",IF(AND(Q11=1,O11=1),"AMBER",IF(OR(N11=1,O11=1),"YELLOW","GREEN"))) -> GREEN | S11: =IF(R11="RED",3,IF(R11="AMBER",2,IF(R11="YELLOW",1,0))) -> 0 | T11: =MAX(0,T10*(1-Decay)+IF(I11="",0,MAX(0,I11-T_Comfort))-Recovery_Rate*MAX(0,T_Night-K11)) -> 0 | U11: =IF(T11>Capacity,1,0) -> 0 | V11: =1/(1+EXP(-Logistic_k*(T11-Capacity))) -> 0.0024726232 | W11: =IF(M11="",0,Beta*Pop_Share_Sel*(1-Sens_Red)*MAX(0,M11-T_Mort)) -> 0 | X11: =IF(ISNUMBER(F11),F11+Coef_B1*(Climate_Shift+G10),"") -> 17.310136 | Y11: =IF(AND(ISNUMBER(X11),H11<>""),H11+Climate_Shift-X11,"") -> 2.6898642 | Z11: =IF(ISNUMBER(Y11),ABS(Y11),"") -> 2.6898642 | AA11: =IF(COUNT(Z9:Z11)=0,"",AVERAGE(Z9:Z11)) -> 2.395745 | AB11: =IF(AD10=1,0,MAX(0,AB10+IF(ISNUMBER(Y11),Y11-CUSUM_k,0))) -> 1.6898642 | AC11: =IF(AD10=1,0,MAX(0,AC10+IF(ISNUMBER(Y11),-Y11-CUSUM_k,0))) -> 0 | AD11: =IF(OR(AB11>CUSUM_h,AC11>CUSUM_h,AND(ISNUMBER(AA11),AA11>MAE_Tol)),1,0) -> 0 | AE11: =IF(ISNUMBER(X11),IF(X11+Local_Sensing*UHI_Day_Eff>=T_Day,1,0),0) -> 0 | AF11: =IF(NOT(ISNUMBER(X11)),"n/a",IF(AND(AE11=1,N11=1),"Hit",IF(AND(AE11=0,N11=1),"Miss",IF(AND(AE11=1,N11=0),"False alarm","Correct quiet")))) -> Correct quiet | AG11: =IF(H11="",0,IF(H11+Climate_Shift>=T_Day,1,0)) -> 0 | AH11: =IF(AND(N11=1,AG11=0),1,0) -> 0 | AI11: =IF(U11=1,"ESCALATE: surge health & transport capacity",IF(AD11=1,"Model drift: retrain, recalibrate, raise change request",IF(S11>=2,"Activate heat plan: outreach and cooling centres",IF(AND(E11=1,OR(N11=1,O11=1)),"Data QA: verify sensor before acting",IF(AF11="Miss","Review missed alert: threshold or model",IF(AH11=1,"Equity: local alert not seen at reference station","Monitor")))))) -> Monitor | AK11: First tipping day | AL11: =IFERROR(INDEX($C$9:$C$161,MATCH(1,U9:U161,0)),"—") -> 44760 | AN11: =T_Day -> 28 | AO11: =Capacity -> 40 | AP11: =CUSUM_h -> 15
A12: 4 | B12: =2+(SelYear-1979)*153+A12-1 -> 6584 | C12: =INDEX(Data_Heathrow!$A:$A,B12) -> 44685 | D12: =INDEX(Data_Heathrow!$E:$E,B12) -> 19.9 | E12: =INDEX(Data_Heathrow!$Q:$Q,B12) -> 0 | F12: =INDEX(Data_Heathrow!$T:$T,B12) -> 20.505559 | G12: =IF(AND(Drift_Rate<>0,A12>=Drift_Start),Drift_Rate*(A12-Drift_Start+1)/30,0) -> 0 | H12: =IF(AND(E12=1,QA_Policy="Exclude suspect"),"",IF(AND(E12=1,QA_Policy="Impute with model",ISNUMBER(F12)),F12,D12)+G12) -> 19.9 | I12: =IF(H12="","",H12+Climate_Shift+UHI_Day_Eff) -> 21.9 | J12: =INDEX(Data_Heathrow!$G:$G,B12) -> 10.5 | K12: =J12+Climate_Shift+UHI_Night_Eff -> 14.5 | L12: =IF(INDEX(Data_Heathrow!$I:$I,B12)="","",INDEX(Data_Heathrow!$I:$I,B12)) -> 15.2 | M12: =IF(L12="","",L12+Climate_Shift+(UHI_Day_Eff+UHI_Night_Eff)/2) -> 18.2 | N12: =IF(I12="",0,IF(I12>=T_Day,1,0)) -> 0 | O12: =IF(K12>=T_Night,1,0) -> 0 | P12: =IF(N12=1,P11+1,0) -> 0 | Q12: =IF(P12>=HW_Days,1,0) -> 0 | R12: =IF(AND(N12=1,I12>=T_Red,O12=1),"RED",IF(AND(Q12=1,O12=1),"AMBER",IF(OR(N12=1,O12=1),"YELLOW","GREEN"))) -> GREEN | S12: =IF(R12="RED",3,IF(R12="AMBER",2,IF(R12="YELLOW",1,0))) -> 0 | T12: =MAX(0,T11*(1-Decay)+IF(I12="",0,MAX(0,I12-T_Comfort))-Recovery_Rate*MAX(0,T_Night-K12)) -> 0 | U12: =IF(T12>Capacity,1,0) -> 0 | V12: =1/(1+EXP(-Logistic_k*(T12-Capacity))) -> 0.0024726232 | W12: =IF(M12="",0,Beta*Pop_Share_Sel*(1-Sens_Red)*MAX(0,M12-T_Mort)) -> 0 | X12: =IF(ISNUMBER(F12),F12+Coef_B1*(Climate_Shift+G11),"") -> 20.505559 | Y12: =IF(AND(ISNUMBER(X12),H12<>""),H12+Climate_Shift-X12,"") -> -0.60555869 | Z12: =IF(ISNUMBER(Y12),ABS(Y12),"") -> 0.60555869 | AA12: =IF(COUNT(Z9:Z12)=0,"",AVERAGE(Z9:Z12)) -> 1.7990162 | AB12: =IF(AD11=1,0,MAX(0,AB11+IF(ISNUMBER(Y12),Y12-CUSUM_k,0))) -> 0.084305466 | AC12: =IF(AD11=1,0,MAX(0,AC11+IF(ISNUMBER(Y12),-Y12-CUSUM_k,0))) -> 0 | AD12: =IF(OR(AB12>CUSUM_h,AC12>CUSUM_h,AND(ISNUMBER(AA12),AA12>MAE_Tol)),1,0) -> 0 | AE12: =IF(ISNUMBER(X12),IF(X12+Local_Sensing*UHI_Day_Eff>=T_Day,1,0),0) -> 0 | AF12: =IF(NOT(ISNUMBER(X12)),"n/a",IF(AND(AE12=1,N12=1),"Hit",IF(AND(AE12=0,N12=1),"Miss",IF(AND(AE12=1,N12=0),"False alarm","Correct quiet")))) -> Correct quiet | AG12: =IF(H12="",0,IF(H12+Climate_Shift>=T_Day,1,0)) -> 0 | AH12: =IF(AND(N12=1,AG12=0),1,0) -> 0 | AI12: =IF(U12=1,"ESCALATE: surge health & transport capacity",IF(AD12=1,"Model drift: retrain, recalibrate, raise change request",IF(S12>=2,"Activate heat plan: outreach and cooling centres",IF(AND(E12=1,OR(N12=1,O12=1)),"Data QA: verify sensor before acting",IF(AF12="Miss","Review missed alert: threshold or model",IF(AH12=1,"Equity: local alert not seen at reference station","Monitor")))))) -> Monitor | AK12: First drift alarm | AL12: =IFERROR(INDEX($C$9:$C$161,MATCH(1,AD9:AD161,0)),"—") -> 44760 | AN12: =T_Day -> 28 | AO12: =Capacity -> 40 | AP12: =CUSUM_h -> 15
A13: 5 | B13: =2+(SelYear-1979)*153+A13-1 -> 6585 | C13: =INDEX(Data_Heathrow!$A:$A,B13) -> 44686 | D13: =INDEX(Data_Heathrow!$E:$E,B13) -> 23.3 | E13: =INDEX(Data_Heathrow!$Q:$Q,B13) -> 0 | F13: =INDEX(Data_Heathrow!$T:$T,B13) -> 20.367159 | G13: =IF(AND(Drift_Rate<>0,A13>=Drift_Start),Drift_Rate*(A13-Drift_Start+1)/30,0) -> 0 | H13: =IF(AND(E13=1,QA_Policy="Exclude suspect"),"",IF(AND(E13=1,QA_Policy="Impute with model",ISNUMBER(F13)),F13,D13)+G13) -> 23.3 | I13: =IF(H13="","",H13+Climate_Shift+UHI_Day_Eff) -> 25.3 | J13: =INDEX(Data_Heathrow!$G:$G,B13) -> 7.5 | K13: =J13+Climate_Shift+UHI_Night_Eff -> 11.5 | L13: =IF(INDEX(Data_Heathrow!$I:$I,B13)="","",INDEX(Data_Heathrow!$I:$I,B13)) -> 13.7 | M13: =IF(L13="","",L13+Climate_Shift+(UHI_Day_Eff+UHI_Night_Eff)/2) -> 16.7 | N13: =IF(I13="",0,IF(I13>=T_Day,1,0)) -> 0 | O13: =IF(K13>=T_Night,1,0) -> 0 | P13: =IF(N13=1,P12+1,0) -> 0 | Q13: =IF(P13>=HW_Days,1,0) -> 0 | R13: =IF(AND(N13=1,I13>=T_Red,O13=1),"RED",IF(AND(Q13=1,O13=1),"AMBER",IF(OR(N13=1,O13=1),"YELLOW","GREEN"))) -> GREEN | S13: =IF(R13="RED",3,IF(R13="AMBER",2,IF(R13="YELLOW",1,0))) -> 0 | T13: =MAX(0,T12*(1-Decay)+IF(I13="",0,MAX(0,I13-T_Comfort))-Recovery_Rate*MAX(0,T_Night-K13)) -> 0 | U13: =IF(T13>Capacity,1,0) -> 0 | V13: =1/(1+EXP(-Logistic_k*(T13-Capacity))) -> 0.0024726232 | W13: =IF(M13="",0,Beta*Pop_Share_Sel*(1-Sens_Red)*MAX(0,M13-T_Mort)) -> 0 | X13: =IF(ISNUMBER(F13),F13+Coef_B1*(Climate_Shift+G12),"") -> 20.367159 | Y13: =IF(AND(ISNUMBER(X13),H13<>""),H13+Climate_Shift-X13,"") -> 2.932841 | Z13: =IF(ISNUMBER(Y13),ABS(Y13),"") -> 2.932841 | AA13: =IF(COUNT(Z9:Z13)=0,"",AVERAGE(Z9:Z13)) -> 2.0824724 | AB13: =IF(AD12=1,0,MAX(0,AB12+IF(ISNUMBER(Y13),Y13-CUSUM_k,0))) -> 2.0171465 | AC13: =IF(AD12=1,0,MAX(0,AC12+IF(ISNUMBER(Y13),-Y13-CUSUM_k,0))) -> 0 | AD13: =IF(OR(AB13>CUSUM_h,AC13>CUSUM_h,AND(ISNUMBER(AA13),AA13>MAE_Tol)),1,0) -> 0 | AE13: =IF(ISNUMBER(X13),IF(X13+Local_Sensing*UHI_Day_Eff>=T_Day,1,0),0) -> 0 | AF13: =IF(NOT(ISNUMBER(X13)),"n/a",IF(AND(AE13=1,N13=1),"Hit",IF(AND(AE13=0,N13=1),"Miss",IF(AND(AE13=1,N13=0),"False alarm","Correct quiet")))) -> Correct quiet | AG13: =IF(H13="",0,IF(H13+Climate_Shift>=T_Day,1,0)) -> 0 | AH13: =IF(AND(N13=1,AG13=0),1,0) -> 0 | AI13: =IF(U13=1,"ESCALATE: surge health & transport capacity",IF(AD13=1,"Model drift: retrain, recalibrate, raise change request",IF(S13>=2,"Activate heat plan: outreach and cooling centres",IF(AND(E13=1,OR(N13=1,O13=1)),"Data QA: verify sensor before acting",IF(AF13="Miss","Review missed alert: threshold or model",IF(AH13=1,"Equity: local alert not seen at reference station","Monitor")))))) -> Monitor | AK13: First representation gap | AL13: =IFERROR(INDEX($C$9:$C$161,MATCH(1,AH9:AH161,0)),"—") -> 44697 | AN13: =T_Day -> 28 | AO13: =Capacity -> 40 | AP13: =CUSUM_h -> 15
A14: 6 | B14: =2+(SelYear-1979)*153+A14-1 -> 6586 | C14: =INDEX(Data_Heathrow!$A:$A,B14) -> 44687 | D14: =INDEX(Data_Heathrow!$E:$E,B14) -> 20.3 | E14: =INDEX(Data_Heathrow!$Q:$Q,B14) -> 0 | F14: =INDEX(Data_Heathrow!$T:$T,B14) -> 23.294077 | G14: =IF(AND(Drift_Rate<>0,A14>=Drift_Start),Drift_Rate*(A14-Drift_Start+1)/30,0) -> 0 | H14: =IF(AND(E14=1,QA_Policy="Exclude suspect"),"",IF(AND(E14=1,QA_Policy="Impute with model",ISNUMBER(F14)),F14,D14)+G14) -> 20.3 | I14: =IF(H14="","",H14+Climate_Shift+UHI_Day_Eff) -> 22.3 | J14: =INDEX(Data_Heathrow!$G:$G,B14) -> 9.2 | K14: =J14+Climate_Shift+UHI_Night_Eff -> 13.2 | L14: =IF(INDEX(Data_Heathrow!$I:$I,B14)="","",INDEX(Data_Heathrow!$I:$I,B14)) -> 16.2 | M14: =IF(L14="","",L14+Climate_Shift+(UHI_Day_Eff+UHI_Night_Eff)/2) -> 19.2 | N14: =IF(I14="",0,IF(I14>=T_Day,1,0)) -> 0 | O14: =IF(K14>=T_Night,1,0) -> 0 | P14: =IF(N14=1,P13+1,0) -> 0 | Q14: =IF(P14>=HW_Days,1,0) -> 0 | R14: =IF(AND(N14=1,I14>=T_Red,O14=1),"RED",IF(AND(Q14=1,O14=1),"AMBER",IF(OR(N14=1,O14=1),"YELLOW","GREEN"))) -> GREEN | S14: =IF(R14="RED",3,IF(R14="AMBER",2,IF(R14="YELLOW",1,0))) -> 0 | T14: =MAX(0,T13*(1-Decay)+IF(I14="",0,MAX(0,I14-T_Comfort))-Recovery_Rate*MAX(0,T_Night-K14)) -> 0 | U14: =IF(T14>Capacity,1,0) -> 0 | V14: =1/(1+EXP(-Logistic_k*(T14-Capacity))) -> 0.0024726232 | W14: =IF(M14="",0,Beta*Pop_Share_Sel*(1-Sens_Red)*MAX(0,M14-T_Mort)) -> 0 | X14: =IF(ISNUMBER(F14),F14+Coef_B1*(Climate_Shift+G13),"") -> 23.294077 | Y14: =IF(AND(ISNUMBER(X14),H14<>""),H14+Climate_Shift-X14,"") -> -2.9940767 | Z14: =IF(ISNUMBER(Y14),ABS(Y14),"") -> 2.9940767 | AA14: =IF(COUNT(Z9:Z14)=0,"",AVERAGE(Z9:Z14)) -> 2.2647933 | AB14: =IF(AD13=1,0,MAX(0,AB13+IF(ISNUMBER(Y14),Y14-CUSUM_k,0))) -> 0 | AC14: =IF(AD13=1,0,MAX(0,AC13+IF(ISNUMBER(Y14),-Y14-CUSUM_k,0))) -> 1.9940767 | AD14: =IF(OR(AB14>CUSUM_h,AC14>CUSUM_h,AND(ISNUMBER(AA14),AA14>MAE_Tol)),1,0) -> 0 | AE14: =IF(ISNUMBER(X14),IF(X14+Local_Sensing*UHI_Day_Eff>=T_Day,1,0),0) -> 0 | AF14: =IF(NOT(ISNUMBER(X14)),"n/a",IF(AND(AE14=1,N14=1),"Hit",IF(AND(AE14=0,N14=1),"Miss",IF(AND(AE14=1,N14=0),"False alarm","Correct quiet")))) -> Correct quiet | AG14: =IF(H14="",0,IF(H14+Climate_Shift>=T_Day,1,0)) -> 0 | AH14: =IF(AND(N14=1,AG14=0),1,0) -> 0 | AI14: =IF(U14=1,"ESCALATE: surge health & transport capacity",IF(AD14=1,"Model drift: retrain, recalibrate, raise change request",IF(S14>=2,"Activate heat plan: outreach and cooling centres",IF(AND(E14=1,OR(N14=1,O14=1)),"Data QA: verify sensor before acting",IF(AF14="Miss","Review missed alert: threshold or model",IF(AH14=1,"Equity: local alert not seen at reference station","Monitor")))))) -> Monitor | AN14: =T_Day -> 28 | AO14: =Capacity -> 40 | AP14: =CUSUM_h -> 15
A15: 7 | B15: =2+(SelYear-1979)*153+A15-1 -> 6587 | C15: =INDEX(Data_Heathrow!$A:$A,B15) -> 44688 | D15: =INDEX(Data_Heathrow!$E:$E,B15) -> 20.6 | E15: =INDEX(Data_Heathrow!$Q:$Q,B15) -> 0 | F15: =INDEX(Data_Heathrow!$T:$T,B15) -> 20.87684 | G15: =IF(AND(Drift_Rate<>0,A15>=Drift_Start),Drift_Rate*(A15-Drift_Start+1)/30,0) -> 0 | H15: =IF(AND(E15=1,QA_Policy="Exclude suspect"),"",IF(AND(E15=1,QA_Policy="Impute with model",ISNUMBER(F15)),F15,D15)+G15) -> 20.6 | I15: =IF(H15="","",H15+Climate_Shift+UHI_Day_Eff) -> 22.6 | J15: =INDEX(Data_Heathrow!$G:$G,B15) -> 12.4 | K15: =J15+Climate_Shift+UHI_Night_Eff -> 16.4 | L15: =IF(INDEX(Data_Heathrow!$I:$I,B15)="","",INDEX(Data_Heathrow!$I:$I,B15)) -> 16.4 | M15: =IF(L15="","",L15+Climate_Shift+(UHI_Day_Eff+UHI_Night_Eff)/2) -> 19.4 | N15: =IF(I15="",0,IF(I15>=T_Day,1,0)) -> 0 | O15: =IF(K15>=T_Night,1,0) -> 0 | P15: =IF(N15=1,P14+1,0) -> 0 | Q15: =IF(P15>=HW_Days,1,0) -> 0 | R15: =IF(AND(N15=1,I15>=T_Red,O15=1),"RED",IF(AND(Q15=1,O15=1),"AMBER",IF(OR(N15=1,O15=1),"YELLOW","GREEN"))) -> GREEN | S15: =IF(R15="RED",3,IF(R15="AMBER",2,IF(R15="YELLOW",1,0))) -> 0 | T15: =MAX(0,T14*(1-Decay)+IF(I15="",0,MAX(0,I15-T_Comfort))-Recovery_Rate*MAX(0,T_Night-K15)) -> 0 | U15: =IF(T15>Capacity,1,0) -> 0 | V15: =1/(1+EXP(-Logistic_k*(T15-Capacity))) -> 0.0024726232 | W15: =IF(M15="",0,Beta*Pop_Share_Sel*(1-Sens_Red)*MAX(0,M15-T_Mort)) -> 0 | X15: =IF(ISNUMBER(F15),F15+Coef_B1*(Climate_Shift+G14),"") -> 20.87684 | Y15: =IF(AND(ISNUMBER(X15),H15<>""),H15+Climate_Shift-X15,"") -> -0.27684003 | Z15: =IF(ISNUMBER(Y15),ABS(Y15),"") -> 0.27684003 | AA15: =IF(COUNT(Z9:Z15)=0,"",AVERAGE(Z9:Z15)) -> 1.9334677 | AB15: =IF(AD14=1,0,MAX(0,AB14+IF(ISNUMBER(Y15),Y15-CUSUM_k,0))) -> 0 | AC15: =IF(AD14=1,0,MAX(0,AC14+IF(ISNUMBER(Y15),-Y15-CUSUM_k,0))) -> 1.2709168 | AD15: =IF(OR(AB15>CUSUM_h,AC15>CUSUM_h,AND(ISNUMBER(AA15),AA15>MAE_Tol)),1,0) -> 0 | AE15: =IF(ISNUMBER(X15),IF(X15+Local_Sensing*UHI_Day_Eff>=T_Day,1,0),0) -> 0 | AF15: =IF(NOT(ISNUMBER(X15)),"n/a",IF(AND(AE15=1,N15=1),"Hit",IF(AND(AE15=0,N15=1),"Miss",IF(AND(AE15=1,N15=0),"False alarm","Correct quiet")))) -> Correct quiet | AG15: =IF(H15="",0,IF(H15+Climate_Shift>=T_Day,1,0)) -> 0 | AH15: =IF(AND(N15=1,AG15=0),1,0) -> 0 | AI15: =IF(U15=1,"ESCALATE: surge health & transport capacity",IF(AD15=1,"Model drift: retrain, recalibrate, raise change request",IF(S15>=2,"Activate heat plan: outreach and cooling centres",IF(AND(E15=1,OR(N15=1,O15=1)),"Data QA: verify sensor before acting",IF(AF15="Miss","Review missed alert: threshold or model",IF(AH15=1,"Equity: local alert not seen at reference station","Monitor")))))) -> Monitor | AN15: =T_Day -> 28 | AO15: =Capacity -> 40 | AP15: =CUSUM_h -> 15
A16: 8 | B16: =2+(SelYear-1979)*153+A16-1 -> 6588 | C16: =INDEX(Data_Heathrow!$A:$A,B16) -> 44689 | D16: =INDEX(Data_Heathrow!$E:$E,B16) -> 23.4 | E16: =INDEX(Data_Heathrow!$Q:$Q,B16) -> 0 | F16: =INDEX(Data_Heathrow!$T:$T,B16) -> 21.138327 | G16: =IF(AND(Drift_Rate<>0,A16>=Drift_Start),Drift_Rate*(A16-Drift_Start+1)/30,0) -> 0 | H16: =IF(AND(E16=1,QA_Policy="Exclude suspect"),"",IF(AND(E16=1,QA_Policy="Impute with model",ISNUMBER(F16)),F16,D16)+G16) -> 23.4 | I16: =IF(H16="","",H16+Climate_Shift+UHI_Day_Eff) -> 25.4 | J16: =INDEX(Data_Heathrow!$G:$G,B16) -> 9.6 | K16: =J16+Climate_Shift+UHI_Night_Eff -> 13.6 | L16: =IF(INDEX(Data_Heathrow!$I:$I,B16)="","",INDEX(Data_Heathrow!$I:$I,B16)) -> 15.1 | M16: =IF(L16="","",L16+Climate_Shift+(UHI_Day_Eff+UHI_Night_Eff)/2) -> 18.1 | N16: =IF(I16="",0,IF(I16>=T_Day,1,0)) -> 0 | O16: =IF(K16>=T_Night,1,0) -> 0 | P16: =IF(N16=1,P15+1,0) -> 0 | Q16: =IF(P16>=HW_Days,1,0) -> 0 | R16: =IF(AND(N16=1,I16>=T_Red,O16=1),"RED",IF(AND(Q16=1,O16=1),"AMBER",IF(OR(N16=1,O16=1),"YELLOW","GREEN"))) -> GREEN | S16: =IF(R16="RED",3,IF(R16="AMBER",2,IF(R16="YELLOW",1,0))) -> 0 | T16: =MAX(0,T15*(1-Decay)+IF(I16="",0,MAX(0,I16-T_Comfort))-Recovery_Rate*MAX(0,T_Night-K16)) -> 0 | U16: =IF(T16>Capacity,1,0) -> 0 | V16: =1/(1+EXP(-Logistic_k*(T16-Capacity))) -> 0.0024726232 | W16: =IF(M16="",0,Beta*Pop_Share_Sel*(1-Sens_Red)*MAX(0,M16-T_Mort)) -> 0 | X16: =IF(ISNUMBER(F16),F16+Coef_B1*(Climate_Shift+G15),"") -> 21.138327 | Y16: =IF(AND(ISNUMBER(X16),H16<>""),H16+Climate_Shift-X16,"") -> 2.2616733 | Z16: =IF(ISNUMBER(Y16),ABS(Y16),"") -> 2.2616733 | AA16: =IF(COUNT(Z10:Z16)=0,"",AVERAGE(Z10:Z16)) -> 1.9803542 | AB16: =IF(AD15=1,0,MAX(0,AB15+IF(ISNUMBER(Y16),Y16-CUSUM_k,0))) -> 1.2616733 | AC16: =IF(AD15=1,0,MAX(0,AC15+IF(ISNUMBER(Y16),-Y16-CUSUM_k,0))) -> 0 | AD16: =IF(OR(AB16>CUSUM_h,AC16>CUSUM_h,AND(ISNUMBER(AA16),AA16>MAE_Tol)),1,0) -> 0 | AE16: =IF(ISNUMBER(X16),IF(X16+Local_Sensing*UHI_Day_Eff>=T_Day,1,0),0) -> 0 | AF16: =IF(NOT(ISNUMBER(X16)),"n/a",IF(AND(AE16=1,N16=1),"Hit",IF(AND(AE16=0,N16=1),"Miss",IF(AND(AE16=1,N16=0),"False alarm","Correct quiet")))) -> Correct quiet | AG16: =IF(H16="",0,IF(H16+Climate_Shift>=T_Day,1,0)) -> 0 | AH16: =IF(AND(N16=1,AG16=0),1,0) -> 0 | AI16: =IF(U16=1,"ESCALATE: surge health & transport capacity",IF(AD16=1,"Model drift: retrain, recalibrate, raise change request",IF(S16>=2,"Activate heat plan: outreach and cooling centres",IF(AND(E16=1,OR(N16=1,O16=1)),"Data QA: verify sensor before acting",IF(AF16="Miss","Review missed alert: threshold or model",IF(AH16=1,"Equity: local alert not seen at reference station","Monitor")))))) -> Monitor | AN16: =T_Day -> 28 | AO16: =Capacity -> 40 | AP16: =CUSUM_h -> 15
A17: 9 | B17: =2+(SelYear-1979)*153+A17-1 -> 6589 | C17: =INDEX(Data_Heathrow!$A:$A,B17) -> 44690 | D17: =INDEX(Data_Heathrow!$E:$E,B17) -> 20.9 | E17: =INDEX(Data_Heathrow!$Q:$Q,B17) -> 0 | F17: =INDEX(Data_Heathrow!$T:$T,B17) -> 23.526586 | G17: =IF(AND(Drift_Rate<>0,A17>=Drift_Start),Drift_Rate*(A17-Drift_Start+1)/30,0) -> 0 | H17: =IF(AND(E17=1,QA_Policy="Exclude suspect"),"",IF(AND(E17=1,QA_Policy="Impute with model",ISNUMBER(F17)),F17,D17)+G17) -> 20.9 | I17: =IF(H17="","",H17+Climate_Shift+UHI_Day_Eff) -> 22.9 | J17: =INDEX(Data_Heathrow!$G:$G,B17) -> 6 | K17: =J17+Climate_Shift+UHI_Night_Eff -> 10 | L17: =IF(INDEX(Data_Heathrow!$I:$I,B17)="","",INDEX(Data_Heathrow!$I:$I,B17)) -> 14.7 | M17: =IF(L17="","",L17+Climate_Shift+(UHI_Day_Eff+UHI_Night_Eff)/2) -> 17.7 | N17: =IF(I17="",0,IF(I17>=T_Day,1,0)) -> 0 | O17: =IF(K17>=T_Night,1,0) -> 0 | P17: =IF(N17=1,P16+1,0) -> 0 | Q17: =IF(P17>=HW_Days,1,0) -> 0 | R17: =IF(AND(N17=1,I17>=T_Red,O17=1),"RED",IF(AND(Q17=1,O17=1),"AMBER",IF(OR(N17=1,O17=1),"YELLOW","GREEN"))) -> GREEN | S17: =IF(R17="RED",3,IF(R17="AMBER",2,IF(R17="YELLOW",1,0))) -> 0 | T17: =MAX(0,T16*(1-Decay)+IF(I17="",0,MAX(0,I17-T_Comfort))-Recovery_Rate*MAX(0,T_Night-K17)) -> 0 | U17: =IF(T17>Capacity,1,0) -> 0 | V17: =1/(1+EXP(-Logistic_k*(T17-Capacity))) -> 0.0024726232 | W17: =IF(M17="",0,Beta*Pop_Share_Sel*(1-Sens_Red)*MAX(0,M17-T_Mort)) -> 0 | X17: =IF(ISNUMBER(F17),F17+Coef_B1*(Climate_Shift+G16),"") -> 23.526586 | Y17: =IF(AND(ISNUMBER(X17),H17<>""),H17+Climate_Shift-X17,"") -> -2.6265862 | Z17: =IF(ISNUMBER(Y17),ABS(Y17),"") -> 2.6265862 | AA17: =IF(COUNT(Z11:Z17)=0,"",AVERAGE(Z11:Z17)) -> 2.0553486 | AB17: =IF(AD16=1,0,MAX(0,AB16+IF(ISNUMBER(Y17),Y17-CUSUM_k,0))) -> 0 | AC17: =IF(AD16=1,0,MAX(0,AC16+IF(ISNUMBER(Y17),-Y17-CUSUM_k,0))) -> 1.6265862 | AD17: =IF(OR(AB17>CUSUM_h,AC17>CUSUM_h,AND(ISNUMBER(AA17),AA17>MAE_Tol)),1,0) -> 0 | AE17: =IF(ISNUMBER(X17),IF(X17+Local_Sensing*UHI_Day_Eff>=T_Day,1,0),0) -> 0 | AF17: =IF(NOT(ISNUMBER(X17)),"n/a",IF(AND(AE17=1,N17=1),"Hit",IF(AND(AE17=0,N17=1),"Miss",IF(AND(AE17=1,N17=0),"False alarm","Correct quiet")))) -> Correct quiet | AG17: =IF(H17="",0,IF(H17+Climate_Shift>=T_Day,1,0)) -> 0 | AH17: =IF(AND(N17=1,AG17=0),1,0) -> 0 | AI17: =IF(U17=1,"ESCALATE: surge health & transport capacity",IF(AD17=1,"Model drift: retrain, recalibrate, raise change request",IF(S17>=2,"Activate heat plan: outreach and cooling centres",IF(AND(E17=1,OR(N17=1,O17=1)),"Data QA: verify sensor before acting",IF(AF17="Miss","Review missed alert: threshold or model",IF(AH17=1,"Equity: local alert not seen at reference station","Monitor")))))) -> Monitor | AN17: =T_Day -> 28 | AO17: =Capacity -> 40 | AP17: =CUSUM_h -> 15
A18: 10 | B18: =2+(SelYear-1979)*153+A18-1 -> 6590 | C18: =INDEX(Data_Heathrow!$A:$A,B18) -> 44691 | D18: =INDEX(Data_Heathrow!$E:$E,B18) -> 16.1 | E18: =INDEX(Data_Heathrow!$Q:$Q,B18) -> 1 | F18: =INDEX(Data_Heathrow!$T:$T,B18) -> 21.29943 | G18: =IF(AND(Drift_Rate<>0,A18>=Drift_Start),Drift_Rate*(A18-Drift_Start+1)/30,0) -> 0 | H18: =IF(AND(E18=1,QA_Policy="Exclude suspect"),"",IF(AND(E18=1,QA_Policy="Impute with model",ISNUMBER(F18)),F18,D18)+G18) -> 16.1 | I18: =IF(H18="","",H18+Climate_Shift+UHI_Day_Eff) -> 18.1 | J18: =INDEX(Data_Heathrow!$G:$G,B18) -> 13.4 | K18: =J18+Climate_Shift+UHI_Night_Eff -> 17.4 | L18: =IF(INDEX(Data_Heathrow!$I:$I,B18)="","",INDEX(Data_Heathrow!$I:$I,B18)) -> 17.1 | M18: =IF(L18="","",L18+Climate_Shift+(UHI_Day_Eff+UHI_Night_Eff)/2) -> 20.1 | N18: =IF(I18="",0,IF(I18>=T_Day,1,0)) -> 0 | O18: =IF(K18>=T_Night,1,0) -> 0 | P18: =IF(N18=1,P17+1,0) -> 0 | Q18: =IF(P18>=HW_Days,1,0) -> 0 | R18: =IF(AND(N18=1,I18>=T_Red,O18=1),"RED",IF(AND(Q18=1,O18=1),"AMBER",IF(OR(N18=1,O18=1),"YELLOW","GREEN"))) -> GREEN | S18: =IF(R18="RED",3,IF(R18="AMBER",2,IF(R18="YELLOW",1,0))) -> 0 | T18: =MAX(0,T17*(1-Decay)+IF(I18="",0,MAX(0,I18-T_Comfort))-Recovery_Rate*MAX(0,T_Night-K18)) -> 0 | U18: =IF(T18>Capacity,1,0) -> 0 | V18: =1/(1+EXP(-Logistic_k*(T18-Capacity))) -> 0.0024726232 | W18: =IF(M18="",0,Beta*Pop_Share_Sel*(1-Sens_Red)*MAX(0,M18-T_Mort)) -> 0.05553961 | X18: =IF(ISNUMBER(F18),F18+Coef_B1*(Climate_Shift+G17),"") -> 21.29943 | Y18: =IF(AND(ISNUMBER(X18),H18<>""),H18+Climate_Shift-X18,"") -> -5.1994298 | Z18: =IF(ISNUMBER(Y18),ABS(Y18),"") -> 5.1994298 | AA18: =IF(COUNT(Z12:Z18)=0,"",AVERAGE(Z12:Z18)) -> 2.413858 | AB18: =IF(AD17=1,0,MAX(0,AB17+IF(ISNUMBER(Y18),Y18-CUSUM_k,0))) -> 0 | AC18: =IF(AD17=1,0,MAX(0,AC17+IF(ISNUMBER(Y18),-Y18-CUSUM_k,0))) -> 5.8260159 | AD18: =IF(OR(AB18>CUSUM_h,AC18>CUSUM_h,AND(ISNUMBER(AA18),AA18>MAE_Tol)),1,0) -> 0 | AE18: =IF(ISNUMBER(X18),IF(X18+Local_Sensing*UHI_Day_Eff>=T_Day,1,0),0) -> 0 | AF18: =IF(NOT(ISNUMBER(X18)),"n/a",IF(AND(AE18=1,N18=1),"Hit",IF(AND(AE18=0,N18=1),"Miss",IF(AND(AE18=1,N18=0),"False alarm","Correct quiet")))) -> Correct quiet | AG18: =IF(H18="",0,IF(H18+Climate_Shift>=T_Day,1,0)) -> 0 | AH18: =IF(AND(N18=1,AG18=0),1,0) -> 0 | AI18: =IF(U18=1,"ESCALATE: surge health & transport capacity",IF(AD18=1,"Model drift: retrain, recalibrate, raise change request",IF(S18>=2,"Activate heat plan: outreach and cooling centres",IF(AND(E18=1,OR(N18=1,O18=1)),"Data QA: verify sensor before acting",IF(AF18="Miss","Review missed alert: threshold or model",IF(AH18=1,"Equity: local alert not seen at reference station","Monitor")))))) -> Monitor | AN18: =T_Day -> 28 | AO18: =Capacity -> 40 | AP18: =CUSUM_h -> 15
A19: 11 | B19: =2+(SelYear-1979)*153+A19-1 -> 6591 | C19: =INDEX(Data_Heathrow!$A:$A,B19) -> 44692 | D19: =INDEX(Data_Heathrow!$E:$E,B19) -> 18.9 | E19: =INDEX(Data_Heathrow!$Q:$Q,B19) -> 0 | F19: =INDEX(Data_Heathrow!$T:$T,B19) -> 17.112506 | G19: =IF(AND(Drift_Rate<>0,A19>=Drift_Start),Drift_Rate*(A19-Drift_Start+1)/30,0) -> 0 | H19: =IF(AND(E19=1,QA_Policy="Exclude suspect"),"",IF(AND(E19=1,QA_Policy="Impute with model",ISNUMBER(F19)),F19,D19)+G19) -> 18.9 | I19: =IF(H19="","",H19+Climate_Shift+UHI_Day_Eff) -> 20.9 | J19: =INDEX(Data_Heathrow!$G:$G,B19) -> 11.7 | K19: =J19+Climate_Shift+UHI_Night_Eff -> 15.7 | L19: =IF(INDEX(Data_Heathrow!$I:$I,B19)="","",INDEX(Data_Heathrow!$I:$I,B19)) -> 13.9 | M19: =IF(L19="","",L19+Climate_Shift+(UHI_Day_Eff+UHI_Night_Eff)/2) -> 16.9 | N19: =IF(I19="",0,IF(I19>=T_Day,1,0)) -> 0 | O19: =IF(K19>=T_Night,1,0) -> 0 | P19: =IF(N19=1,P18+1,0) -> 0 | Q19: =IF(P19>=HW_Days,1,0) -> 0 | R19: =IF(AND(N19=1,I19>=T_Red,O19=1),"RED",IF(AND(Q19=1,O19=1),"AMBER",IF(OR(N19=1,O19=1),"YELLOW","GREEN"))) -> GREEN | S19: =IF(R19="RED",3,IF(R19="AMBER",2,IF(R19="YELLOW",1,0))) -> 0 | T19: =MAX(0,T18*(1-Decay)+IF(I19="",0,MAX(0,I19-T_Comfort))-Recovery_Rate*MAX(0,T_Night-K19)) -> 0 | U19: =IF(T19>Capacity,1,0) -> 0 | V19: =1/(1+EXP(-Logistic_k*(T19-Capacity))) -> 0.0024726232 | W19: =IF(M19="",0,Beta*Pop_Share_Sel*(1-Sens_Red)*MAX(0,M19-T_Mort)) -> 0 | X19: =IF(ISNUMBER(F19),F19+Coef_B1*(Climate_Shift+G18),"") -> 17.112506 | Y19: =IF(AND(ISNUMBER(X19),H19<>""),H19+Climate_Shift-X19,"") -> 1.7874945 | Z19: =IF(ISNUMBER(Y19),ABS(Y19),"") -> 1.7874945 | AA19: =IF(COUNT(Z13:Z19)=0,"",AVERAGE(Z13:Z19)) -> 2.5827059 | AB19: =IF(AD18=1,0,MAX(0,AB18+IF(ISNUMBER(Y19),Y19-CUSUM_k,0))) -> 0.7874945 | AC19: =IF(AD18=1,0,MAX(0,AC18+IF(ISNUMBER(Y19),-Y19-CUSUM_k,0))) -> 3.0385214 | AD19: =IF(OR(AB19>CUSUM_h,AC19>CUSUM_h,AND(ISNUMBER(AA19),AA19>MAE_Tol)),1,0) -> 0 | AE19: =IF(ISNUMBER(X19),IF(X19+Local_Sensing*UHI_Day_Eff>=T_Day,1,0),0) -> 0 | AF19: =IF(NOT(ISNUMBER(X19)),"n/a",IF(AND(AE19=1,N19=1),"Hit",IF(AND(AE19=0,N19=1),"Miss",IF(AND(AE19=1,N19=0),"False alarm","Correct quiet")))) -> Correct quiet | AG19: =IF(H19="",0,IF(H19+Climate_Shift>=T_Day,1,0)) -> 0 | AH19: =IF(AND(N19=1,AG19=0),1,0) -> 0 | AI19: =IF(U19=1,"ESCALATE: surge health & transport capacity",IF(AD19=1,"Model drift: retrain, recalibrate, raise change request",IF(S19>=2,"Activate heat plan: outreach and cooling centres",IF(AND(E19=1,OR(N19=1,O19=1)),"Data QA: verify sensor before acting",IF(AF19="Miss","Review missed alert: threshold or model",IF(AH19=1,"Equity: local alert not seen at reference station","Monitor")))))) -> Monitor | AN19: =T_Day -> 28 | AO19: =Capacity -> 40 | AP19: =CUSUM_h -> 15
A20: 12 | B20: =2+(SelYear-1979)*153+A20-1 -> 6592 | C20: =INDEX(Data_Heathrow!$A:$A,B20) -> 44693 | D20: =INDEX(Data_Heathrow!$E:$E,B20) -> 21.4 | E20: =INDEX(Data_Heathrow!$Q:$Q,B20) -> 0 | F20: =INDEX(Data_Heathrow!$T:$T,B20) -> 19.271765 | G20: =IF(AND(Drift_Rate<>0,A20>=Drift_Start),Drift_Rate*(A20-Drift_Start+1)/30,0) -> 0 | H20: =IF(AND(E20=1,QA_Policy="Exclude suspect"),"",IF(AND(E20=1,QA_Policy="Impute with model",ISNUMBER(F20)),F20,D20)+G20) -> 21.4 | I20: =IF(H20="","",H20+Climate_Shift+UHI_Day_Eff) -> 23.4 | J20: =INDEX(Data_Heathrow!$G:$G,B20) -> 7 | K20: =J20+Climate_Shift+UHI_Night_Eff -> 11 | L20: =IF(INDEX(Data_Heathrow!$I:$I,B20)="","",INDEX(Data_Heathrow!$I:$I,B20)) -> 12.9 | M20: =IF(L20="","",L20+Climate_Shift+(UHI_Day_Eff+UHI_Night_Eff)/2) -> 15.9 | N20: =IF(I20="",0,IF(I20>=T_Day,1,0)) -> 0 | O20: =IF(K20>=T_Night,1,0) -> 0 | P20: =IF(N20=1,P19+1,0) -> 0 | Q20: =IF(P20>=HW_Days,1,0) -> 0 | R20: =IF(AND(N20=1,I20>=T_Red,O20=1),"RED",IF(AND(Q20=1,O20=1),"AMBER",IF(OR(N20=1,O20=1),"YELLOW","GREEN"))) -> GREEN | S20: =IF(R20="RED",3,IF(R20="AMBER",2,IF(R20="YELLOW",1,0))) -> 0 | T20: =MAX(0,T19*(1-Decay)+IF(I20="",0,MAX(0,I20-T_Comfort))-Recovery_Rate*MAX(0,T_Night-K20)) -> 0 | U20: =IF(T20>Capacity,1,0) -> 0 | V20: =1/(1+EXP(-Logistic_k*(T20-Capacity))) -> 0.0024726232 | W20: =IF(M20="",0,Beta*Pop_Share_Sel*(1-Sens_Red)*MAX(0,M20-T_Mort)) -> 0 | X20: =IF(ISNUMBER(F20),F20+Coef_B1*(Climate_Shift+G19),"") -> 19.271765 | Y20: =IF(AND(ISNUMBER(X20),H20<>""),H20+Climate_Shift-X20,"") -> 2.1282353 | Z20: =IF(ISNUMBER(Y20),ABS(Y20),"") -> 2.1282353 | AA20: =IF(COUNT(Z14:Z20)=0,"",AVERAGE(Z14:Z20)) -> 2.4677623 | AB20: =IF(AD19=1,0,MAX(0,AB19+IF(ISNUMBER(Y20),Y20-CUSUM_k,0))) -> 1.9157298 | AC20: =IF(AD19=1,0,MAX(0,AC19+IF(ISNUMBER(Y20),-Y20-CUSUM_k,0))) -> 0 | AD20: =IF(OR(AB20>CUSUM_h,AC20>CUSUM_h,AND(ISNUMBER(AA20),AA20>MAE_Tol)),1,0) -> 0 | AE20: =IF(ISNUMBER(X20),IF(X20+Local_Sensing*UHI_Day_Eff>=T_Day,1,0),0) -> 0 | AF20: =IF(NOT(ISNUMBER(X20)),"n/a",IF(AND(AE20=1,N20=1),"Hit",IF(AND(AE20=0,N20=1),"Miss",IF(AND(AE20=1,N20=0),"False alarm","Correct quiet")))) -> Correct quiet | AG20: =IF(H20="",0,IF(H20+Climate_Shift>=T_Day,1,0)) -> 0 | AH20: =IF(AND(N20=1,AG20=0),1,0) -> 0 | AI20: =IF(U20=1,"ESCALATE: surge health & transport capacity",IF(AD20=1,"Model drift: retrain, recalibrate, raise change request",IF(S20>=2,"Activate heat plan: outreach and cooling centres",IF(AND(E20=1,OR(N20=1,O20=1)),"Data QA: verify sensor before acting",IF(AF20="Miss","Review missed alert: threshold or model",IF(AH20=1,"Equity: local alert not seen at reference station","Monitor")))))) -> Monitor | AN20: =T_Day -> 28 | AO20: =Capacity -> 40 | AP20: =CUSUM_h -> 15
A21: 13 | B21: =2+(SelYear-1979)*153+A21-1 -> 6593 | C21: =INDEX(Data_Heathrow!$A:$A,B21) -> 44694 | D21: =INDEX(Data_Heathrow!$E:$E,B21) -> 23.4 | E21: =INDEX(Data_Heathrow!$Q:$Q,B21) -> 0 | F21: =INDEX(Data_Heathrow!$T:$T,B21) -> 21.564798 | G21: =IF(AND(Drift_Rate<>0,A21>=Drift_Start),Drift_Rate*(A21-Drift_Start+1)/30,0) -> 0 | H21: =IF(AND(E21=1,QA_Policy="Exclude suspect"),"",IF(AND(E21=1,QA_Policy="Impute with model",ISNUMBER(F21)),F21,D21)+G21) -> 23.4 | I21: =IF(H21="","",H21+Climate_Shift+UHI_Day_Eff) -> 25.4 | J21: =INDEX(Data_Heathrow!$G:$G,B21) -> 10.1 | K21: =J21+Climate_Shift+UHI_Night_Eff -> 14.1 | L21: =IF(INDEX(Data_Heathrow!$I:$I,B21)="","",INDEX(Data_Heathrow!$I:$I,B21)) -> 15.8 | M21: =IF(L21="","",L21+Climate_Shift+(UHI_Day_Eff+UHI_Night_Eff)/2) -> 18.8 | N21: =IF(I21="",0,IF(I21>=T_Day,1,0)) -> 0 | O21: =IF(K21>=T_Night,1,0) -> 0 | P21: =IF(N21=1,P20+1,0) -> 0 | Q21: =IF(P21>=HW_Days,1,0) -> 0 | R21: =IF(AND(N21=1,I21>=T_Red,O21=1),"RED",IF(AND(Q21=1,O21=1),"AMBER",IF(OR(N21=1,O21=1),"YELLOW","GREEN"))) -> GREEN | S21: =IF(R21="RED",3,IF(R21="AMBER",2,IF(R21="YELLOW",1,0))) -> 0 | T21: =MAX(0,T20*(1-Decay)+IF(I21="",0,MAX(0,I21-T_Comfort))-Recovery_Rate*MAX(0,T_Night-K21)) -> 0 | U21: =IF(T21>Capacity,1,0) -> 0 | V21: =1/(1+EXP(-Logistic_k*(T21-Capacity))) -> 0.0024726232 | W21: =IF(M21="",0,Beta*Pop_Share_Sel*(1-Sens_Red)*MAX(0,M21-T_Mort)) -> 0 | X21: =IF(ISNUMBER(F21),F21+Coef_B1*(Climate_Shift+G20),"") -> 21.564798 | Y21: =IF(AND(ISNUMBER(X21),H21<>""),H21+Climate_Shift-X21,"") -> 1.8352021 | Z21: =IF(ISNUMBER(Y21),ABS(Y21),"") -> 1.8352021 | AA21: =IF(COUNT(Z15:Z21)=0,"",AVERAGE(Z15:Z21)) -> 2.3022087 | AB21: =IF(AD20=1,0,MAX(0,AB20+IF(ISNUMBER(Y21),Y21-CUSUM_k,0))) -> 2.7509319 | AC21: =IF(AD20=1,0,MAX(0,AC20+IF(ISNUMBER(Y21),-Y21-CUSUM_k,0))) -> 0 | AD21: =IF(OR(AB21>CUSUM_h,AC21>CUSUM_h,AND(ISNUMBER(AA21),AA21>MAE_Tol)),1,0) -> 0 | AE21: =IF(ISNUMBER(X21),IF(X21+Local_Sensing*UHI_Day_Eff>=T_Day,1,0),0) -> 0 | AF21: =IF(NOT(ISNUMBER(X21)),"n/a",IF(AND(AE21=1,N21=1),"Hit",IF(AND(AE21=0,N21=1),"Miss",IF(AND(AE21=1,N21=0),"False alarm","Correct quiet")))) -> Correct quiet | AG21: =IF(H21="",0,IF(H21+Climate_Shift>=T_Day,1,0)) -> 0 | AH21: =IF(AND(N21=1,AG21=0),1,0) -> 0 | AI21: =IF(U21=1,"ESCALATE: surge health & transport capacity",IF(AD21=1,"Model drift: retrain, recalibrate, raise change request",IF(S21>=2,"Activate heat plan: outreach and cooling centres",IF(AND(E21=1,OR(N21=1,O21=1)),"Data QA: verify sensor before acting",IF(AF21="Miss","Review missed alert: threshold or model",IF(AH21=1,"Equity: local alert not seen at reference station","Monitor")))))) -> Monitor | AN21: =T_Day -> 28 | AO21: =Capacity -> 40 | AP21: =CUSUM_h -> 15
A22: 14 | B22: =2+(SelYear-1979)*153+A22-1 -> 6594 | C22: =INDEX(Data_Heathrow!$A:$A,B22) -> 44695 | D22: =INDEX(Data_Heathrow!$E:$E,B22) -> 18.9 | E22: =INDEX(Data_Heathrow!$Q:$Q,B22) -> 0 | F22: =INDEX(Data_Heathrow!$T:$T,B22) -> 23.253668 | G22: =IF(AND(Drift_Rate<>0,A22>=Drift_Start),Drift_Rate*(A22-Drift_Start+1)/30,0) -> 0 | H22: =IF(AND(E22=1,QA_Policy="Exclude suspect"),"",IF(AND(E22=1,QA_Policy="Impute with model",ISNUMBER(F22)),F22,D22)+G22) -> 18.9 | I22: =IF(H22="","",H22+Climate_Shift+UHI_Day_Eff) -> 20.9 | J22: =INDEX(Data_Heathrow!$G:$G,B22) -> 7.8 | K22: =J22+Climate_Shift+UHI_Night_Eff -> 11.8 | L22: =IF(INDEX(Data_Heathrow!$I:$I,B22)="","",INDEX(Data_Heathrow!$I:$I,B22)) -> 15.6 | M22: =IF(L22="","",L22+Climate_Shift+(UHI_Day_Eff+UHI_Night_Eff)/2) -> 18.6 | N22: =IF(I22="",0,IF(I22>=T_Day,1,0)) -> 0 | O22: =IF(K22>=T_Night,1,0) -> 0 | P22: =IF(N22=1,P21+1,0) -> 0 | Q22: =IF(P22>=HW_Days,1,0) -> 0 | R22: =IF(AND(N22=1,I22>=T_Red,O22=1),"RED",IF(AND(Q22=1,O22=1),"AMBER",IF(OR(N22=1,O22=1),"YELLOW","GREEN"))) -> GREEN | S22: =IF(R22="RED",3,IF(R22="AMBER",2,IF(R22="YELLOW",1,0))) -> 0 | T22: =MAX(0,T21*(1-Decay)+IF(I22="",0,MAX(0,I22-T_Comfort))-Recovery_Rate*MAX(0,T_Night-K22)) -> 0 | U22: =IF(T22>Capacity,1,0) -> 0 | V22: =1/(1+EXP(-Logistic_k*(T22-Capacity))) -> 0.0024726232 | W22: =IF(M22="",0,Beta*Pop_Share_Sel*(1-Sens_Red)*MAX(0,M22-T_Mort)) -> 0 | X22: =IF(ISNUMBER(F22),F22+Coef_B1*(Climate_Shift+G21),"") -> 23.253668 | Y22: =IF(AND(ISNUMBER(X22),H22<>""),H22+Climate_Shift-X22,"") -> -4.3536681 | Z22: =IF(ISNUMBER(Y22),ABS(Y22),"") -> 4.3536681 | AA22: =IF(COUNT(Z16:Z22)=0,"",AVERAGE(Z16:Z22)) -> 2.8846127 | AB22: =IF(AD21=1,0,MAX(0,AB21+IF(ISNUMBER(Y22),Y22-CUSUM_k,0))) -> 0 | AC22: =IF(AD21=1,0,MAX(0,AC21+IF(ISNUMBER(Y22),-Y22-CUSUM_k,0))) -> 3.3536681 | AD22: =IF(OR(AB22>CUSUM_h,AC22>CUSUM_h,AND(ISNUMBER(AA22),AA22>MAE_Tol)),1,0) -> 0 | AE22: =IF(ISNUMBER(X22),IF(X22+Local_Sensing*UHI_Day_Eff>=T_Day,1,0),0) -> 0 | AF22: =IF(NOT(ISNUMBER(X22)),"n/a",IF(AND(AE22=1,N22=1),"Hit",IF(AND(AE22=0,N22=1),"Miss",IF(AND(AE22=1,N22=0),"False alarm","Correct quiet")))) -> Correct quiet | AG22: =IF(H22="",0,IF(H22+Climate_Shift>=T_Day,1,0)) -> 0 | AH22: =IF(AND(N22=1,AG22=0),1,0) -> 0 | AI22: =IF(U22=1,"ESCALATE: surge health & transport capacity",IF(AD22=1,"Model drift: retrain, recalibrate, raise change request",IF(S22>=2,"Activate heat plan: outreach and cooling centres",IF(AND(E22=1,OR(N22=1,O22=1)),"Data QA: verify sensor before acting",IF(AF22="Miss","Review missed alert: threshold or model",IF(AH22=1,"Equity: local alert not seen at reference station","Monitor")))))) -> Monitor | AN22: =T_Day -> 28 | AO22: =Capacity -> 40 | AP22: =CUSUM_h -> 15
A23: 15 | B23: =2+(SelYear-1979)*153+A23-1 -> 6595 | C23: =INDEX(Data_Heathrow!$A:$A,B23) -> 44696 | D23: =INDEX(Data_Heathrow!$E:$E,B23) -> 23.1 | E23: =INDEX(Data_Heathrow!$Q:$Q,B23) -> 0 | F23: =INDEX(Data_Heathrow!$T:$T,B23) -> 19.591738 | G23: =IF(AND(Drift_Rate<>0,A23>=Drift_Start),Drift_Rate*(A23-Drift_Start+1)/30,0) -> 0 | H23: =IF(AND(E23=1,QA_Policy="Exclude suspect"),"",IF(AND(E23=1,QA_Policy="Impute with model",ISNUMBER(F23)),F23,D23)+G23) -> 23.1 | I23: =IF(H23="","",H23+Climate_Shift+UHI_Day_Eff) -> 25.1 | J23: =INDEX(Data_Heathrow!$G:$G,B23) -> 12.9 | K23: =J23+Climate_Shift+UHI_Night_Eff -> 16.9 | L23: =IF(INDEX(Data_Heathrow!$I:$I,B23)="","",INDEX(Data_Heathrow!$I:$I,B23)) -> 15.9 | M23: =IF(L23="","",L23+Climate_Shift+(UHI_Day_Eff+UHI_Night_Eff)/2) -> 18.9 | N23: =IF(I23="",0,IF(I23>=T_Day,1,0)) -> 0 | O23: =IF(K23>=T_Night,1,0) -> 0 | P23: =IF(N23=1,P22+1,0) -> 0 | Q23: =IF(P23>=HW_Days,1,0) -> 0 | R23: =IF(AND(N23=1,I23>=T_Red,O23=1),"RED",IF(AND(Q23=1,O23=1),"AMBER",IF(OR(N23=1,O23=1),"YELLOW","GREEN"))) -> GREEN | S23: =IF(R23="RED",3,IF(R23="AMBER",2,IF(R23="YELLOW",1,0))) -> 0 | T23: =MAX(0,T22*(1-Decay)+IF(I23="",0,MAX(0,I23-T_Comfort))-Recovery_Rate*MAX(0,T_Night-K23)) -> 0 | U23: =IF(T23>Capacity,1,0) -> 0 | V23: =1/(1+EXP(-Logistic_k*(T23-Capacity))) -> 0.0024726232 | W23: =IF(M23="",0,Beta*Pop_Share_Sel*(1-Sens_Red)*MAX(0,M23-T_Mort)) -> 0 | X23: =IF(ISNUMBER(F23),F23+Coef_B1*(Climate_Shift+G22),"") -> 19.591738 | Y23: =IF(AND(ISNUMBER(X23),H23<>""),H23+Climate_Shift-X23,"") -> 3.5082624 | Z23: =IF(ISNUMBER(Y23),ABS(Y23),"") -> 3.5082624 | AA23: =IF(COUNT(Z17:Z23)=0,"",AVERAGE(Z17:Z23)) -> 3.0626969 | AB23: =IF(AD22=1,0,MAX(0,AB22+IF(ISNUMBER(Y23),Y23-CUSUM_k,0))) -> 2.5082624 | AC23: =IF(AD22=1,0,MAX(0,AC22+IF(ISNUMBER(Y23),-Y23-CUSUM_k,0))) -> 0 | AD23: =IF(OR(AB23>CUSUM_h,AC23>CUSUM_h,AND(ISNUMBER(AA23),AA23>MAE_Tol)),1,0) -> 0 | AE23: =IF(ISNUMBER(X23),IF(X23+Local_Sensing*UHI_Day_Eff>=T_Day,1,0),0) -> 0 | AF23: =IF(NOT(ISNUMBER(X23)),"n/a",IF(AND(AE23=1,N23=1),"Hit",IF(AND(AE23=0,N23=1),"Miss",IF(AND(AE23=1,N23=0),"False alarm","Correct quiet")))) -> Correct quiet | AG23: =IF(H23="",0,IF(H23+Climate_Shift>=T_Day,1,0)) -> 0 | AH23: =IF(AND(N23=1,AG23=0),1,0) -> 0 | AI23: =IF(U23=1,"ESCALATE: surge health & transport capacity",IF(AD23=1,"Model drift: retrain, recalibrate, raise change request",IF(S23>=2,"Activate heat plan: outreach and cooling centres",IF(AND(E23=1,OR(N23=1,O23=1)),"Data QA: verify sensor before acting",IF(AF23="Miss","Review missed alert: threshold or model",IF(AH23=1,"Equity: local alert not seen at reference station","Monitor")))))) -> Monitor | AN23: =T_Day -> 28 | AO23: =Capacity -> 40 | AP23: =CUSUM_h -> 15
A24: 16 | B24: =2+(SelYear-1979)*153+A24-1 -> 6596 | C24: =INDEX(Data_Heathrow!$A:$A,B24) -> 44697 | D24: =INDEX(Data_Heathrow!$E:$E,B24) -> 27.5 | E24: =INDEX(Data_Heathrow!$Q:$Q,B24) -> 0 | F24: =INDEX(Data_Heathrow!$T:$T,B24) -> 22.857291 | G24: =IF(AND(Drift_Rate<>0,A24>=Drift_Start),Drift_Rate*(A24-Drift_Start+1)/30,0) -> 0 | H24: =IF(AND(E24=1,QA_Policy="Exclude suspect"),"",IF(AND(E24=1,QA_Policy="Impute with model",ISNUMBER(F24)),F24,D24)+G24) -> 27.5 | I24: =IF(H24="","",H24+Climate_Shift+UHI_Day_Eff) -> 29.5 | J24: =INDEX(Data_Heathrow!$G:$G,B24) -> 12.2 | K24: =J24+Climate_Shift+UHI_Night_Eff -> 16.2 | L24: =IF(INDEX(Data_Heathrow!$I:$I,B24)="","",INDEX(Data_Heathrow!$I:$I,B24)) -> 17.6 | M24: =IF(L24="","",L24+Climate_Shift+(UHI_Day_Eff+UHI_Night_Eff)/2) -> 20.6 | N24: =IF(I24="",0,IF(I24>=T_Day,1,0)) -> 1 | O24: =IF(K24>=T_Night,1,0) -> 0 | P24: =IF(N24=1,P23+1,0) -> 1 | Q24: =IF(P24>=HW_Days,1,0) -> 0 | R24: =IF(AND(N24=1,I24>=T_Red,O24=1),"RED",IF(AND(Q24=1,O24=1),"AMBER",IF(OR(N24=1,O24=1),"YELLOW","GREEN"))) -> YELLOW | S24: =IF(R24="RED",3,IF(R24="AMBER",2,IF(R24="YELLOW",1,0))) -> 1 | T24: =MAX(0,T23*(1-Decay)+IF(I24="",0,MAX(0,I24-T_Comfort))-Recovery_Rate*MAX(0,T_Night-K24)) -> 3.6 | U24: =IF(T24>Capacity,1,0) -> 0 | V24: =1/(1+EXP(-Logistic_k*(T24-Capacity))) -> 0.0042355396 | W24: =IF(M24="",0,Beta*Pop_Share_Sel*(1-Sens_Red)*MAX(0,M24-T_Mort)) -> 0.33323766 | X24: =IF(ISNUMBER(F24),F24+Coef_B1*(Climate_Shift+G23),"") -> 22.857291 | Y24: =IF(AND(ISNUMBER(X24),H24<>""),H24+Climate_Shift-X24,"") -> 4.6427092 | Z24: =IF(ISNUMBER(Y24),ABS(Y24),"") -> 4.6427092 | AA24: =IF(COUNT(Z18:Z24)=0,"",AVERAGE(Z18:Z24)) -> 3.3507145 | AB24: =IF(AD23=1,0,MAX(0,AB23+IF(ISNUMBER(Y24),Y24-CUSUM_k,0))) -> 6.1509716 | AC24: =IF(AD23=1,0,MAX(0,AC23+IF(ISNUMBER(Y24),-Y24-CUSUM_k,0))) -> 0 | AD24: =IF(OR(AB24>CUSUM_h,AC24>CUSUM_h,AND(ISNUMBER(AA24),AA24>MAE_Tol)),1,0) -> 0 | AE24: =IF(ISNUMBER(X24),IF(X24+Local_Sensing*UHI_Day_Eff>=T_Day,1,0),0) -> 0 | AF24: =IF(NOT(ISNUMBER(X24)),"n/a",IF(AND(AE24=1,N24=1),"Hit",IF(AND(AE24=0,N24=1),"Miss",IF(AND(AE24=1,N24=0),"False alarm","Correct quiet")))) -> Miss | AG24: =IF(H24="",0,IF(H24+Climate_Shift>=T_Day,1,0)) -> 0 | AH24: =IF(AND(N24=1,AG24=0),1,0) -> 1 | AI24: =IF(U24=1,"ESCALATE: surge health & transport capacity",IF(AD24=1,"Model drift: retrain, recalibrate, raise change request",IF(S24>=2,"Activate heat plan: outreach and cooling centres",IF(AND(E24=1,OR(N24=1,O24=1)),"Data QA: verify sensor before acting",IF(AF24="Miss","Review missed alert: threshold or model",IF(AH24=1,"Equity: local alert not seen at reference station","Monitor")))))) -> Review missed alert: threshold or model | AN24: =T_Day -> 28 | AO24: =Capacity -> 40 | AP24: =CUSUM_h -> 15
A25: 17 | B25: =2+(SelYear-1979)*153+A25-1 -> 6597 | C25: =INDEX(Data_Heathrow!$A:$A,B25) -> 44698 | D25: =INDEX(Data_Heathrow!$E:$E,B25) -> 23.1 | E25: =INDEX(Data_Heathrow!$Q:$Q,B25) -> 0 | F25: =INDEX(Data_Heathrow!$T:$T,B25) -> 26.440424 | G25: =IF(AND(Drift_Rate<>0,A25>=Drift_Start),Drift_Rate*(A25-Drift_Start+1)/30,0) -> 0 | H25: =IF(AND(E25=1,QA_Policy="Exclude suspect"),"",IF(AND(E25=1,QA_Policy="Impute with model",ISNUMBER(F25)),F25,D25)+G25) -> 23.1 | I25: =IF(H25="","",H25+Climate_Shift+UHI_Day_Eff) -> 25.1 | J25: =INDEX(Data_Heathrow!$G:$G,B25) -> 10.9 | K25: =J25+Climate_Shift+UHI_Night_Eff -> 14.9 | L25: =IF(INDEX(Data_Heathrow!$I:$I,B25)="","",INDEX(Data_Heathrow!$I:$I,B25)) -> 19.2 | M25: =IF(L25="","",L25+Climate_Shift+(UHI_Day_Eff+UHI_Night_Eff)/2) -> 22.2 | N25: =IF(I25="",0,IF(I25>=T_Day,1,0)) -> 0 | O25: =IF(K25>=T_Night,1,0) -> 0 | P25: =IF(N25=1,P24+1,0) -> 0 | Q25: =IF(P25>=HW_Days,1,0) -> 0 | R25: =IF(AND(N25=1,I25>=T_Red,O25=1),"RED",IF(AND(Q25=1,O25=1),"AMBER",IF(OR(N25=1,O25=1),"YELLOW","GREEN"))) -> GREEN | S25: =IF(R25="RED",3,IF(R25="AMBER",2,IF(R25="YELLOW",1,0))) -> 0 | T25: =MAX(0,T24*(1-Decay)+IF(I25="",0,MAX(0,I25-T_Comfort))-Recovery_Rate*MAX(0,T_Night-K25)) -> 1.43 | U25: =IF(T25>Capacity,1,0) -> 0 | V25: =1/(1+EXP(-Logistic_k*(T25-Capacity))) -> 0.0030623672 | W25: =IF(M25="",0,Beta*Pop_Share_Sel*(1-Sens_Red)*MAX(0,M25-T_Mort)) -> 1.2218714 | X25: =IF(ISNUMBER(F25),F25+Coef_B1*(Climate_Shift+G24),"") -> 26.440424 | Y25: =IF(AND(ISNUMBER(X25),H25<>""),H25+Climate_Shift-X25,"") -> -3.3404243 | Z25: =IF(ISNUMBER(Y25),ABS(Y25),"") -> 3.3404243 | AA25: =IF(COUNT(Z19:Z25)=0,"",AVERAGE(Z19:Z25)) -> 3.0851423 | AB25: =IF(AD24=1,0,MAX(0,AB24+IF(ISNUMBER(Y25),Y25-CUSUM_k,0))) -> 1.8105472 | AC25: =IF(AD24=1,0,MAX(0,AC24+IF(ISNUMBER(Y25),-Y25-CUSUM_k,0))) -> 2.3404243 | AD25: =IF(OR(AB25>CUSUM_h,AC25>CUSUM_h,AND(ISNUMBER(AA25),AA25>MAE_Tol)),1,0) -> 0 | AE25: =IF(ISNUMBER(X25),IF(X25+Local_Sensing*UHI_Day_Eff>=T_Day,1,0),0) -> 0 | AF25: =IF(NOT(ISNUMBER(X25)),"n/a",IF(AND(AE25=1,N25=1),"Hit",IF(AND(AE25=0,N25=1),"Miss",IF(AND(AE25=1,N25=0),"False alarm","Correct quiet")))) -> Correct quiet | AG25: =IF(H25="",0,IF(H25+Climate_Shift>=T_Day,1,0)) -> 0 | AH25: =IF(AND(N25=1,AG25=0),1,0) -> 0 | AI25: =IF(U25=1,"ESCALATE: surge health & transport capacity",IF(AD25=1,"Model drift: retrain, recalibrate, raise change request",IF(S25>=2,"Activate heat plan: outreach and cooling centres",IF(AND(E25=1,OR(N25=1,O25=1)),"Data QA: verify sensor before acting",IF(AF25="Miss","Review missed alert: threshold or model",IF(AH25=1,"Equity: local alert not seen at reference station","Monitor")))))) -> Monitor | AN25: =T_Day -> 28 | AO25: =Capacity -> 40 | AP25: =CUSUM_h -> 15
A26: 18 | B26: =2+(SelYear-1979)*153+A26-1 -> 6598 | C26: =INDEX(Data_Heathrow!$A:$A,B26) -> 44699 | D26: =INDEX(Data_Heathrow!$E:$E,B26) -> 22.4 | E26: =INDEX(Data_Heathrow!$Q:$Q,B26) -> 0 | F26: =INDEX(Data_Heathrow!$T:$T,B26) -> 22.920031 | G26: =IF(AND(Drift_Rate<>0,A26>=Drift_Start),Drift_Rate*(A26-Drift_Start+1)/30,0) -> 0 | H26: =IF(AND(E26=1,QA_Policy="Exclude suspect"),"",IF(AND(E26=1,QA_Policy="Impute with model",ISNUMBER(F26)),F26,D26)+G26) -> 22.4 | I26: =IF(H26="","",H26+Climate_Shift+UHI_Day_Eff) -> 24.4 | J26: =INDEX(Data_Heathrow!$G:$G,B26) -> 11.1 | K26: =J26+Climate_Shift+UHI_Night_Eff -> 15.1 | L26: =IF(INDEX(Data_Heathrow!$I:$I,B26)="","",INDEX(Data_Heathrow!$I:$I,B26)) -> 17.1 | M26: =IF(L26="","",L26+Climate_Shift+(UHI_Day_Eff+UHI_Night_Eff)/2) -> 20.1 | N26: =IF(I26="",0,IF(I26>=T_Day,1,0)) -> 0 | O26: =IF(K26>=T_Night,1,0) -> 0 | P26: =IF(N26=1,P25+1,0) -> 0 | Q26: =IF(P26>=HW_Days,1,0) -> 0 | R26: =IF(AND(N26=1,I26>=T_Red,O26=1),"RED",IF(AND(Q26=1,O26=1),"AMBER",IF(OR(N26=1,O26=1),"YELLOW","GREEN"))) -> GREEN | S26: =IF(R26="RED",3,IF(R26="AMBER",2,IF(R26="YELLOW",1,0))) -> 0 | T26: =MAX(0,T25*(1-Decay)+IF(I26="",0,MAX(0,I26-T_Comfort))-Recovery_Rate*MAX(0,T_Night-K26)) -> 0 | U26: =IF(T26>Capacity,1,0) -> 0 | V26: =1/(1+EXP(-Logistic_k*(T26-Capacity))) -> 0.0024726232 | W26: =IF(M26="",0,Beta*Pop_Share_Sel*(1-Sens_Red)*MAX(0,M26-T_Mort)) -> 0.05553961 | X26: =IF(ISNUMBER(F26),F26+Coef_B1*(Climate_Shift+G25),"") -> 22.920031 | Y26: =IF(AND(ISNUMBER(X26),H26<>""),H26+Climate_Shift-X26,"") -> -0.52003061 | Z26: =IF(ISNUMBER(Y26),ABS(Y26),"") -> 0.52003061 | AA26: =IF(COUNT(Z20:Z26)=0,"",AVERAGE(Z20:Z26)) -> 2.904076 | AB26: =IF(AD25=1,0,MAX(0,AB25+IF(ISNUMBER(Y26),Y26-CUSUM_k,0))) -> 0.29051659 | AC26: =IF(AD25=1,0,MAX(0,AC25+IF(ISNUMBER(Y26),-Y26-CUSUM_k,0))) -> 1.860455 | AD26: =IF(OR(AB26>CUSUM_h,AC26>CUSUM_h,AND(ISNUMBER(AA26),AA26>MAE_Tol)),1,0) -> 0 | AE26: =IF(ISNUMBER(X26),IF(X26+Local_Sensing*UHI_Day_Eff>=T_Day,1,0),0) -> 0 | AF26: =IF(NOT(ISNUMBER(X26)),"n/a",IF(AND(AE26=1,N26=1),"Hit",IF(AND(AE26=0,N26=1),"Miss",IF(AND(AE26=1,N26=0),"False alarm","Correct quiet")))) -> Correct quiet | AG26: =IF(H26="",0,IF(H26+Climate_Shift>=T_Day,1,0)) -> 0 | AH26: =IF(AND(N26=1,AG26=0),1,0) -> 0 | AI26: =IF(U26=1,"ESCALATE: surge health & transport capacity",IF(AD26=1,"Model drift: retrain, recalibrate, raise change request",IF(S26>=2,"Activate heat plan: outreach and cooling centres",IF(AND(E26=1,OR(N26=1,O26=1)),"Data QA: verify sensor before acting",IF(AF26="Miss","Review missed alert: threshold or model",IF(AH26=1,"Equity: local alert not seen at reference station","Monitor")))))) -> Monitor | AN26: =T_Day -> 28 | AO26: =Capacity -> 40 | AP26: =CUSUM_h -> 15
... A161: 153 | B161: =2+(SelYear-1979)*153+A161-1 -> 6733 | C161: =INDEX(Data_Heathrow!$A:$A,B161) -> 44834 | D161: =INDEX(Data_Heathrow!$E:$E,B161) -> 19.4 | E161: =INDEX(Data_Heathrow!$Q:$Q,B161) -> 0 | F161: =INDEX(Data_Heathrow!$T:$T,B161) -> 17.268451 | G161: =IF(AND(Drift_Rate<>0,A161>=Drift_Start),Drift_Rate*(A161-Drift_Start+1)/30,0) -> 0 | H161: =IF(AND(E161=1,QA_Policy="Exclude suspect"),"",IF(AND(E161=1,QA_Policy="Impute with model",ISNUMBER(F161)),F161,D161)+G161) -> 19.4 | I161: =IF(H161="","",H161+Climate_Shift+UHI_Day_Eff) -> 21.4 | J161: =INDEX(Data_Heathrow!$G:$G,B161) -> 7.4 | K161: =J161+Climate_Shift+UHI_Night_Eff -> 11.4 | L161: =IF(INDEX(Data_Heathrow!$I:$I,B161)="","",INDEX(Data_Heathrow!$I:$I,B161)) -> 12.1 | M161: =IF(L161="","",L161+Climate_Shift+(UHI_Day_Eff+UHI_Night_Eff)/2) -> 15.1 | N161: =IF(I161="",0,IF(I161>=T_Day,1,0)) -> 0 | O161: =IF(K161>=T_Night,1,0) -> 0 | P161: =IF(N161=1,P160+1,0) -> 0 | Q161: =IF(P161>=HW_Days,1,0) -> 0 | R161: =IF(AND(N161=1,I161>=T_Red,O161=1),"RED",IF(AND(Q161=1,O161=1),"AMBER",IF(OR(N161=1,O161=1),"YELLOW","GREEN"))) -> GREEN | S161: =IF(R161="RED",3,IF(R161="AMBER",2,IF(R161="YELLOW",1,0))) -> 0 | T161: =MAX(0,T160*(1-Decay)+IF(I161="",0,MAX(0,I161-T_Comfort))-Recovery_Rate*MAX(0,T_Night-K161)) -> 0 | U161: =IF(T161>Capacity,1,0) -> 0 | V161: =1/(1+EXP(-Logistic_k*(T161-Capacity))) -> 0.0024726232 | W161: =IF(M161="",0,Beta*Pop_Share_Sel*(1-Sens_Red)*MAX(0,M161-T_Mort)) -> 0 | X161: =IF(ISNUMBER(F161),F161+Coef_B1*(Climate_Shift+G160),"") -> 17.268451 | Y161: =IF(AND(ISNUMBER(X161),H161<>""),H161+Climate_Shift-X161,"") -> 2.1315489 | Z161: =IF(ISNUMBER(Y161),ABS(Y161),"") -> 2.1315489 | AA161: =IF(COUNT(Z155:Z161)=0,"",AVERAGE(Z155:Z161)) -> 1.4557344 | AB161: =IF(AD160=1,0,MAX(0,AB160+IF(ISNUMBER(Y161),Y161-CUSUM_k,0))) -> 1.1315489 | AC161: =IF(AD160=1,0,MAX(0,AC160+IF(ISNUMBER(Y161),-Y161-CUSUM_k,0))) -> 0 | AD161: =IF(OR(AB161>CUSUM_h,AC161>CUSUM_h,AND(ISNUMBER(AA161),AA161>MAE_Tol)),1,0) -> 0 | AE161: =IF(ISNUMBER(X161),IF(X161+Local_Sensing*UHI_Day_Eff>=T_Day,1,0),0) -> 0 | AF161: =IF(NOT(ISNUMBER(X161)),"n/a",IF(AND(AE161=1,N161=1),"Hit",IF(AND(AE161=0,N161=1),"Miss",IF(AND(AE161=1,N161=0),"False alarm","Correct quiet")))) -> Correct quiet | AG161: =IF(H161="",0,IF(H161+Climate_Shift>=T_Day,1,0)) -> 0 | AH161: =IF(AND(N161=1,AG161=0),1,0) -> 0 | AI161: =IF(U161=1,"ESCALATE: surge health & transport capacity",IF(AD161=1,"Model drift: retrain, recalibrate, raise change request",IF(S161>=2,"Activate heat plan: outreach and cooling centres",IF(AND(E161=1,OR(N161=1,O161=1)),"Data QA: verify sensor before acting",IF(AF161="Miss","Review missed alert: threshold or model",IF(AH161=1,"Equity: local alert not seen at reference station","Monitor")))))) -> Monitor | AN161: =T_Day -> 28 | AO161: =Capacity -> 40 | AP161: =CUSUM_h -> 15

Sheet AI_Model
A1: AI_Model — next-day maximum-temperature forecaster and its training window
A2: Ordinary least squares, solved transparently from masked sums over Data_Heathrow. Model: TX(t) = a + b1·TX(t−1) + b2·PP(t−1). Change the training window on the Control Panel.
B4: Training window
B5: Effective training start | C5: =Train_Start -> 1979 | D5: Retraining governance (Optimise) can override the manual window.
B6: Effective training end | C6: =Train_End -> 1998
B7: Rolling retraining active? (1 = yes) | C7: =Retrain_On -> 0 | D7: Set on Optimise (MLOps lever) with scenario 'With interventions'.
B8: n (training days) | C8: =SUM(Data_Heathrow!$S$2:$S$6886) -> 2789 | D8: Valid days only: suspect values and gaps excluded.
B9: Masked sums
B10: Σx1 (TX prev) | C10: =SUMPRODUCT(Data_Heathrow!$S$2:$S$6886,Data_Heathrow!$O$2:$O$6886) -> 58016.5
B11: Σx2 (PP prev) | C11: =SUMPRODUCT(Data_Heathrow!$S$2:$S$6886,Data_Heathrow!$P$2:$P$6886) -> 2834406.5
B12: Σy (TX) | C12: =SUMPRODUCT(Data_Heathrow!$S$2:$S$6886,Data_Heathrow!$E$2:$E$6886) -> 58600.8
B13: Σx1² | C13: =SUMPRODUCT(Data_Heathrow!$S$2:$S$6886,Data_Heathrow!$O$2:$O$6886,Data_Heathrow!$O$2:$O$6886) -> 1254904.3
B14: Σx2² | C14: =SUMPRODUCT(Data_Heathrow!$S$2:$S$6886,Data_Heathrow!$P$2:$P$6886,Data_Heathrow!$P$2:$P$6886) -> 2.8807082e+09
B15: Σx1x2 | C15: =SUMPRODUCT(Data_Heathrow!$S$2:$S$6886,Data_Heathrow!$O$2:$O$6886,Data_Heathrow!$P$2:$P$6886) -> 58991740
B16: Σx1y | C16: =SUMPRODUCT(Data_Heathrow!$S$2:$S$6886,Data_Heathrow!$O$2:$O$6886,Data_Heathrow!$E$2:$E$6886) -> 1259340.9
B17: Σx2y | C17: =SUMPRODUCT(Data_Heathrow!$S$2:$S$6886,Data_Heathrow!$P$2:$P$6886,Data_Heathrow!$E$2:$E$6886) -> 59584900
B18: Centred moments
B19: mean x1 | C19: =C10/C8 -> 20.8019
B20: mean x2 | C20: =C11/C8 -> 1016.2806
B21: mean y | C21: =C12/C8 -> 21.011402
B22: var x1 | C22: =C13/C8-C19^2 -> 17.228698
B23: var x2 | C23: =C14/C8-C20^2 -> 55.934086
B24: cov x1x2 | C24: =C15/C8-C19*C20 -> 11.006928
B25: cov x1y | C25: =C16/C8-C19*C21 -> 14.461434
B26: cov x2y | C26: =C17/C8-C20*C21 -> 10.773054
B27: determinant | C27: =C22*C23-C24^2 -> 842.51903
B28: Coefficients
B29: b1 — persistence (TX prev) | C29: =(C23*C25-C24*C26)/C27 -> 0.81933919 | D29: How much of yesterday's heat carries over.
B30: b2 — pressure (PP prev) | C30: =(C22*C26-C24*C25)/C27 -> 0.031369895 | D30: Positive = high pressure (heat-dome blocking) raises tomorrow's max.
B31: a — intercept | C31: =C21-C29*C19-C30*C20 -> -27.913025
B33: Model performance (from Annual_Trend and Monitor_Control)
B34: Mean residual inside training window (°C) | C34: =IFERROR(SUMPRODUCT(Data_Heathrow!$S$2:$S$6886,Data_Heathrow!$U$2:$U$6886)/C8,0) -> 3.2482682e-17 | D34: ≈ 0 by construction.
B35: Mean residual, selected year (°C) | C35: =IFERROR(AVERAGEIFS(Data_Heathrow!$U$2:$U$6886,Data_Heathrow!$B$2:$B$6886,SelYear),"n/a") -> 0.53542114 | D35: Positive = model under-forecasts (under-warns).
B36: MAE, selected year (°C) | C36: =IFERROR(AVERAGEIFS(Data_Heathrow!$W$2:$W$6886,Data_Heathrow!$B$2:$B$6886,SelYear),"n/a") -> 1.8812407
B37: MAE on hot days, selected year (°C) | C37: =IFERROR(AVERAGEIFS(Data_Heathrow!$W$2:$W$6886,Data_Heathrow!$B$2:$B$6886,SelYear,Data_Heathrow!$E$2:$E$6886,">="&T_Day),"n/a") -> 2.8776196 | D37: Error where it matters most — at the threshold.
B38: Training data leaks the test year? (1 = yes) | C38: =IF(AND(SelYear>=Train_Start,SelYear<=Train_End),1,0) -> 0 | D38: If 1, performance is optimistic — a classic MLOps pitfall.
B40: Discussion: a model with excellent average error can still fail at the tail (heat-dome onset), and a model trained on a cooler past drifts as the climate shifts. Monitoring must watch both bias (CUSUM) and tail error. Note: because the model uses yesterday's reading, it partly follows a slowly drifting sensor — residual monitoring alone can miss data drift. An independent reference (second station, satellite) is needed.

Sheet Tipping_Points
A1: Tipping_Points — thresholds, non-linearity and where the system flips
A2: Sweeps recompute the selected year and typology at many settings at once. Look for the knee of each curve: small changes in input, large changes in outcome.
B4: 1. Threshold sweep — how alert design changes hot-day counts and AI recall | H4: 2. Climate-shift sweep — non-linear growth of harm
B5: Hot-day threshold °C | C5: Hot days | D5: AI hits | E5: Actual (model-valid) | F5: AI recall | H5: Climate shift °C | I5: Hot days (area) | J5: London excess deaths
B6: 24 | C6: =COUNTIFS(Data_Heathrow!$B$2:$B$6886,SelYear,Data_Heathrow!$E$2:$E$6886,">="&(B6-Climate_Shift-UHI_Day_Eff)) -> 102 | D6: =SUMPRODUCT((Data_Heathrow!$B$2:$B$6886=SelYear)*(Data_Heathrow!$R$2:$R$6886=1)*((Data_Heathrow!$E$2:$E$6886+Climate_Shift+UHI_Day_Eff)>=B6)*((Data_Heathrow!$V$2:$V$6886+Coef_B1*Climate_Shift+Local_Sensing*UHI_Day_Eff)>=B6)) -> 52 | E6: =SUMPRODUCT((Data_Heathrow!$B$2:$B$6886=SelYear)*(Data_Heathrow!$R$2:$R$6886=1)*((Data_Heathrow!$E$2:$E$6886+Climate_Shift+UHI_Day_Eff)>=B6)) -> 95 | F6: =IF(E6=0,"n/a",D6/E6) -> 0.54736842 | H6: 0 | I6: =COUNTIFS(Data_Heathrow!$B$2:$B$6886,SelYear,Data_Heathrow!$E$2:$E$6886,">="&(T_Day-H6-UHI_Day_Eff)) -> 41 | J6: =Beta*(1-Sens_Red)*(Equity_Lens!$E$6*SUMPRODUCT((Data_Heathrow!$B$2:$B$6886=SelYear)*(Data_Heathrow!$I$2:$I$6886<>"")*((Data_Heathrow!$I$2:$I$6886+H6+(Equity_Lens!$F$6+Equity_Lens!$G$6)/2-T_Mort)>0)*(Data_Heathrow!$I$2:$I$6886+H6+(Equity_Lens!$F$6+Equity_Lens!$G$6)/2-T_Mort))+Equity_Lens!$E$7*SUMPRODUCT((Data_Heathrow!$B$2:$B$6886=SelYear)*(Data_Heathrow!$I$2:$I$6886<>"")*((Data_Heathrow!$I$2:$I$6886+H6+(Equity_Lens!$F$7+Equity_Lens!$G$7)/2-T_Mort)>0)*(Data_Heathrow!$I$2:$I$6886+H6+(Equity_Lens!$F$7+Equity_Lens!$G$7)/2-T_Mort))+Equity_Lens!$E$8*SUMPRODUCT((Data_Heathrow!$B$2:$B$6886=SelYear)*(Data_Heathrow!$I$2:$I$6886<>"")*((Data_Heathrow!$I$2:$I$6886+H6+(Equity_Lens!$F$8+Equity_Lens!$G$8)/2-T_Mort)>0)*(Data_Heathrow!$I$2:$I$6886+H6+(Equity_Lens!$F$8+Equity_Lens!$G$8)/2-T_Mort))+Equity_Lens!$E$9*SUMPRODUCT((Data_Heathrow!$B$2:$B$6886=SelYear)*(Data_Heathrow!$I$2:$I$6886<>"")*((Data_Heathrow!$I$2:$I$6886+H6+(Equity_Lens!$F$9+Equity_Lens!$G$9)/2-T_Mort)>0)*(Data_Heathrow!$I$2:$I$6886+H6+(Equity_Lens!$F$9+Equity_Lens!$G$9)/2-T_Mort))) -> 387
B7: 25 | C7: =COUNTIFS(Data_Heathrow!$B$2:$B$6886,SelYear,Data_Heathrow!$E$2:$E$6886,">="&(B7-Climate_Shift-UHI_Day_Eff)) -> 83 | D7: =SUMPRODUCT((Data_Heathrow!$B$2:$B$6886=SelYear)*(Data_Heathrow!$R$2:$R$6886=1)*((Data_Heathrow!$E$2:$E$6886+Climate_Shift+UHI_Day_Eff)>=B7)*((Data_Heathrow!$V$2:$V$6886+Coef_B1*Climate_Shift+Local_Sensing*UHI_Day_Eff)>=B7)) -> 35 | E7: =SUMPRODUCT((Data_Heathrow!$B$2:$B$6886=SelYear)*(Data_Heathrow!$R$2:$R$6886=1)*((Data_Heathrow!$E$2:$E$6886+Climate_Shift+UHI_Day_Eff)>=B7)) -> 78 | F7: =IF(E7=0,"n/a",D7/E7) -> 0.44871795 | H7: 0.5 | I7: =COUNTIFS(Data_Heathrow!$B$2:$B$6886,SelYear,Data_Heathrow!$E$2:$E$6886,">="&(T_Day-H7-UHI_Day_Eff)) -> 42 | J7: =Beta*(1-Sens_Red)*(Equity_Lens!$E$6*SUMPRODUCT((Data_Heathrow!$B$2:$B$6886=SelYear)*(Data_Heathrow!$I$2:$I$6886<>"")*((Data_Heathrow!$I$2:$I$6886+H7+(Equity_Lens!$F$6+Equity_Lens!$G$6)/2-T_Mort)>0)*(Data_Heathrow!$I$2:$I$6886+H7+(Equity_Lens!$F$6+Equity_Lens!$G$6)/2-T_Mort))+Equity_Lens!$E$7*SUMPRODUCT((Data_Heathrow!$B$2:$B$6886=SelYear)*(Data_Heathrow!$I$2:$I$6886<>"")*((Data_Heathrow!$I$2:$I$6886+H7+(Equity_Lens!$F$7+Equity_Lens!$G$7)/2-T_Mort)>0)*(Data_Heathrow!$I$2:$I$6886+H7+(Equity_Lens!$F$7+Equity_Lens!$G$7)/2-T_Mort))+Equity_Lens!$E$8*SUMPRODUCT((Data_Heathrow!$B$2:$B$6886=SelYear)*(Data_Heathrow!$I$2:$I$6886<>"")*((Data_Heathrow!$I$2:$I$6886+H7+(Equity_Lens!$F$8+Equity_Lens!$G$8)/2-T_Mort)>0)*(Data_Heathrow!$I$2:$I$6886+H7+(Equity_Lens!$F$8+Equity_Lens!$G$8)/2-T_Mort))+Equity_Lens!$E$9*SUMPRODUCT((Data_Heathrow!$B$2:$B$6886=SelYear)*(Data_Heathrow!$I$2:$I$6886<>"")*((Data_Heathrow!$I$2:$I$6886+H7+(Equity_Lens!$F$9+Equity_Lens!$G$9)/2-T_Mort)>0)*(Data_Heathrow!$I$2:$I$6886+H7+(Equity_Lens!$F$9+Equity_Lens!$G$9)/2-T_Mort))) -> 454.01317
B8: 26 | C8: =COUNTIFS(Data_Heathrow!$B$2:$B$6886,SelYear,Data_Heathrow!$E$2:$E$6886,">="&(B8-Climate_Shift-UHI_Day_Eff)) -> 63 | D8: =SUMPRODUCT((Data_Heathrow!$B$2:$B$6886=SelYear)*(Data_Heathrow!$R$2:$R$6886=1)*((Data_Heathrow!$E$2:$E$6886+Climate_Shift+UHI_Day_Eff)>=B8)*((Data_Heathrow!$V$2:$V$6886+Coef_B1*Climate_Shift+Local_Sensing*UHI_Day_Eff)>=B8)) -> 31 | E8: =SUMPRODUCT((Data_Heathrow!$B$2:$B$6886=SelYear)*(Data_Heathrow!$R$2:$R$6886=1)*((Data_Heathrow!$E$2:$E$6886+Climate_Shift+UHI_Day_Eff)>=B8)) -> 59 | F8: =IF(E8=0,"n/a",D8/E8) -> 0.52542373 | H8: 1 | I8: =COUNTIFS(Data_Heathrow!$B$2:$B$6886,SelYear,Data_Heathrow!$E$2:$E$6886,">="&(T_Day-H8-UHI_Day_Eff)) -> 50 | J8: =Beta*(1-Sens_Red)*(Equity_Lens!$E$6*SUMPRODUCT((Data_Heathrow!$B$2:$B$6886=SelYear)*(Data_Heathrow!$I$2:$I$6886<>"")*((Data_Heathrow!$I$2:$I$6886+H8+(Equity_Lens!$F$6+Equity_Lens!$G$6)/2-T_Mort)>0)*(Data_Heathrow!$I$2:$I$6886+H8+(Equity_Lens!$F$6+Equity_Lens!$G$6)/2-T_Mort))+Equity_Lens!$E$7*SUMPRODUCT((Data_Heathrow!$B$2:$B$6886=SelYear)*(Data_Heathrow!$I$2:$I$6886<>"")*((Data_Heathrow!$I$2:$I$6886+H8+(Equity_Lens!$F$7+Equity_Lens!$G$7)/2-T_Mort)>0)*(Data_Heathrow!$I$2:$I$6886+H8+(Equity_Lens!$F$7+Equity_Lens!$G$7)/2-T_Mort))+Equity_Lens!$E$8*SUMPRODUCT((Data_Heathrow!$B$2:$B$6886=SelYear)*(Data_Heathrow!$I$2:$I$6886<>"")*((Data_Heathrow!$I$2:$I$6886+H8+(Equity_Lens!$F$8+Equity_Lens!$G$8)/2-T_Mort)>0)*(Data_Heathrow!$I$2:$I$6886+H8+(Equity_Lens!$F$8+Equity_Lens!$G$8)/2-T_Mort))+Equity_Lens!$E$9*SUMPRODUCT((Data_Heathrow!$B$2:$B$6886=SelYear)*(Data_Heathrow!$I$2:$I$6886<>"")*((Data_Heathrow!$I$2:$I$6886+H8+(Equity_Lens!$F$9+Equity_Lens!$G$9)/2-T_Mort)>0)*(Data_Heathrow!$I$2:$I$6886+H8+(Equity_Lens!$F$9+Equity_Lens!$G$9)/2-T_Mort))) -> 527.71886
B9: 27 | C9: =COUNTIFS(Data_Heathrow!$B$2:$B$6886,SelYear,Data_Heathrow!$E$2:$E$6886,">="&(B9-Climate_Shift-UHI_Day_Eff)) -> 50 | D9: =SUMPRODUCT((Data_Heathrow!$B$2:$B$6886=SelYear)*(Data_Heathrow!$R$2:$R$6886=1)*((Data_Heathrow!$E$2:$E$6886+Climate_Shift+UHI_Day_Eff)>=B9)*((Data_Heathrow!$V$2:$V$6886+Coef_B1*Climate_Shift+Local_Sensing*UHI_Day_Eff)>=B9)) -> 17 | E9: =SUMPRODUCT((Data_Heathrow!$B$2:$B$6886=SelYear)*(Data_Heathrow!$R$2:$R$6886=1)*((Data_Heathrow!$E$2:$E$6886+Climate_Shift+UHI_Day_Eff)>=B9)) -> 48 | F9: =IF(E9=0,"n/a",D9/E9) -> 0.35416667 | H9: 1.5 | I9: =COUNTIFS(Data_Heathrow!$B$2:$B$6886,SelYear,Data_Heathrow!$E$2:$E$6886,">="&(T_Day-H9-UHI_Day_Eff)) -> 57 | J9: =Beta*(1-Sens_Red)*(Equity_Lens!$E$6*SUMPRODUCT((Data_Heathrow!$B$2:$B$6886=SelYear)*(Data_Heathrow!$I$2:$I$6886<>"")*((Data_Heathrow!$I$2:$I$6886+H9+(Equity_Lens!$F$6+Equity_Lens!$G$6)/2-T_Mort)>0)*(Data_Heathrow!$I$2:$I$6886+H9+(Equity_Lens!$F$6+Equity_Lens!$G$6)/2-T_Mort))+Equity_Lens!$E$7*SUMPRODUCT((Data_Heathrow!$B$2:$B$6886=SelYear)*(Data_Heathrow!$I$2:$I$6886<>"")*((Data_Heathrow!$I$2:$I$6886+H9+(Equity_Lens!$F$7+Equity_Lens!$G$7)/2-T_Mort)>0)*(Data_Heathrow!$I$2:$I$6886+H9+(Equity_Lens!$F$7+Equity_Lens!$G$7)/2-T_Mort))+Equity_Lens!$E$8*SUMPRODUCT((Data_Heathrow!$B$2:$B$6886=SelYear)*(Data_Heathrow!$I$2:$I$6886<>"")*((Data_Heathrow!$I$2:$I$6886+H9+(Equity_Lens!$F$8+Equity_Lens!$G$8)/2-T_Mort)>0)*(Data_Heathrow!$I$2:$I$6886+H9+(Equity_Lens!$F$8+Equity_Lens!$G$8)/2-T_Mort))+Equity_Lens!$E$9*SUMPRODUCT((Data_Heathrow!$B$2:$B$6886=SelYear)*(Data_Heathrow!$I$2:$I$6886<>"")*((Data_Heathrow!$I$2:$I$6886+H9+(Equity_Lens!$F$9+Equity_Lens!$G$9)/2-T_Mort)>0)*(Data_Heathrow!$I$2:$I$6886+H9+(Equity_Lens!$F$9+Equity_Lens!$G$9)/2-T_Mort))) -> 607.88566
B10: 28 | C10: =COUNTIFS(Data_Heathrow!$B$2:$B$6886,SelYear,Data_Heathrow!$E$2:$E$6886,">="&(B10-Climate_Shift-UHI_Day_Eff)) -> 41 | D10: =SUMPRODUCT((Data_Heathrow!$B$2:$B$6886=SelYear)*(Data_Heathrow!$R$2:$R$6886=1)*((Data_Heathrow!$E$2:$E$6886+Climate_Shift+UHI_Day_Eff)>=B10)*((Data_Heathrow!$V$2:$V$6886+Coef_B1*Climate_Shift+Local_Sensing*UHI_Day_Eff)>=B10)) -> 14 | E10: =SUMPRODUCT((Data_Heathrow!$B$2:$B$6886=SelYear)*(Data_Heathrow!$R$2:$R$6886=1)*((Data_Heathrow!$E$2:$E$6886+Climate_Shift+UHI_Day_Eff)>=B10)) -> 40 | F10: =IF(E10=0,"n/a",D10/E10) -> 0.35 | H10: 2 | I10: =COUNTIFS(Data_Heathrow!$B$2:$B$6886,SelYear,Data_Heathrow!$E$2:$E$6886,">="&(T_Day-H10-UHI_Day_Eff)) -> 63 | J10: =Beta*(1-Sens_Red)*(Equity_Lens!$E$6*SUMPRODUCT((Data_Heathrow!$B$2:$B$6886=SelYear)*(Data_Heathrow!$I$2:$I$6886<>"")*((Data_Heathrow!$I$2:$I$6886+H10+(Equity_Lens!$F$6+Equity_Lens!$G$6)/2-T_Mort)>0)*(Data_Heathrow!$I$2:$I$6886+H10+(Equity_Lens!$F$6+Equity_Lens!$G$6)/2-T_Mort))+Equity_Lens!$E$7*SUMPRODUCT((Data_Heathrow!$B$2:$B$6886=SelYear)*(Data_Heathrow!$I$2:$I$6886<>"")*((Data_Heathrow!$I$2:$I$6886+H10+(Equity_Lens!$F$7+Equity_Lens!$G$7)/2-T_Mort)>0)*(Data_Heathrow!$I$2:$I$6886+H10+(Equity_Lens!$F$7+Equity_Lens!$G$7)/2-T_Mort))+Equity_Lens!$E$8*SUMPRODUCT((Data_Heathrow!$B$2:$B$6886=SelYear)*(Data_Heathrow!$I$2:$I$6886<>"")*((Data_Heathrow!$I$2:$I$6886+H10+(Equity_Lens!$F$8+Equity_Lens!$G$8)/2-T_Mort)>0)*(Data_Heathrow!$I$2:$I$6886+H10+(Equity_Lens!$F$8+Equity_Lens!$G$8)/2-T_Mort))+Equity_Lens!$E$9*SUMPRODUCT((Data_Heathrow!$B$2:$B$6886=SelYear)*(Data_Heathrow!$I$2:$I$6886<>"")*((Data_Heathrow!$I$2:$I$6886+H10+(Equity_Lens!$F$9+Equity_Lens!$G$9)/2-T_Mort)>0)*(Data_Heathrow!$I$2:$I$6886+H10+(Equity_Lens!$F$9+Equity_Lens!$G$9)/2-T_Mort))) -> 694.71721
B11: 29 | C11: =COUNTIFS(Data_Heathrow!$B$2:$B$6886,SelYear,Data_Heathrow!$E$2:$E$6886,">="&(B11-Climate_Shift-UHI_Day_Eff)) -> 35 | D11: =SUMPRODUCT((Data_Heathrow!$B$2:$B$6886=SelYear)*(Data_Heathrow!$R$2:$R$6886=1)*((Data_Heathrow!$E$2:$E$6886+Climate_Shift+UHI_Day_Eff)>=B11)*((Data_Heathrow!$V$2:$V$6886+Coef_B1*Climate_Shift+Local_Sensing*UHI_Day_Eff)>=B11)) -> 9 | E11: =SUMPRODUCT((Data_Heathrow!$B$2:$B$6886=SelYear)*(Data_Heathrow!$R$2:$R$6886=1)*((Data_Heathrow!$E$2:$E$6886+Climate_Shift+UHI_Day_Eff)>=B11)) -> 34 | F11: =IF(E11=0,"n/a",D11/E11) -> 0.26470588 | H11: 2.5 | I11: =COUNTIFS(Data_Heathrow!$B$2:$B$6886,SelYear,Data_Heathrow!$E$2:$E$6886,">="&(T_Day-H11-UHI_Day_Eff)) -> 70 | J11: =Beta*(1-Sens_Red)*(Equity_Lens!$E$6*SUMPRODUCT((Data_Heathrow!$B$2:$B$6886=SelYear)*(Data_Heathrow!$I$2:$I$6886<>"")*((Data_Heathrow!$I$2:$I$6886+H11+(Equity_Lens!$F$6+Equity_Lens!$G$6)/2-T_Mort)>0)*(Data_Heathrow!$I$2:$I$6886+H11+(Equity_Lens!$F$6+Equity_Lens!$G$6)/2-T_Mort))+Equity_Lens!$E$7*SUMPRODUCT((Data_Heathrow!$B$2:$B$6886=SelYear)*(Data_Heathrow!$I$2:$I$6886<>"")*((Data_Heathrow!$I$2:$I$6886+H11+(Equity_Lens!$F$7+Equity_Lens!$G$7)/2-T_Mort)>0)*(Data_Heathrow!$I$2:$I$6886+H11+(Equity_Lens!$F$7+Equity_Lens!$G$7)/2-T_Mort))+Equity_Lens!$E$8*SUMPRODUCT((Data_Heathrow!$B$2:$B$6886=SelYear)*(Data_Heathrow!$I$2:$I$6886<>"")*((Data_Heathrow!$I$2:$I$6886+H11+(Equity_Lens!$F$8+Equity_Lens!$G$8)/2-T_Mort)>0)*(Data_Heathrow!$I$2:$I$6886+H11+(Equity_Lens!$F$8+Equity_Lens!$G$8)/2-T_Mort))+Equity_Lens!$E$9*SUMPRODUCT((Data_Heathrow!$B$2:$B$6886=SelYear)*(Data_Heathrow!$I$2:$I$6886<>"")*((Data_Heathrow!$I$2:$I$6886+H11+(Equity_Lens!$F$9+Equity_Lens!$G$9)/2-T_Mort)>0)*(Data_Heathrow!$I$2:$I$6886+H11+(Equity_Lens!$F$9+Equity_Lens!$G$9)/2-T_Mort))) -> 790.10649
B12: 30 | C12: =COUNTIFS(Data_Heathrow!$B$2:$B$6886,SelYear,Data_Heathrow!$E$2:$E$6886,">="&(B12-Climate_Shift-UHI_Day_Eff)) -> 22 | D12: =SUMPRODUCT((Data_Heathrow!$B$2:$B$6886=SelYear)*(Data_Heathrow!$R$2:$R$6886=1)*((Data_Heathrow!$E$2:$E$6886+Climate_Shift+UHI_Day_Eff)>=B12)*((Data_Heathrow!$V$2:$V$6886+Coef_B1*Climate_Shift+Local_Sensing*UHI_Day_Eff)>=B12)) -> 6 | E12: =SUMPRODUCT((Data_Heathrow!$B$2:$B$6886=SelYear)*(Data_Heathrow!$R$2:$R$6886=1)*((Data_Heathrow!$E$2:$E$6886+Climate_Shift+UHI_Day_Eff)>=B12)) -> 22 | F12: =IF(E12=0,"n/a",D12/E12) -> 0.27272727 | H12: 3 | I12: =COUNTIFS(Data_Heathrow!$B$2:$B$6886,SelYear,Data_Heathrow!$E$2:$E$6886,">="&(T_Day-H12-UHI_Day_Eff)) -> 83 | J12: =Beta*(1-Sens_Red)*(Equity_Lens!$E$6*SUMPRODUCT((Data_Heathrow!$B$2:$B$6886=SelYear)*(Data_Heathrow!$I$2:$I$6886<>"")*((Data_Heathrow!$I$2:$I$6886+H12+(Equity_Lens!$F$6+Equity_Lens!$G$6)/2-T_Mort)>0)*(Data_Heathrow!$I$2:$I$6886+H12+(Equity_Lens!$F$6+Equity_Lens!$G$6)/2-T_Mort))+Equity_Lens!$E$7*SUMPRODUCT((Data_Heathrow!$B$2:$B$6886=SelYear)*(Data_Heathrow!$I$2:$I$6886<>"")*((Data_Heathrow!$I$2:$I$6886+H12+(Equity_Lens!$F$7+Equity_Lens!$G$7)/2-T_Mort)>0)*(Data_Heathrow!$I$2:$I$6886+H12+(Equity_Lens!$F$7+Equity_Lens!$G$7)/2-T_Mort))+Equity_Lens!$E$8*SUMPRODUCT((Data_Heathrow!$B$2:$B$6886=SelYear)*(Data_Heathrow!$I$2:$I$6886<>"")*((Data_Heathrow!$I$2:$I$6886+H12+(Equity_Lens!$F$8+Equity_Lens!$G$8)/2-T_Mort)>0)*(Data_Heathrow!$I$2:$I$6886+H12+(Equity_Lens!$F$8+Equity_Lens!$G$8)/2-T_Mort))+Equity_Lens!$E$9*SUMPRODUCT((Data_Heathrow!$B$2:$B$6886=SelYear)*(Data_Heathrow!$I$2:$I$6886<>"")*((Data_Heathrow!$I$2:$I$6886+H12+(Equity_Lens!$F$9+Equity_Lens!$G$9)/2-T_Mort)>0)*(Data_Heathrow!$I$2:$I$6886+H12+(Equity_Lens!$F$9+Equity_Lens!$G$9)/2-T_Mort))) -> 891.62826
B13: 31 | C13: =COUNTIFS(Data_Heathrow!$B$2:$B$6886,SelYear,Data_Heathrow!$E$2:$E$6886,">="&(B13-Climate_Shift-UHI_Day_Eff)) -> 19 | D13: =SUMPRODUCT((Data_Heathrow!$B$2:$B$6886=SelYear)*(Data_Heathrow!$R$2:$R$6886=1)*((Data_Heathrow!$E$2:$E$6886+Climate_Shift+UHI_Day_Eff)>=B13)*((Data_Heathrow!$V$2:$V$6886+Coef_B1*Climate_Shift+Local_Sensing*UHI_Day_Eff)>=B13)) -> 5 | E13: =SUMPRODUCT((Data_Heathrow!$B$2:$B$6886=SelYear)*(Data_Heathrow!$R$2:$R$6886=1)*((Data_Heathrow!$E$2:$E$6886+Climate_Shift+UHI_Day_Eff)>=B13)) -> 19 | F13: =IF(E13=0,"n/a",D13/E13) -> 0.26315789 | H13: 3.5 | I13: =COUNTIFS(Data_Heathrow!$B$2:$B$6886,SelYear,Data_Heathrow!$E$2:$E$6886,">="&(T_Day-H13-UHI_Day_Eff)) -> 90 | J13: =Beta*(1-Sens_Red)*(Equity_Lens!$E$6*SUMPRODUCT((Data_Heathrow!$B$2:$B$6886=SelYear)*(Data_Heathrow!$I$2:$I$6886<>"")*((Data_Heathrow!$I$2:$I$6886+H13+(Equity_Lens!$F$6+Equity_Lens!$G$6)/2-T_Mort)>0)*(Data_Heathrow!$I$2:$I$6886+H13+(Equity_Lens!$F$6+Equity_Lens!$G$6)/2-T_Mort))+Equity_Lens!$E$7*SUMPRODUCT((Data_Heathrow!$B$2:$B$6886=SelYear)*(Data_Heathrow!$I$2:$I$6886<>"")*((Data_Heathrow!$I$2:$I$6886+H13+(Equity_Lens!$F$7+Equity_Lens!$G$7)/2-T_Mort)>0)*(Data_Heathrow!$I$2:$I$6886+H13+(Equity_Lens!$F$7+Equity_Lens!$G$7)/2-T_Mort))+Equity_Lens!$E$8*SUMPRODUCT((Data_Heathrow!$B$2:$B$6886=SelYear)*(Data_Heathrow!$I$2:$I$6886<>"")*((Data_Heathrow!$I$2:$I$6886+H13+(Equity_Lens!$F$8+Equity_Lens!$G$8)/2-T_Mort)>0)*(Data_Heathrow!$I$2:$I$6886+H13+(Equity_Lens!$F$8+Equity_Lens!$G$8)/2-T_Mort))+Equity_Lens!$E$9*SUMPRODUCT((Data_Heathrow!$B$2:$B$6886=SelYear)*(Data_Heathrow!$I$2:$I$6886<>"")*((Data_Heathrow!$I$2:$I$6886+H13+(Equity_Lens!$F$9+Equity_Lens!$G$9)/2-T_Mort)>0)*(Data_Heathrow!$I$2:$I$6886+H13+(Equity_Lens!$F$9+Equity_Lens!$G$9)/2-T_Mort))) -> 999.32882
B14: 32 | C14: =COUNTIFS(Data_Heathrow!$B$2:$B$6886,SelYear,Data_Heathrow!$E$2:$E$6886,">="&(B14-Climate_Shift-UHI_Day_Eff)) -> 11 | D14: =SUMPRODUCT((Data_Heathrow!$B$2:$B$6886=SelYear)*(Data_Heathrow!$R$2:$R$6886=1)*((Data_Heathrow!$E$2:$E$6886+Climate_Shift+UHI_Day_Eff)>=B14)*((Data_Heathrow!$V$2:$V$6886+Coef_B1*Climate_Shift+Local_Sensing*UHI_Day_Eff)>=B14)) -> 2 | E14: =SUMPRODUCT((Data_Heathrow!$B$2:$B$6886=SelYear)*(Data_Heathrow!$R$2:$R$6886=1)*((Data_Heathrow!$E$2:$E$6886+Climate_Shift+UHI_Day_Eff)>=B14)) -> 11 | F14: =IF(E14=0,"n/a",D14/E14) -> 0.18181818 | H14: 4 | I14: =COUNTIFS(Data_Heathrow!$B$2:$B$6886,SelYear,Data_Heathrow!$E$2:$E$6886,">="&(T_Day-H14-UHI_Day_Eff)) -> 102 | J14: =Beta*(1-Sens_Red)*(Equity_Lens!$E$6*SUMPRODUCT((Data_Heathrow!$B$2:$B$6886=SelYear)*(Data_Heathrow!$I$2:$I$6886<>"")*((Data_Heathrow!$I$2:$I$6886+H14+(Equity_Lens!$F$6+Equity_Lens!$G$6)/2-T_Mort)>0)*(Data_Heathrow!$I$2:$I$6886+H14+(Equity_Lens!$F$6+Equity_Lens!$G$6)/2-T_Mort))+Equity_Lens!$E$7*SUMPRODUCT((Data_Heathrow!$B$2:$B$6886=SelYear)*(Data_Heathrow!$I$2:$I$6886<>"")*((Data_Heathrow!$I$2:$I$6886+H14+(Equity_Lens!$F$7+Equity_Lens!$G$7)/2-T_Mort)>0)*(Data_Heathrow!$I$2:$I$6886+H14+(Equity_Lens!$F$7+Equity_Lens!$G$7)/2-T_Mort))+Equity_Lens!$E$8*SUMPRODUCT((Data_Heathrow!$B$2:$B$6886=SelYear)*(Data_Heathrow!$I$2:$I$6886<>"")*((Data_Heathrow!$I$2:$I$6886+H14+(Equity_Lens!$F$8+Equity_Lens!$G$8)/2-T_Mort)>0)*(Data_Heathrow!$I$2:$I$6886+H14+(Equity_Lens!$F$8+Equity_Lens!$G$8)/2-T_Mort))+Equity_Lens!$E$9*SUMPRODUCT((Data_Heathrow!$B$2:$B$6886=SelYear)*(Data_Heathrow!$I$2:$I$6886<>"")*((Data_Heathrow!$I$2:$I$6886+H14+(Equity_Lens!$F$9+Equity_Lens!$G$9)/2-T_Mort)>0)*(Data_Heathrow!$I$2:$I$6886+H14+(Equity_Lens!$F$9+Equity_Lens!$G$9)/2-T_Mort))) -> 1113.185
B15: 33 | C15: =COUNTIFS(Data_Heathrow!$B$2:$B$6886,SelYear,Data_Heathrow!$E$2:$E$6886,">="&(B15-Climate_Shift-UHI_Day_Eff)) -> 9 | D15: =SUMPRODUCT((Data_Heathrow!$B$2:$B$6886=SelYear)*(Data_Heathrow!$R$2:$R$6886=1)*((Data_Heathrow!$E$2:$E$6886+Climate_Shift+UHI_Day_Eff)>=B15)*((Data_Heathrow!$V$2:$V$6886+Coef_B1*Climate_Shift+Local_Sensing*UHI_Day_Eff)>=B15)) -> 1 | E15: =SUMPRODUCT((Data_Heathrow!$B$2:$B$6886=SelYear)*(Data_Heathrow!$R$2:$R$6886=1)*((Data_Heathrow!$E$2:$E$6886+Climate_Shift+UHI_Day_Eff)>=B15)) -> 9 | F15: =IF(E15=0,"n/a",D15/E15) -> 0.11111111
B16: 34 | C16: =COUNTIFS(Data_Heathrow!$B$2:$B$6886,SelYear,Data_Heathrow!$E$2:$E$6886,">="&(B16-Climate_Shift-UHI_Day_Eff)) -> 7 | D16: =SUMPRODUCT((Data_Heathrow!$B$2:$B$6886=SelYear)*(Data_Heathrow!$R$2:$R$6886=1)*((Data_Heathrow!$E$2:$E$6886+Climate_Shift+UHI_Day_Eff)>=B16)*((Data_Heathrow!$V$2:$V$6886+Coef_B1*Climate_Shift+Local_Sensing*UHI_Day_Eff)>=B16)) -> 1 | E16: =SUMPRODUCT((Data_Heathrow!$B$2:$B$6886=SelYear)*(Data_Heathrow!$R$2:$R$6886=1)*((Data_Heathrow!$E$2:$E$6886+Climate_Shift+UHI_Day_Eff)>=B16)) -> 7 | F16: =IF(E16=0,"n/a",D16/E16) -> 0.14285714 | H16: Ratio: deaths at +2°C vs +0°C | J16: =IFERROR(J10/J6,"n/a") -> 1.7951349
B17: 35 | C17: =COUNTIFS(Data_Heathrow!$B$2:$B$6886,SelYear,Data_Heathrow!$E$2:$E$6886,">="&(B17-Climate_Shift-UHI_Day_Eff)) -> 6 | D17: =SUMPRODUCT((Data_Heathrow!$B$2:$B$6886=SelYear)*(Data_Heathrow!$R$2:$R$6886=1)*((Data_Heathrow!$E$2:$E$6886+Climate_Shift+UHI_Day_Eff)>=B17)*((Data_Heathrow!$V$2:$V$6886+Coef_B1*Climate_Shift+Local_Sensing*UHI_Day_Eff)>=B17)) -> 0 | E17: =SUMPRODUCT((Data_Heathrow!$B$2:$B$6886=SelYear)*(Data_Heathrow!$R$2:$R$6886=1)*((Data_Heathrow!$E$2:$E$6886+Climate_Shift+UHI_Day_Eff)>=B17)) -> 6 | F17: =IF(E17=0,"n/a",D17/E17) -> 0 | H17: Linear expectation would be ≈ 1 + 2×(slope). Compare.
B18: 36 | C18: =COUNTIFS(Data_Heathrow!$B$2:$B$6886,SelYear,Data_Heathrow!$E$2:$E$6886,">="&(B18-Climate_Shift-UHI_Day_Eff)) -> 3 | D18: =SUMPRODUCT((Data_Heathrow!$B$2:$B$6886=SelYear)*(Data_Heathrow!$R$2:$R$6886=1)*((Data_Heathrow!$E$2:$E$6886+Climate_Shift+UHI_Day_Eff)>=B18)*((Data_Heathrow!$V$2:$V$6886+Coef_B1*Climate_Shift+Local_Sensing*UHI_Day_Eff)>=B18)) -> 0 | E18: =SUMPRODUCT((Data_Heathrow!$B$2:$B$6886=SelYear)*(Data_Heathrow!$R$2:$R$6886=1)*((Data_Heathrow!$E$2:$E$6886+Climate_Shift+UHI_Day_Eff)>=B18)) -> 3 | F18: =IF(E18=0,"n/a",D18/E18) -> 0
B19: 37 | C19: =COUNTIFS(Data_Heathrow!$B$2:$B$6886,SelYear,Data_Heathrow!$E$2:$E$6886,">="&(B19-Climate_Shift-UHI_Day_Eff)) -> 2 | D19: =SUMPRODUCT((Data_Heathrow!$B$2:$B$6886=SelYear)*(Data_Heathrow!$R$2:$R$6886=1)*((Data_Heathrow!$E$2:$E$6886+Climate_Shift+UHI_Day_Eff)>=B19)*((Data_Heathrow!$V$2:$V$6886+Coef_B1*Climate_Shift+Local_Sensing*UHI_Day_Eff)>=B19)) -> 0 | E19: =SUMPRODUCT((Data_Heathrow!$B$2:$B$6886=SelYear)*(Data_Heathrow!$R$2:$R$6886=1)*((Data_Heathrow!$E$2:$E$6886+Climate_Shift+UHI_Day_Eff)>=B19)) -> 2 | F19: =IF(E19=0,"n/a",D19/E19) -> 0
B20: 38 | C20: =COUNTIFS(Data_Heathrow!$B$2:$B$6886,SelYear,Data_Heathrow!$E$2:$E$6886,">="&(B20-Climate_Shift-UHI_Day_Eff)) -> 2 | D20: =SUMPRODUCT((Data_Heathrow!$B$2:$B$6886=SelYear)*(Data_Heathrow!$R$2:$R$6886=1)*((Data_Heathrow!$E$2:$E$6886+Climate_Shift+UHI_Day_Eff)>=B20)*((Data_Heathrow!$V$2:$V$6886+Coef_B1*Climate_Shift+Local_Sensing*UHI_Day_Eff)>=B20)) -> 0 | E20: =SUMPRODUCT((Data_Heathrow!$B$2:$B$6886=SelYear)*(Data_Heathrow!$R$2:$R$6886=1)*((Data_Heathrow!$E$2:$E$6886+Climate_Shift+UHI_Day_Eff)>=B20)) -> 2 | F20: =IF(E20=0,"n/a",D20/E20) -> 0
B21: 39 | C21: =COUNTIFS(Data_Heathrow!$B$2:$B$6886,SelYear,Data_Heathrow!$E$2:$E$6886,">="&(B21-Climate_Shift-UHI_Day_Eff)) -> 2 | D21: =SUMPRODUCT((Data_Heathrow!$B$2:$B$6886=SelYear)*(Data_Heathrow!$R$2:$R$6886=1)*((Data_Heathrow!$E$2:$E$6886+Climate_Shift+UHI_Day_Eff)>=B21)*((Data_Heathrow!$V$2:$V$6886+Coef_B1*Climate_Shift+Local_Sensing*UHI_Day_Eff)>=B21)) -> 0 | E21: =SUMPRODUCT((Data_Heathrow!$B$2:$B$6886=SelYear)*(Data_Heathrow!$R$2:$R$6886=1)*((Data_Heathrow!$E$2:$E$6886+Climate_Shift+UHI_Day_Eff)>=B21)) -> 2 | F21: =IF(E21=0,"n/a",D21/E21) -> 0
B22: 40 | C22: =COUNTIFS(Data_Heathrow!$B$2:$B$6886,SelYear,Data_Heathrow!$E$2:$E$6886,">="&(B22-Climate_Shift-UHI_Day_Eff)) -> 1 | D22: =SUMPRODUCT((Data_Heathrow!$B$2:$B$6886=SelYear)*(Data_Heathrow!$R$2:$R$6886=1)*((Data_Heathrow!$E$2:$E$6886+Climate_Shift+UHI_Day_Eff)>=B22)*((Data_Heathrow!$V$2:$V$6886+Coef_B1*Climate_Shift+Local_Sensing*UHI_Day_Eff)>=B22)) -> 0 | E22: =SUMPRODUCT((Data_Heathrow!$B$2:$B$6886=SelYear)*(Data_Heathrow!$R$2:$R$6886=1)*((Data_Heathrow!$E$2:$E$6886+Climate_Shift+UHI_Day_Eff)>=B22)) -> 1 | F22: =IF(E22=0,"n/a",D22/E22) -> 0
B25: 3. Stock-and-flow tipping model (live from Monitor_Control)
B26: Heat-stress stock(t) = max(0, stock(t−1) × (1 − Decay) + inflow − night recovery)
B27: Inflow = max(0, TX_adj − T_Comfort): daytime heat load on people, buildings and infrastructure.
B28: Night recovery = Recovery_Rate × max(0, T_Night − TN_adj): cool nights accelerate recovery; the UHI suppresses it. Decay is slow background recovery.
B29: Tipping = stock > Capacity: health, transport and energy services are overwhelmed (a regime shift, not a gradual decline).
B30: P(service failure) is logistic in (stock − capacity): the threshold is a zone of rising probability, not a cliff edge.
B32: Peak stock this year | E32: =KPI_PeakStock -> 45.575094
B33: Capacity | E33: =Capacity -> 40
B34: Headroom (capacity − peak) | E34: =Capacity-KPI_PeakStock -> -5.5750936
B35: Tipping days | E35: =KPI_TipDays -> 3
B36: First tipping date | E36: =First_Tip -> 44760
B38: Try: raise Climate_Shift in 0.5°C steps and record the first shift at which Tipping days > 0 (Goal Seek on Capacity headroom, or Excel Data ▸ What-If ▸ Data Table). That shift is your modelled tipping threshold — feed it into Req_Feedback as a design margin.

Sheet Equity_Lens
A1: Equity_Lens — who carries the heat, and who does the monitoring miss?
A2: Typology uplifts and group profiles are ILLUSTRATIVE ASSUMPTIONS for teaching. Groups must test, challenge and evidence them.
B4: 1. Neighbourhood typologies (selected year, current scenario)
B5: Typology | C5: UHI day °C | D5: UHI night °C | E5: Pop. share | F5: Day eff °C | G5: Night eff °C | H5: Hot days | I5: Warm nights | J5: Degree-days > T_Mort | K5: Excess deaths | L5: Rep. gap days | M5: AI missed hot days (ref. only) | N5: AI missed (local sensing) | O5: Calibration °C·days
B6: Reference: Heathrow station | C6: 0 | D6: 0 | E6: 0 | F6: =C6-Day_Red_Frac*MAX(0,C6) -> 0 | G6: =D6-Night_Red_Frac*MAX(0,D6) -> 0 | H6: =COUNTIFS(Data_Heathrow!$B$2:$B$6886,SelYear,Data_Heathrow!$E$2:$E$6886,">="&(T_Day-Climate_Shift-F6)) -> 22 | I6: =COUNTIFS(Data_Heathrow!$B$2:$B$6886,SelYear,Data_Heathrow!$G$2:$G$6886,">="&(T_Night-Climate_Shift-G6)) -> 14 | J6: =SUMPRODUCT((Data_Heathrow!$B$2:$B$6886=SelYear)*(Data_Heathrow!$I$2:$I$6886<>"")*((Data_Heathrow!$I$2:$I$6886+Climate_Shift+(F6+G6)/2-T_Mort)>0)*(Data_Heathrow!$I$2:$I$6886+Climate_Shift+(F6+G6)/2-T_Mort)) -> 124.5 | K6: =Beta*E6*(1-Sens_Red)*J6 -> 0 | L6: =COUNTIFS(Data_Heathrow!$B$2:$B$6886,SelYear,Data_Heathrow!$E$2:$E$6886,">="&(T_Day-Climate_Shift-F6),Data_Heathrow!$E$2:$E$6886,"<"&(T_Day-Climate_Shift)) -> 0 | M6: =SUMPRODUCT((Data_Heathrow!$B$2:$B$6886=SelYear)*(Data_Heathrow!$R$2:$R$6886=1)*((Data_Heathrow!$E$2:$E$6886+Climate_Shift+F6)>=T_Day)*((Data_Heathrow!$V$2:$V$6886+Coef_B1*Climate_Shift)<T_Day)) -> 8 | N6: =SUMPRODUCT((Data_Heathrow!$B$2:$B$6886=SelYear)*(Data_Heathrow!$R$2:$R$6886=1)*((Data_Heathrow!$E$2:$E$6886+Climate_Shift+F6)>=T_Day)*((Data_Heathrow!$V$2:$V$6886+Coef_B1*Climate_Shift+F6)<T_Day)) -> 8 | O6: =SUMPRODUCT((Data_Heathrow!$B$2:$B$6886=Calib_Year)*(Data_Heathrow!$I$2:$I$6886<>"")*((Data_Heathrow!$I$2:$I$6886+(C6+D6)/2-T_Mort)>0)*(Data_Heathrow!$I$2:$I$6886+(C6+D6)/2-T_Mort)) -> 124.5
B7: Inner London: dense, low green | C7: 2 | D7: 4 | E7: 0.3 | F7: =C7-Day_Red_Frac*MAX(0,C7) -> 2 | G7: =D7-Night_Red_Frac*MAX(0,D7) -> 4 | H7: =COUNTIFS(Data_Heathrow!$B$2:$B$6886,SelYear,Data_Heathrow!$E$2:$E$6886,">="&(T_Day-Climate_Shift-F7)) -> 41 | I7: =COUNTIFS(Data_Heathrow!$B$2:$B$6886,SelYear,Data_Heathrow!$G$2:$G$6886,">="&(T_Night-Climate_Shift-G7)) -> 64 | J7: =SUMPRODUCT((Data_Heathrow!$B$2:$B$6886=SelYear)*(Data_Heathrow!$I$2:$I$6886<>"")*((Data_Heathrow!$I$2:$I$6886+Climate_Shift+(F7+G7)/2-T_Mort)>0)*(Data_Heathrow!$I$2:$I$6886+Climate_Shift+(F7+G7)/2-T_Mort)) -> 336.6 | K7: =Beta*E7*(1-Sens_Red)*J7 -> 186.94633 | L7: =COUNTIFS(Data_Heathrow!$B$2:$B$6886,SelYear,Data_Heathrow!$E$2:$E$6886,">="&(T_Day-Climate_Shift-F7),Data_Heathrow!$E$2:$E$6886,"<"&(T_Day-Climate_Shift)) -> 19 | M7: =SUMPRODUCT((Data_Heathrow!$B$2:$B$6886=SelYear)*(Data_Heathrow!$R$2:$R$6886=1)*((Data_Heathrow!$E$2:$E$6886+Climate_Shift+F7)>=T_Day)*((Data_Heathrow!$V$2:$V$6886+Coef_B1*Climate_Shift)<T_Day)) -> 26 | N7: =SUMPRODUCT((Data_Heathrow!$B$2:$B$6886=SelYear)*(Data_Heathrow!$R$2:$R$6886=1)*((Data_Heathrow!$E$2:$E$6886+Climate_Shift+F7)>=T_Day)*((Data_Heathrow!$V$2:$V$6886+Coef_B1*Climate_Shift+F7)<T_Day)) -> 14 | O7: =SUMPRODUCT((Data_Heathrow!$B$2:$B$6886=Calib_Year)*(Data_Heathrow!$I$2:$I$6886<>"")*((Data_Heathrow!$I$2:$I$6886+(C7+D7)/2-T_Mort)>0)*(Data_Heathrow!$I$2:$I$6886+(C7+D7)/2-T_Mort)) -> 336.6
B8: Outer London: suburban | C8: 0.5 | D8: 1 | E8: 0.55 | F8: =C8-Day_Red_Frac*MAX(0,C8) -> 0.5 | G8: =D8-Night_Red_Frac*MAX(0,D8) -> 1 | H8: =COUNTIFS(Data_Heathrow!$B$2:$B$6886,SelYear,Data_Heathrow!$E$2:$E$6886,">="&(T_Day-Climate_Shift-F8)) -> 31 | I8: =COUNTIFS(Data_Heathrow!$B$2:$B$6886,SelYear,Data_Heathrow!$G$2:$G$6886,">="&(T_Night-Climate_Shift-G8)) -> 23 | J8: =SUMPRODUCT((Data_Heathrow!$B$2:$B$6886=SelYear)*(Data_Heathrow!$I$2:$I$6886<>"")*((Data_Heathrow!$I$2:$I$6886+Climate_Shift+(F8+G8)/2-T_Mort)>0)*(Data_Heathrow!$I$2:$I$6886+Climate_Shift+(F8+G8)/2-T_Mort)) -> 165.75 | K8: =Beta*E8*(1-Sens_Red)*J8 -> 168.77099 | L8: =COUNTIFS(Data_Heathrow!$B$2:$B$6886,SelYear,Data_Heathrow!$E$2:$E$6886,">="&(T_Day-Climate_Shift-F8),Data_Heathrow!$E$2:$E$6886,"<"&(T_Day-Climate_Shift)) -> 9 | M8: =SUMPRODUCT((Data_Heathrow!$B$2:$B$6886=SelYear)*(Data_Heathrow!$R$2:$R$6886=1)*((Data_Heathrow!$E$2:$E$6886+Climate_Shift+F8)>=T_Day)*((Data_Heathrow!$V$2:$V$6886+Coef_B1*Climate_Shift)<T_Day)) -> 17 | N8: =SUMPRODUCT((Data_Heathrow!$B$2:$B$6886=SelYear)*(Data_Heathrow!$R$2:$R$6886=1)*((Data_Heathrow!$E$2:$E$6886+Climate_Shift+F8)>=T_Day)*((Data_Heathrow!$V$2:$V$6886+Coef_B1*Climate_Shift+F8)<T_Day)) -> 16 | O8: =SUMPRODUCT((Data_Heathrow!$B$2:$B$6886=Calib_Year)*(Data_Heathrow!$I$2:$I$6886<>"")*((Data_Heathrow!$I$2:$I$6886+(C8+D8)/2-T_Mort)>0)*(Data_Heathrow!$I$2:$I$6886+(C8+D8)/2-T_Mort)) -> 165.75
B9: Green & blue corridors | C9: -0.5 | D9: 0 | E9: 0.15 | F9: =C9-Day_Red_Frac*MAX(0,C9) -> -0.5 | G9: =D9-Night_Red_Frac*MAX(0,D9) -> 0 | H9: =COUNTIFS(Data_Heathrow!$B$2:$B$6886,SelYear,Data_Heathrow!$E$2:$E$6886,">="&(T_Day-Climate_Shift-F9)) -> 21 | I9: =COUNTIFS(Data_Heathrow!$B$2:$B$6886,SelYear,Data_Heathrow!$G$2:$G$6886,">="&(T_Night-Climate_Shift-G9)) -> 14 | J9: =SUMPRODUCT((Data_Heathrow!$B$2:$B$6886=SelYear)*(Data_Heathrow!$I$2:$I$6886<>"")*((Data_Heathrow!$I$2:$I$6886+Climate_Shift+(F9+G9)/2-T_Mort)>0)*(Data_Heathrow!$I$2:$I$6886+Climate_Shift+(F9+G9)/2-T_Mort)) -> 112.65 | K9: =Beta*E9*(1-Sens_Red)*J9 -> 31.282685 | L9: =COUNTIFS(Data_Heathrow!$B$2:$B$6886,SelYear,Data_Heathrow!$E$2:$E$6886,">="&(T_Day-Climate_Shift-F9),Data_Heathrow!$E$2:$E$6886,"<"&(T_Day-Climate_Shift)) -> 0 | M9: =SUMPRODUCT((Data_Heathrow!$B$2:$B$6886=SelYear)*(Data_Heathrow!$R$2:$R$6886=1)*((Data_Heathrow!$E$2:$E$6886+Climate_Shift+F9)>=T_Day)*((Data_Heathrow!$V$2:$V$6886+Coef_B1*Climate_Shift)<T_Day)) -> 7 | N9: =SUMPRODUCT((Data_Heathrow!$B$2:$B$6886=SelYear)*(Data_Heathrow!$R$2:$R$6886=1)*((Data_Heathrow!$E$2:$E$6886+Climate_Shift+F9)>=T_Day)*((Data_Heathrow!$V$2:$V$6886+Coef_B1*Climate_Shift+F9)<T_Day)) -> 10 | O9: =SUMPRODUCT((Data_Heathrow!$B$2:$B$6886=Calib_Year)*(Data_Heathrow!$I$2:$I$6886<>"")*((Data_Heathrow!$I$2:$I$6886+(C9+D9)/2-T_Mort)>0)*(Data_Heathrow!$I$2:$I$6886+(C9+D9)/2-T_Mort)) -> 112.65
B10: London-wide (population-weighted) | E10: =SUM(E6:E9) -> 1 | H10: =SUMPRODUCT($E$6:$E$9,H6:H9) -> 32.5 | I10: =SUMPRODUCT($E$6:$E$9,I6:I9) -> 33.95 | J10: =SUMPRODUCT($E$6:$E$9,J6:J9) -> 209.04 | K10: =SUM(K6:K9) -> 387 | L10: =SUMPRODUCT($E$6:$E$9,L6:L9) -> 10.65 | M10: =SUMPRODUCT($E$6:$E$9,M6:M9) -> 18.2 | N10: =SUMPRODUCT($E$6:$E$9,N6:N9) -> 14.5 | O10: =SUMPRODUCT($E$6:$E$9,O6:O9) -> 209.04 | P10: ← β denominator
B11: Rep. gap = days the neighbourhood is above the hot-day threshold but the reference station is not: a monitoring system sited at one station systematically under-warns the hottest, often most deprived, areas. Population shares must sum to 100% (check E10).
B14: 2. Population groups — sensitivity, adaptive capacity and where people live (illustrative)
B15: Group | C15: Sensitivity × | D15: Adaptive capacity (0–1) | E15: Share inner | F15: Share outer | G15: Share green | H15: Weighted °C·days | I15: Exposure index | J15: Rank (1 = most exposed) | K15: Relative to least exposed
B16: Adults aged 75+ | C16: 2.5 | D16: 0.4 | E16: 0.25 | F16: 0.6 | G16: 0.15 | H16: =E16*$J$7+F16*$J$8+G16*$J$9 -> 200.4975 | I16: =H16*C16*(1-D16)*(1-Sens_Red) -> 300.74625 | J16: =RANK(I16,$I$16:$I$21,0) -> 3 | K16: =IFERROR(I16/MIN($I$16:$I$21),0) -> 2.7667345
B17: Long-term conditions or disability | C17: 2 | D17: 0.4 | E17: 0.3 | F17: 0.55 | G17: 0.15 | H17: =E17*$J$7+F17*$J$8+G17*$J$9 -> 209.04 | I17: =H17*C17*(1-D17)*(1-Sens_Red) -> 250.848 | J17: =RANK(I17,$I$16:$I$21,0) -> 4 | K17: =IFERROR(I17/MIN($I$16:$I$21),0) -> 2.3076923
B18: Outdoor and manual workers | C18: 1.5 | D18: 0.5 | E18: 0.35 | F18: 0.5 | G18: 0.15 | H18: =E18*$J$7+F18*$J$8+G18*$J$9 -> 217.5825 | I18: =H18*C18*(1-D18)*(1-Sens_Red) -> 163.18687 | J18: =RANK(I18,$I$16:$I$21,0) -> 5 | K18: =IFERROR(I18/MIN($I$16:$I$21),0) -> 1.5012482
B19: Low-income households in top-floor or single-aspect flats | C19: 1.8 | D19: 0.3 | E19: 0.5 | F19: 0.4 | G19: 0.1 | H19: =E19*$J$7+F19*$J$8+G19*$J$9 -> 245.865 | I19: =H19*C19*(1-D19)*(1-Sens_Red) -> 309.7899 | J19: =RANK(I19,$I$16:$I$21,0) -> 2 | K19: =IFERROR(I19/MIN($I$16:$I$21),0) -> 2.8499321
B20: People experiencing homelessness | C20: 2.5 | D20: 0.1 | E20: 0.6 | F20: 0.3 | G20: 0.1 | H20: =E20*$J$7+F20*$J$8+G20*$J$9 -> 262.95 | I20: =H20*C20*(1-D20)*(1-Sens_Red) -> 591.6375 | J20: =RANK(I20,$I$16:$I$21,0) -> 1 | K20: =IFERROR(I20/MIN($I$16:$I$21),0) -> 5.4428072
B21: Infants and children under 5 | C21: 1.3 | D21: 0.6 | E21: 0.3 | F21: 0.55 | G21: 0.15 | H21: =E21*$J$7+F21*$J$8+G21*$J$9 -> 209.04 | I21: =H21*C21*(1-D21)*(1-Sens_Red) -> 108.7008 | J21: =RANK(I21,$I$16:$I$21,0) -> 6 | K21: =IFERROR(I21/MIN($I$16:$I$21),0) -> 1
B23: Discussion (D&I): structural factors — housing quality, green-space access, income, disability and racial inequality — shape exposure. Avoid treating any group as inherently 'vulnerable'; ask what the system does to them. Who was in the room when thresholds were set?

Sheet Sustainability
A1: Sustainability — the carbon cost of keeping cool
A2: Cooling degree-days (CDD) drive air-conditioning electricity. Adaptation that raises emissions is maladaptation. All factors are editable assumptions.
B4: 1. Assumptions
B5: CDD base temperature (daily mean) | C5: 22 | D5: °C | E5: Common comfort base for cooling demand. Assumption.
B6: London households | C6: 3600000 | D6: households | E6: Order of magnitude from Census 2021; verify with ONS.
B7: Baseline share of households with AC | C7: 0.05 | E7: UK domestic AC is uncommon; assumption to evidence.
B8: Electricity per AC household per CDD | C8: 1.5 | D8: kWh | E8: Assumption.
B9: Grid carbon factor | C9: 0.15 | D9: kgCO₂e/kWh | E9: Check the latest DESNZ GHG conversion factors (falling year on year).
B10: Greening sequestration at 100% level | C10: 2000 | D10: tCO₂e/yr | E10: Assumption; small relative to energy flows.
B11: Model retrains per summer (if MLOps on) | C11: 26 | D11: per summer | E11: Fortnightly retraining.
B12: Compute energy per retrain | C12: 5 | D12: kWh | E12: Tiny model; contrast with large AI models (Green AI).
B14: 2. Cooling degree-days by typology (selected year)
B15: Typology | C15: Baseline CDD | D15: Portfolio CDD
B16: =Optimise!B24 -> Reference: Heathrow station | C16: =SUMPRODUCT((Data_Heathrow!$B$2:$B$6886=SelYear)*(Data_Heathrow!$I$2:$I$6886<>"")*((Data_Heathrow!$I$2:$I$6886+Climate_Shift+Optimise!D24-CDD_Base)>0)*(Data_Heathrow!$I$2:$I$6886+Climate_Shift+Optimise!D24-CDD_Base)) -> 53.5 | D16: =SUMPRODUCT((Data_Heathrow!$B$2:$B$6886=SelYear)*(Data_Heathrow!$I$2:$I$6886<>"")*((Data_Heathrow!$I$2:$I$6886+Climate_Shift+Optimise!E24-CDD_Base)>0)*(Data_Heathrow!$I$2:$I$6886+Climate_Shift+Optimise!E24-CDD_Base)) -> 53.5
B17: =Optimise!B25 -> Inner London: dense, low green | C17: =SUMPRODUCT((Data_Heathrow!$B$2:$B$6886=SelYear)*(Data_Heathrow!$I$2:$I$6886<>"")*((Data_Heathrow!$I$2:$I$6886+Climate_Shift+Optimise!D25-CDD_Base)>0)*(Data_Heathrow!$I$2:$I$6886+Climate_Shift+Optimise!D25-CDD_Base)) -> 181 | D17: =SUMPRODUCT((Data_Heathrow!$B$2:$B$6886=SelYear)*(Data_Heathrow!$I$2:$I$6886<>"")*((Data_Heathrow!$I$2:$I$6886+Climate_Shift+Optimise!E25-CDD_Base)>0)*(Data_Heathrow!$I$2:$I$6886+Climate_Shift+Optimise!E25-CDD_Base)) -> 132.25
B18: =Optimise!B26 -> Outer London: suburban | C18: =SUMPRODUCT((Data_Heathrow!$B$2:$B$6886=SelYear)*(Data_Heathrow!$I$2:$I$6886<>"")*((Data_Heathrow!$I$2:$I$6886+Climate_Shift+Optimise!D26-CDD_Base)>0)*(Data_Heathrow!$I$2:$I$6886+Climate_Shift+Optimise!D26-CDD_Base)) -> 75.1 | D18: =SUMPRODUCT((Data_Heathrow!$B$2:$B$6886=SelYear)*(Data_Heathrow!$I$2:$I$6886<>"")*((Data_Heathrow!$I$2:$I$6886+Climate_Shift+Optimise!E26-CDD_Base)>0)*(Data_Heathrow!$I$2:$I$6886+Climate_Shift+Optimise!E26-CDD_Base)) -> 68.125
B19: =Optimise!B27 -> Green & blue corridors | C19: =SUMPRODUCT((Data_Heathrow!$B$2:$B$6886=SelYear)*(Data_Heathrow!$I$2:$I$6886<>"")*((Data_Heathrow!$I$2:$I$6886+Climate_Shift+Optimise!D27-CDD_Base)>0)*(Data_Heathrow!$I$2:$I$6886+Climate_Shift+Optimise!D27-CDD_Base)) -> 47.45 | D19: =SUMPRODUCT((Data_Heathrow!$B$2:$B$6886=SelYear)*(Data_Heathrow!$I$2:$I$6886<>"")*((Data_Heathrow!$I$2:$I$6886+Climate_Shift+Optimise!E27-CDD_Base)>0)*(Data_Heathrow!$I$2:$I$6886+Climate_Shift+Optimise!E27-CDD_Base)) -> 47.45
B20: Population-weighted CDD | C20: =SUMPRODUCT(Optimise!$C$24:$C$27,C16:C19) -> 102.7225 | D20: =SUMPRODUCT(Optimise!$C$24:$C$27,D16:D19) -> 84.26125
B22: 3. Carbon
B23: Metric | C23: Baseline | D23: Portfolio
B24: AC households | C24: =Households*AC_Pen -> 180000 | D24: =Households*(AC_Pen+Opt_AC_Extra) -> 180000
B25: Cooling electricity (MWh) | C25: =C24*kWh_CDD*C20/1000 -> 27735.075 | D25: =D24*kWh_CDD*D20/1000 -> 22750.537
B26: Net cooling emissions tCO₂e — baseline | C26: =C25*Grid_CF -> 4160.2612
B27: Net cooling emissions tCO₂e — portfolio (incl. sequestration, AI compute) | C27: =D25*Grid_CF-Optimise!C6*Green_Seq+Optimise!C10*Retrains*kWh_Retrain*Grid_CF/1000 -> 2412.5904
B28: AI/MLOps compute emissions tCO₂e | C28: =Optimise!C10*Retrains*kWh_Retrain*Grid_CF/1000 -> 0.00975
B29: Emissions in the scenario selected on the Control Panel | C29: =IF(Mit_On=1,C27,C26) -> 4160.2612
B31: Systems prompt: AC rejects heat outdoors, worsening the street-level UHI for people without AC — a reinforcing loop. Draw the causal loop diagram (DCP systems thinking) before choosing the portfolio.

Sheet Optimise
A1: Optimise — choose an intervention portfolio within budget
A2: Set implementation levels (0–100%). Switch the Control Panel scenario to 'With interventions' to push these effects through every sheet. Solver-ready: maximise C33 subject to C29 ≤ Budget, levels between 0 and 1.
B4: 1. Interventions
B5: Intervention | C5: Level (0–1) | D5: Day UHI cut at 100% | E5: Night UHI cut at 100% | F5: Sensitivity cut at 100% | G5: Cost at 100% £m | H5: Cost £m | I5: What it represents | J5: Extra AC households at 100%
B6: Urban greening and tree canopy | C6: 0.5 | D6: 0.35 | E6: 0.4 | F6: 0 | G6: 40 | H6: =C6*G6 -> 20 | I6: Nature-based solution; co-benefits for biodiversity and flood risk. | J6: 0
B7: Cool and reflective roofs (social housing) | C7: 0.5 | D7: 0.25 | E7: 0.15 | F7: 0 | G7: 25 | H7: =C7*G7 -> 12.5 | I7: Reduces solar gain; strongest effect in dense housing. | J7: 0
B8: Cooling centres and community outreach | C8: 0.5 | D8: 0 | E8: 0 | F8: 0.25 | G8: 3 | H8: =C8*G8 -> 1.5 | I8: Targets people with low adaptive capacity; relies on trusted community partners. | J8: 0
B9: Neighbourhood sensor network (local alerting) | C9: 0.5 | D9: 0 | E9: 0 | F9: 0 | G9: 2 | H9: =C9*G9 -> 1 | I9: ≥50% switches AI alerting from one reference station to local typology data. | J9: 0
B10: MLOps: rolling 20-year retraining with drift gates | C10: 0.5 | D10: 0 | E10: 0 | F10: 0 | G10: 0.5 | H10: =C10*G10 -> 0.25 | I10: ≥50% replaces the manual training window with a rolling one ending last year. | J10: 0
B11: Domestic air-conditioning subsidy | C11: 0 | D11: 0 | E11: 0 | F11: 0.3 | G11: 15 | H11: =C11*G11 -> 0 | I11: Effective for health, but adds electricity demand, heat rejection and carbon. | J11: 0.2
B12: Effect-size and cost values are teaching assumptions — evidence or challenge them.
B14: 2. Combined effects (feed Control Panel when scenario = 'With interventions')
B15: Daytime UHI reduction fraction | C15: =MIN(0.9,SUMPRODUCT(C6:C11,D6:D11)) -> 0.3
B16: Night-time UHI reduction fraction | C16: =MIN(0.9,SUMPRODUCT(C6:C11,E6:E11)) -> 0.275
B17: Health sensitivity reduction | C17: =1-(1-C8*F8)*(1-C11*F11) -> 0.125
B18: Sensor network level | C18: =C9 -> 0.5
B19: Retraining governance level | C19: =C10 -> 0.5
B20: Extra share of households with AC | C20: =C11*J11 -> 0
B22: 3. Outcomes — baseline vs this portfolio (selected year, London-wide)
B23: Typology | C23: Pop. share | D23: Base uplift (mean) °C | E23: Mitigated uplift °C | F23: Base °C·days | G23: Mitigated °C·days
B24: =Equity_Lens!B6 -> Reference: Heathrow station | C24: =Equity_Lens!E6 -> 0 | D24: =(Equity_Lens!C6+Equity_Lens!D6)/2 -> 0 | E24: =((Equity_Lens!C6-Opt_Day_Frac*MAX(0,Equity_Lens!C6))+(Equity_Lens!D6-Opt_Night_Frac*MAX(0,Equity_Lens!D6)))/2 -> 0 | F24: =SUMPRODUCT((Data_Heathrow!$B$2:$B$6886=SelYear)*(Data_Heathrow!$I$2:$I$6886<>"")*((Data_Heathrow!$I$2:$I$6886+Climate_Shift+D24-T_Mort)>0)*(Data_Heathrow!$I$2:$I$6886+Climate_Shift+D24-T_Mort)) -> 124.5 | G24: =SUMPRODUCT((Data_Heathrow!$B$2:$B$6886=SelYear)*(Data_Heathrow!$I$2:$I$6886<>"")*((Data_Heathrow!$I$2:$I$6886+Climate_Shift+E24-T_Mort)>0)*(Data_Heathrow!$I$2:$I$6886+Climate_Shift+E24-T_Mort)) -> 124.5
B25: =Equity_Lens!B7 -> Inner London: dense, low green | C25: =Equity_Lens!E7 -> 0.3 | D25: =(Equity_Lens!C7+Equity_Lens!D7)/2 -> 3 | E25: =((Equity_Lens!C7-Opt_Day_Frac*MAX(0,Equity_Lens!C7))+(Equity_Lens!D7-Opt_Night_Frac*MAX(0,Equity_Lens!D7)))/2 -> 2.15 | F25: =SUMPRODUCT((Data_Heathrow!$B$2:$B$6886=SelYear)*(Data_Heathrow!$I$2:$I$6886<>"")*((Data_Heathrow!$I$2:$I$6886+Climate_Shift+D25-T_Mort)>0)*(Data_Heathrow!$I$2:$I$6886+Climate_Shift+D25-T_Mort)) -> 336.6 | G25: =SUMPRODUCT((Data_Heathrow!$B$2:$B$6886=SelYear)*(Data_Heathrow!$I$2:$I$6886<>"")*((Data_Heathrow!$I$2:$I$6886+Climate_Shift+E25-T_Mort)>0)*(Data_Heathrow!$I$2:$I$6886+Climate_Shift+E25-T_Mort)) -> 262.75
B26: =Equity_Lens!B8 -> Outer London: suburban | C26: =Equity_Lens!E8 -> 0.55 | D26: =(Equity_Lens!C8+Equity_Lens!D8)/2 -> 0.75 | E26: =((Equity_Lens!C8-Opt_Day_Frac*MAX(0,Equity_Lens!C8))+(Equity_Lens!D8-Opt_Night_Frac*MAX(0,Equity_Lens!D8)))/2 -> 0.5375 | F26: =SUMPRODUCT((Data_Heathrow!$B$2:$B$6886=SelYear)*(Data_Heathrow!$I$2:$I$6886<>"")*((Data_Heathrow!$I$2:$I$6886+Climate_Shift+D26-T_Mort)>0)*(Data_Heathrow!$I$2:$I$6886+Climate_Shift+D26-T_Mort)) -> 165.75 | G26: =SUMPRODUCT((Data_Heathrow!$B$2:$B$6886=SelYear)*(Data_Heathrow!$I$2:$I$6886<>"")*((Data_Heathrow!$I$2:$I$6886+Climate_Shift+E26-T_Mort)>0)*(Data_Heathrow!$I$2:$I$6886+Climate_Shift+E26-T_Mort)) -> 153.4
B27: =Equity_Lens!B9 -> Green & blue corridors | C27: =Equity_Lens!E9 -> 0.15 | D27: =(Equity_Lens!C9+Equity_Lens!D9)/2 -> -0.25 | E27: =((Equity_Lens!C9-Opt_Day_Frac*MAX(0,Equity_Lens!C9))+(Equity_Lens!D9-Opt_Night_Frac*MAX(0,Equity_Lens!D9)))/2 -> -0.25 | F27: =SUMPRODUCT((Data_Heathrow!$B$2:$B$6886=SelYear)*(Data_Heathrow!$I$2:$I$6886<>"")*((Data_Heathrow!$I$2:$I$6886+Climate_Shift+D27-T_Mort)>0)*(Data_Heathrow!$I$2:$I$6886+Climate_Shift+D27-T_Mort)) -> 112.65 | G27: =SUMPRODUCT((Data_Heathrow!$B$2:$B$6886=SelYear)*(Data_Heathrow!$I$2:$I$6886<>"")*((Data_Heathrow!$I$2:$I$6886+Climate_Shift+E27-T_Mort)>0)*(Data_Heathrow!$I$2:$I$6886+Climate_Shift+E27-T_Mort)) -> 112.65
B29: Total portfolio cost £m | C29: =SUM(H6:H11) -> 35.25
B30: Within budget? | C30: =IF(C29<=Budget,"Yes","NO — over budget") -> Yes
B31: Excess deaths — baseline | C31: =Beta*SUMPRODUCT(C24:C27,F24:F27) -> 387
B32: Excess deaths — with portfolio | C32: =Beta*(1-Opt_Sens_Red)*SUMPRODUCT(C24:C27,G24:G27) -> 291.73279
B33: Deaths averted (objective to maximise) | C33: =C31-C32 -> 95.267208
B34: Cost per death averted £m | C34: =IFERROR(C29/C33,"n/a") -> 0.37001189
B35: Net cooling carbon change tCO₂e (from Sustainability) | C35: =Sustainability!C27-Sustainability!C26 -> -1747.6709
B36: Within carbon budget? (portfolio) | C36: =IF(Sustainability!C27<=Carbon_Budget,"Yes","NO") -> Yes
B38: Trade-off prompt (BE Finance; RRR decision making): rank portfolios by cost per death averted, carbon and equity (Equity_Lens rank changes). Is the 'optimal' answer acceptable to every stakeholder? Effectiveness = correctness × acceptance.

Sheet Risk_Register
A1: Risk_Register — the Project Simulation template, extended for monitoring and control
A2: Columns B–L follow the module's Risk Register Template. Columns M–R make the register live: each risk has a KRI, a trigger and a link to the requirement it feeds.
B4: Risk no | C4: Risk description | D4: Date when occurred | E4: Probability | F4: Impact | G4: Severity (p x i) | H4: Owner | I4: Mitigation strategy | J4: Proability after mitigation | K4: Impact after mitigation | L4: Comments | M4: Key risk indicator (KRI) | N4: Trigger rule | O4: Current value | P4: Triggered? | Q4: RAG | R4: Feeds requirement | S4: Residual severity
B5: R1 | C5: Persistent anticyclone (heat dome) causes a prolonged heatwave across London | D5: =First_HW -> 44728 | E5: =HW_Prob -> 5 | F5: 5 | G5: =E5*F5 -> 25 | H5: Resilience lead | I5: Heat plan activation; cooling centres; greening | J5: 3 | K5: 4 | L5: Probability is data-driven: years in the last decade with ≥10 hot days. | M5: Longest hot-day run | N5: ≥ HW_Days | O5: =KPI_MaxRun -> 9 | P5: =IF(KPI_MaxRun>=HW_Days,1,0) -> 1 | Q5: =IF(P5=1,"RED",IF(G5>=12,"AMBER","GREEN")) -> RED | R5: REQ-HAZ-01 | S5: =J5*K5 -> 12
B6: R2 | C6: Warm nights (UHI) prevent recovery; heat stress accumulates until services tip | D6: =First_Tip -> 44760 | E6: 4 | F6: 5 | G6: =E6*F6 -> 20 | H6: Health & social care lead | I6: Night-time cooling (roofs, greening); surge staffing | J6: 3 | K6: 3 | L6: Stock-and-flow model on Tipping_Points. | M6: Tipping days | N6: > 0 | O6: =KPI_TipDays -> 3 | P6: =IF(KPI_TipDays>0,1,0) -> 1 | Q6: =IF(P6=1,"RED",IF(G6>=12,"AMBER","GREEN")) -> RED | R6: REQ-RES-01 | S6: =J6*K6 -> 9
B7: R3 | C7: Heat-related excess deaths exceed the board's risk appetite | E7: 4 | F7: 5 | G7: =E7*F7 -> 20 | H7: Director of Public Health | I7: Targeted outreach to people with low adaptive capacity | J7: 3 | K7: 4 | L7: Calibrated to UKHSA 2022 London estimate. | M7: London excess deaths (model) | N7: > Deaths_Appetite | O7: =London_Deaths -> 387 | P7: =IF(London_Deaths>Deaths_Appetite,1,0) -> 1 | Q7: =IF(P7=1,"RED",IF(G7>=12,"AMBER","GREEN")) -> RED | R7: REQ-HLT-01 | S7: =J7*K7 -> 12
B8: R4 | C8: AI forecast drifts as the climate moves away from its training data, causing under-warning | D8: =First_Drift -> 44760 | E8: 3 | F8: 4 | G8: =E8*F8 -> 12 | H8: MLOps lead | I8: Drift gates (CUSUM, MAE); rolling retraining; human review | J8: 2 | K8: 3 | L8: Concept drift (climate) vs data drift (sensor). Which is it? | M8: Drift-alarm events | N8: > 0 | O8: =KPI_DriftDays -> 2 | P8: =IF(KPI_DriftDays>0,1,0) -> 1 | Q8: =IF(P8=1,"RED",IF(G8>=12,"AMBER","GREEN")) -> RED | R8: REQ-AI-01 | S8: =J8*K8 -> 6
B9: R5 | C9: AI misses actual hot days (low recall) at the alert threshold | E9: 3 | F9: 4 | G9: =E9*F9 -> 12 | H9: Product owner (alerts) | I9: Optimise threshold; tail-focused validation; local features | J9: 2 | K9: 3 | L9: Average accuracy hides tail failure. | M9: AI hot-day recall | N9: < Recall_Target | O9: =KPI_Recall -> 0.36585366 | P9: =IF(ISNUMBER(KPI_Recall),IF(KPI_Recall<Recall_Target,1,0),0) -> 1 | Q9: =IF(P9=1,"RED",IF(G9>=12,"AMBER","GREEN")) -> RED | R9: REQ-AI-02 | S9: =J9*K9 -> 6
B10: R6 | C10: Sensor or data-quality failure at the peak of the event (e.g. 19 Jul 2022 suspect max) | E10: 3 | F10: 4 | G10: =E10*F10 -> 12 | H10: Data engineering lead | I10: Redundant stations; automated QA rules; imputation with flagging | J10: 2 | K10: 2 | L10: Compare QA policies on the Control Panel. | M10: Suspect obs on hot/warm days | N10: > 0 | O10: =KPI_SuspectHot -> 5 | P10: =IF(KPI_SuspectHot>0,1,0) -> 1 | Q10: =IF(P10=1,"RED",IF(G10>=12,"AMBER","GREEN")) -> RED | R10: REQ-DAT-01 | S10: =J10*K10 -> 4
B11: R7 | C11: Single reference station under-warns dense, low-green, often deprived neighbourhoods | D11: =First_Gap -> 44697 | E11: 4 | F11: 4 | G11: =E11*F11 -> 16 | H11: Equality, diversity & inclusion lead | I11: Neighbourhood sensor network; co-designed thresholds | J11: 2 | K11: 3 | L11: Representation bias in data = inequitable alerts. | M11: Representation-gap days | N11: > 0 | O11: =KPI_RepGap -> 19 | P11: =IF(KPI_RepGap>0,1,0) -> 1 | Q11: =IF(P11=1,"RED",IF(G11>=12,"AMBER","GREEN")) -> RED | R11: REQ-EQ-01 | S11: =J11*K11 -> 6
B12: R8 | C12: Adaptation relies on air conditioning, increasing carbon and outdoor heat (maladaptation) | E12: 3 | F12: 3 | G12: =E12*F12 -> 9 | H12: Sustainability lead | I12: Prioritise nature-based and passive cooling | J12: 2 | K12: 2 | L12: See Sustainability sheet. | M12: Cooling carbon tCO₂e | N12: > Carbon_Budget | O12: =Carbon_Now -> 4160.2612 | P12: =IF(Carbon_Now>Carbon_Budget,1,0) -> 0 | Q12: =IF(P12=1,"RED",IF(G12>=12,"AMBER","GREEN")) -> GREEN | R12: REQ-SUS-01 | S12: =J12*K12 -> 4
B13: R9 | C13: Intervention portfolio exceeds budget | E13: 2 | F13: 3 | G13: =E13*F13 -> 6 | H13: Programme manager | I13: Phase delivery; Solver-based portfolio selection | J13: 1 | K13: 3 | L13: Contract and incentive choice (ILO6). | M13: Portfolio cost £m | N13: > Budget | O13: =Optimise!C29 -> 35.25 | P13: =IF(Optimise!C29>Budget,1,0) -> 0 | Q13: =IF(P13=1,"RED",IF(G13>=12,"AMBER","GREEN")) -> GREEN | R13: REQ-PRG-01 | S13: =J13*K13 -> 3
B15: Scales: Probability and Impact 1 (very low) to 5 (very high). Row 5 is a worked example; students complete and challenge the rest.
B16: Template header 'Proability after mitigation' kept exactly as in the module template.

Sheet Req_Feedback
A1: Req_Feedback — monitoring and control as the first step of requirements engineering
A2: When a KRI triggers, the loop raises a change request. Requirement text regenerates with the current thresholds, so optimising a threshold rewrites the requirement.
B4: Req ID | C4: Source risk | D4: Trigger status | E4: Requirement statement (shall) | F4: Type | G4: Verification method | H4: Model / simulation link | I4: MoSCoW (group) | J4: Challenge raised (disagreeing well) | K4: Resolution and rationale | L4: Owner
B5: REQ-HAZ-01 | C5: R1 | D5: =IF(Risk_Register!P5=1,"CHANGE REQUEST RAISED","Baseline — monitor") -> CHANGE REQUEST RAISED | E5: ="The alert service shall issue an Amber alert when the local daily maximum is ≥ "&TEXT(T_Day,"0.0")&"°C for ≥ "&HW_Days&" consecutive days and the night minimum is ≥ "&TEXT(T_Night,"0.0")&"°C." -> The alert service shall issue an Amber alert when the local daily maximum is ≥ 28.0°C for ≥ 3 consecutive days and the night minimum is ≥ 18.0°C. | F5: Functional | G5: Back-test against 1979–2023 events; witness test | H5: Threshold sweep (Tipping_Points §1) | I5: Must | J5: e.g. Should the threshold be lower for inner London? | K5: e.g. Agreed typology-specific thresholds; evidence from rep. gap days
B6: REQ-RES-01 | C6: R2 | D6: =IF(Risk_Register!P6=1,"CHANGE REQUEST RAISED","Baseline — monitor") -> CHANGE REQUEST RAISED | E6: ="Health and transport services shall maintain surge capacity sufficient for a heat-stress stock of "&TEXT(MAX(Capacity,KPI_PeakStock)*1.2,"0")&" °C·days (peak + 20% margin)." -> Health and transport services shall maintain surge capacity sufficient for a heat-stress stock of 55 °C·days (peak + 20% margin). | F6: Performance | G6: Simulation; exercise (table-top) | H6: Stock-and-flow tipping model
B7: REQ-HLT-01 | C7: R3 | D7: =IF(Risk_Register!P7=1,"CHANGE REQUEST RAISED","Baseline — monitor") -> CHANGE REQUEST RAISED | E7: ="The programme shall keep modelled London heat-related excess deaths below "&Deaths_Appetite&" per summer under a +"&TEXT(Climate_Shift,"0.0")&"°C scenario." -> The programme shall keep modelled London heat-related excess deaths below 150 per summer under a +0.0°C scenario. | F7: Outcome | G7: Annual review vs UKHSA heat mortality reports | H7: Exposure–response model (Equity_Lens)
B8: REQ-AI-01 | C8: R4 | D8: =IF(Risk_Register!P8=1,"CHANGE REQUEST RAISED","Baseline — monitor") -> CHANGE REQUEST RAISED | E8: ="The forecasting model shall raise a drift alarm when CUSUM exceeds "&TEXT(CUSUM_h,"0")&"°C or 7-day MAE exceeds "&TEXT(MAE_Tol,"0.0")&"°C, and shall be retrained on a window ending no earlier than the previous year." -> The forecasting model shall raise a drift alarm when CUSUM exceeds 15°C or 7-day MAE exceeds 4.5°C, and shall be retrained on a window ending no earlier than the previous year. | F8: AI/MLOps | G8: Monitoring dashboard; model card; audit log | H8: CUSUM drift detection (Monitor_Control)
B9: REQ-AI-02 | C9: R5 | D9: =IF(Risk_Register!P9=1,"CHANGE REQUEST RAISED","Baseline — monitor") -> CHANGE REQUEST RAISED | E9: ="The AI alert shall achieve hot-day recall ≥ "&TEXT(Recall_Target,"0%")&" at the operational threshold, validated on the most recent unseen summer." -> The AI alert shall achieve hot-day recall ≥ 80% at the operational threshold, validated on the most recent unseen summer. | F9: AI/MLOps | G9: Hold-out test; confusion matrix | H9: Recall vs threshold sweep
B10: REQ-DAT-01 | C10: R6 | D10: =IF(Risk_Register!P10=1,"CHANGE REQUEST RAISED","Baseline — monitor") -> CHANGE REQUEST RAISED | E10: ="Observations shall pass automated QA (flag checks and TX ≥ TG) before use; suspect values shall be "&IF(QA_Policy="Use raw","flagged and reviewed",LOWER(QA_Policy))&" with provenance recorded." -> Observations shall pass automated QA (flag checks and TX ≥ TG) before use; suspect values shall be flagged and reviewed with provenance recorded. | F10: Data | G10: Data-quality tests in pipeline | H10: QA policy comparison
B11: REQ-EQ-01 | C11: R7 | D11: =IF(Risk_Register!P11=1,"CHANGE REQUEST RAISED","Baseline — monitor") -> CHANGE REQUEST RAISED | E11: ="Alerts shall be computed at neighbourhood level so that no typology experiences more than 0 representation-gap days per summer (current: "&KPI_RepGap&")." -> Alerts shall be computed at neighbourhood level so that no typology experiences more than 0 representation-gap days per summer (current: 19). | F11: Fairness / D&I | G11: Equity audit with community partners | H11: Equity_Lens rep. gap and missed alerts
B12: REQ-SUS-01 | C12: R8 | D12: =IF(Risk_Register!P12=1,"CHANGE REQUEST RAISED","Baseline — monitor") -> Baseline — monitor | E12: ="Net cooling-related emissions from the portfolio shall not exceed "&TEXT(Carbon_Budget,"#,##0")&" tCO₂e per summer." -> Net cooling-related emissions from the portfolio shall not exceed 20,000 tCO₂e per summer. | F12: Sustainability | G12: Carbon accounting (DESNZ factors) | H12: Sustainability sheet
B13: REQ-PRG-01 | C13: R9 | D13: =IF(Risk_Register!P13=1,"CHANGE REQUEST RAISED","Baseline — monitor") -> Baseline — monitor | E13: ="The intervention portfolio shall be delivered within £"&TEXT(Budget,"0.0")&"m." -> The intervention portfolio shall be delivered within £50.0m. | F13: Programme | G13: Earned value / cost reporting | H13: Optimise (Solver)
B15: Change requests raised: | D15: =COUNTIF(D5:D13,"CHANGE REQUEST RAISED") -> 7
B16: Row 5 shows example group entries in columns I–K. Each group logs at least two genuine disagreements and how they were resolved.

Sheet Annual_Trend
A1: Annual_Trend — the moving baseline (1979–2023), selected typology and thresholds
A2: Shows why yesterday's thresholds and models go stale: hot days rise and the model trained on a cooler past drifts.
B4: Year | C4: In training window | D4: Hot days | E4: Warm nights | F4: Max TX °C | G4: Mean residual °C | H4: MAE °C | I4: MAE on hot days °C | J4: Suspect obs | K4: Years ≥10 hot days (rolling 10-yr)
B5: 1979 | C5: =IF(AND(B5>=Train_Start,B5<=Train_End),1,0) -> 1 | D5: =COUNTIFS(Data_Heathrow!$B$2:$B$6886,B5,Data_Heathrow!$E$2:$E$6886,">="&(T_Day-Climate_Shift-UHI_Day_Eff)) -> 8 | E5: =COUNTIFS(Data_Heathrow!$B$2:$B$6886,B5,Data_Heathrow!$G$2:$G$6886,">="&(T_Night-Climate_Shift-UHI_Night_Eff)) -> 27 | F5: =_xlfn.MAXIFS(Data_Heathrow!$E$2:$E$6886,Data_Heathrow!$B$2:$B$6886,B5)+Climate_Shift+UHI_Day_Eff -> 31.9 | G5: =IFERROR(AVERAGEIFS(Data_Heathrow!$U$2:$U$6886,Data_Heathrow!$B$2:$B$6886,B5),"") -> -0.29094866 | H5: =IFERROR(AVERAGEIFS(Data_Heathrow!$W$2:$W$6886,Data_Heathrow!$B$2:$B$6886,B5),"") -> 1.723513 | I5: =IFERROR(AVERAGEIFS(Data_Heathrow!$W$2:$W$6886,Data_Heathrow!$B$2:$B$6886,B5,Data_Heathrow!$E$2:$E$6886,">="&T_Day),"") -> 3.6555578 | J5: =SUMIFS(Data_Heathrow!$Q$2:$Q$6886,Data_Heathrow!$B$2:$B$6886,B5) -> 3 | K5: =COUNTIF(D5:D5,">=10") -> 0
B6: 1980 | C6: =IF(AND(B6>=Train_Start,B6<=Train_End),1,0) -> 1 | D6: =COUNTIFS(Data_Heathrow!$B$2:$B$6886,B6,Data_Heathrow!$E$2:$E$6886,">="&(T_Day-Climate_Shift-UHI_Day_Eff)) -> 4 | E6: =COUNTIFS(Data_Heathrow!$B$2:$B$6886,B6,Data_Heathrow!$G$2:$G$6886,">="&(T_Night-Climate_Shift-UHI_Night_Eff)) -> 26 | F6: =_xlfn.MAXIFS(Data_Heathrow!$E$2:$E$6886,Data_Heathrow!$B$2:$B$6886,B6)+Climate_Shift+UHI_Day_Eff -> 31 | G6: =IFERROR(AVERAGEIFS(Data_Heathrow!$U$2:$U$6886,Data_Heathrow!$B$2:$B$6886,B6),"") -> -0.15816368 | H6: =IFERROR(AVERAGEIFS(Data_Heathrow!$W$2:$W$6886,Data_Heathrow!$B$2:$B$6886,B6),"") -> 1.827928 | I6: =IFERROR(AVERAGEIFS(Data_Heathrow!$W$2:$W$6886,Data_Heathrow!$B$2:$B$6886,B6,Data_Heathrow!$E$2:$E$6886,">="&T_Day),"") -> 3.7994842 | J6: =SUMIFS(Data_Heathrow!$Q$2:$Q$6886,Data_Heathrow!$B$2:$B$6886,B6) -> 6 | K6: =COUNTIF(D5:D6,">=10") -> 0
B7: 1981 | C7: =IF(AND(B7>=Train_Start,B7<=Train_End),1,0) -> 1 | D7: =COUNTIFS(Data_Heathrow!$B$2:$B$6886,B7,Data_Heathrow!$E$2:$E$6886,">="&(T_Day-Climate_Shift-UHI_Day_Eff)) -> 11 | E7: =COUNTIFS(Data_Heathrow!$B$2:$B$6886,B7,Data_Heathrow!$G$2:$G$6886,">="&(T_Night-Climate_Shift-UHI_Night_Eff)) -> 29 | F7: =_xlfn.MAXIFS(Data_Heathrow!$E$2:$E$6886,Data_Heathrow!$B$2:$B$6886,B7)+Climate_Shift+UHI_Day_Eff -> 30.8 | G7: =IFERROR(AVERAGEIFS(Data_Heathrow!$U$2:$U$6886,Data_Heathrow!$B$2:$B$6886,B7),"") -> -0.053753542 | H7: =IFERROR(AVERAGEIFS(Data_Heathrow!$W$2:$W$6886,Data_Heathrow!$B$2:$B$6886,B7),"") -> 1.8462455 | I7: =IFERROR(AVERAGEIFS(Data_Heathrow!$W$2:$W$6886,Data_Heathrow!$B$2:$B$6886,B7,Data_Heathrow!$E$2:$E$6886,">="&T_Day),"") -> 2.3677106 | J7: =SUMIFS(Data_Heathrow!$Q$2:$Q$6886,Data_Heathrow!$B$2:$B$6886,B7) -> 5 | K7: =COUNTIF(D5:D7,">=10") -> 1
B8: 1982 | C8: =IF(AND(B8>=Train_Start,B8<=Train_End),1,0) -> 1 | D8: =COUNTIFS(Data_Heathrow!$B$2:$B$6886,B8,Data_Heathrow!$E$2:$E$6886,">="&(T_Day-Climate_Shift-UHI_Day_Eff)) -> 18 | E8: =COUNTIFS(Data_Heathrow!$B$2:$B$6886,B8,Data_Heathrow!$G$2:$G$6886,">="&(T_Night-Climate_Shift-UHI_Night_Eff)) -> 40 | F8: =_xlfn.MAXIFS(Data_Heathrow!$E$2:$E$6886,Data_Heathrow!$B$2:$B$6886,B8)+Climate_Shift+UHI_Day_Eff -> 31.3 | G8: =IFERROR(AVERAGEIFS(Data_Heathrow!$U$2:$U$6886,Data_Heathrow!$B$2:$B$6886,B8),"") -> 0.032059416 | H8: =IFERROR(AVERAGEIFS(Data_Heathrow!$W$2:$W$6886,Data_Heathrow!$B$2:$B$6886,B8),"") -> 1.8179496 | I8: =IFERROR(AVERAGEIFS(Data_Heathrow!$W$2:$W$6886,Data_Heathrow!$B$2:$B$6886,B8,Data_Heathrow!$E$2:$E$6886,">="&T_Day),"") -> 3.3828012 | J8: =SUMIFS(Data_Heathrow!$Q$2:$Q$6886,Data_Heathrow!$B$2:$B$6886,B8) -> 7 | K8: =COUNTIF(D5:D8,">=10") -> 2
B9: 1983 | C9: =IF(AND(B9>=Train_Start,B9<=Train_End),1,0) -> 1 | D9: =COUNTIFS(Data_Heathrow!$B$2:$B$6886,B9,Data_Heathrow!$E$2:$E$6886,">="&(T_Day-Climate_Shift-UHI_Day_Eff)) -> 34 | E9: =COUNTIFS(Data_Heathrow!$B$2:$B$6886,B9,Data_Heathrow!$G$2:$G$6886,">="&(T_Night-Climate_Shift-UHI_Night_Eff)) -> 48 | F9: =_xlfn.MAXIFS(Data_Heathrow!$E$2:$E$6886,Data_Heathrow!$B$2:$B$6886,B9)+Climate_Shift+UHI_Day_Eff -> 34.8 | G9: =IFERROR(AVERAGEIFS(Data_Heathrow!$U$2:$U$6886,Data_Heathrow!$B$2:$B$6886,B9),"") -> 0.14798132 | H9: =IFERROR(AVERAGEIFS(Data_Heathrow!$W$2:$W$6886,Data_Heathrow!$B$2:$B$6886,B9),"") -> 1.8673987 | I9: =IFERROR(AVERAGEIFS(Data_Heathrow!$W$2:$W$6886,Data_Heathrow!$B$2:$B$6886,B9,Data_Heathrow!$E$2:$E$6886,">="&T_Day),"") -> 2.5314998 | J9: =SUMIFS(Data_Heathrow!$Q$2:$Q$6886,Data_Heathrow!$B$2:$B$6886,B9) -> 5 | K9: =COUNTIF(D5:D9,">=10") -> 3
B10: 1984 | C10: =IF(AND(B10>=Train_Start,B10<=Train_End),1,0) -> 1 | D10: =COUNTIFS(Data_Heathrow!$B$2:$B$6886,B10,Data_Heathrow!$E$2:$E$6886,">="&(T_Day-Climate_Shift-UHI_Day_Eff)) -> 23 | E10: =COUNTIFS(Data_Heathrow!$B$2:$B$6886,B10,Data_Heathrow!$G$2:$G$6886,">="&(T_Night-Climate_Shift-UHI_Night_Eff)) -> 39 | F10: =_xlfn.MAXIFS(Data_Heathrow!$E$2:$E$6886,Data_Heathrow!$B$2:$B$6886,B10)+Climate_Shift+UHI_Day_Eff -> 33.7 | G10: =IFERROR(AVERAGEIFS(Data_Heathrow!$U$2:$U$6886,Data_Heathrow!$B$2:$B$6886,B10),"") -> 0.086603964 | H10: =IFERROR(AVERAGEIFS(Data_Heathrow!$W$2:$W$6886,Data_Heathrow!$B$2:$B$6886,B10),"") -> 1.9289597 | I10: =IFERROR(AVERAGEIFS(Data_Heathrow!$W$2:$W$6886,Data_Heathrow!$B$2:$B$6886,B10,Data_Heathrow!$E$2:$E$6886,">="&T_Day),"") -> 2.507676 | J10: =SUMIFS(Data_Heathrow!$Q$2:$Q$6886,Data_Heathrow!$B$2:$B$6886,B10) -> 7 | K10: =COUNTIF(D5:D10,">=10") -> 4
B11: 1985 | C11: =IF(AND(B11>=Train_Start,B11<=Train_End),1,0) -> 1 | D11: =COUNTIFS(Data_Heathrow!$B$2:$B$6886,B11,Data_Heathrow!$E$2:$E$6886,">="&(T_Day-Climate_Shift-UHI_Day_Eff)) -> 8 | E11: =COUNTIFS(Data_Heathrow!$B$2:$B$6886,B11,Data_Heathrow!$G$2:$G$6886,">="&(T_Night-Climate_Shift-UHI_Night_Eff)) -> 18 | F11: =_xlfn.MAXIFS(Data_Heathrow!$E$2:$E$6886,Data_Heathrow!$B$2:$B$6886,B11)+Climate_Shift+UHI_Day_Eff -> 31.8 | G11: =IFERROR(AVERAGEIFS(Data_Heathrow!$U$2:$U$6886,Data_Heathrow!$B$2:$B$6886,B11),"") -> -0.085248236 | H11: =IFERROR(AVERAGEIFS(Data_Heathrow!$W$2:$W$6886,Data_Heathrow!$B$2:$B$6886,B11),"") -> 1.7344764 | I11: =IFERROR(AVERAGEIFS(Data_Heathrow!$W$2:$W$6886,Data_Heathrow!$B$2:$B$6886,B11,Data_Heathrow!$E$2:$E$6886,">="&T_Day),"") -> 4.3300472 | J11: =SUMIFS(Data_Heathrow!$Q$2:$Q$6886,Data_Heathrow!$B$2:$B$6886,B11) -> 6 | K11: =COUNTIF(D5:D11,">=10") -> 4
B12: 1986 | C12: =IF(AND(B12>=Train_Start,B12<=Train_End),1,0) -> 1 | D12: =COUNTIFS(Data_Heathrow!$B$2:$B$6886,B12,Data_Heathrow!$E$2:$E$6886,">="&(T_Day-Climate_Shift-UHI_Day_Eff)) -> 12 | E12: =COUNTIFS(Data_Heathrow!$B$2:$B$6886,B12,Data_Heathrow!$G$2:$G$6886,">="&(T_Night-Climate_Shift-UHI_Night_Eff)) -> 23 | F12: =_xlfn.MAXIFS(Data_Heathrow!$E$2:$E$6886,Data_Heathrow!$B$2:$B$6886,B12)+Climate_Shift+UHI_Day_Eff -> 32.6 | G12: =IFERROR(AVERAGEIFS(Data_Heathrow!$U$2:$U$6886,Data_Heathrow!$B$2:$B$6886,B12),"") -> -0.27371564 | H12: =IFERROR(AVERAGEIFS(Data_Heathrow!$W$2:$W$6886,Data_Heathrow!$B$2:$B$6886,B12),"") -> 1.7847553 | I12: =IFERROR(AVERAGEIFS(Data_Heathrow!$W$2:$W$6886,Data_Heathrow!$B$2:$B$6886,B12,Data_Heathrow!$E$2:$E$6886,">="&T_Day),"") -> 2.1360353 | J12: =SUMIFS(Data_Heathrow!$Q$2:$Q$6886,Data_Heathrow!$B$2:$B$6886,B12) -> 7 | K12: =COUNTIF(D5:D12,">=10") -> 5
B13: 1987 | C13: =IF(AND(B13>=Train_Start,B13<=Train_End),1,0) -> 1 | D13: =COUNTIFS(Data_Heathrow!$B$2:$B$6886,B13,Data_Heathrow!$E$2:$E$6886,">="&(T_Day-Climate_Shift-UHI_Day_Eff)) -> 9 | E13: =COUNTIFS(Data_Heathrow!$B$2:$B$6886,B13,Data_Heathrow!$G$2:$G$6886,">="&(T_Night-Climate_Shift-UHI_Night_Eff)) -> 25 | F13: =_xlfn.MAXIFS(Data_Heathrow!$E$2:$E$6886,Data_Heathrow!$B$2:$B$6886,B13)+Climate_Shift+UHI_Day_Eff -> 31.2 | G13: =IFERROR(AVERAGEIFS(Data_Heathrow!$U$2:$U$6886,Data_Heathrow!$B$2:$B$6886,B13),"") -> -0.24704752 | H13: =IFERROR(AVERAGEIFS(Data_Heathrow!$W$2:$W$6886,Data_Heathrow!$B$2:$B$6886,B13),"") -> 1.9099758 | I13: =IFERROR(AVERAGEIFS(Data_Heathrow!$W$2:$W$6886,Data_Heathrow!$B$2:$B$6886,B13,Data_Heathrow!$E$2:$E$6886,">="&T_Day),"") -> 2.7301948 | J13: =SUMIFS(Data_Heathrow!$Q$2:$Q$6886,Data_Heathrow!$B$2:$B$6886,B13) -> 9 | K13: =COUNTIF(D5:D13,">=10") -> 5
B14: 1988 | C14: =IF(AND(B14>=Train_Start,B14<=Train_End),1,0) -> 1 | D14: =COUNTIFS(Data_Heathrow!$B$2:$B$6886,B14,Data_Heathrow!$E$2:$E$6886,">="&(T_Day-Climate_Shift-UHI_Day_Eff)) -> 5 | E14: =COUNTIFS(Data_Heathrow!$B$2:$B$6886,B14,Data_Heathrow!$G$2:$G$6886,">="&(T_Night-Climate_Shift-UHI_Night_Eff)) -> 21 | F14: =_xlfn.MAXIFS(Data_Heathrow!$E$2:$E$6886,Data_Heathrow!$B$2:$B$6886,B14)+Climate_Shift+UHI_Day_Eff -> 31.1 | G14: =IFERROR(AVERAGEIFS(Data_Heathrow!$U$2:$U$6886,Data_Heathrow!$B$2:$B$6886,B14),"") -> -0.21130816 | H14: =IFERROR(AVERAGEIFS(Data_Heathrow!$W$2:$W$6886,Data_Heathrow!$B$2:$B$6886,B14),"") -> 1.6953817 | I14: =IFERROR(AVERAGEIFS(Data_Heathrow!$W$2:$W$6886,Data_Heathrow!$B$2:$B$6886,B14,Data_Heathrow!$E$2:$E$6886,">="&T_Day),"") -> 2.5407422 | J14: =SUMIFS(Data_Heathrow!$Q$2:$Q$6886,Data_Heathrow!$B$2:$B$6886,B14) -> 5 | K14: =COUNTIF(D5:D14,">=10") -> 5
B15: 1989 | C15: =IF(AND(B15>=Train_Start,B15<=Train_End),1,0) -> 1 | D15: =COUNTIFS(Data_Heathrow!$B$2:$B$6886,B15,Data_Heathrow!$E$2:$E$6886,">="&(T_Day-Climate_Shift-UHI_Day_Eff)) -> 39 | E15: =COUNTIFS(Data_Heathrow!$B$2:$B$6886,B15,Data_Heathrow!$G$2:$G$6886,">="&(T_Night-Climate_Shift-UHI_Night_Eff)) -> 54 | F15: =_xlfn.MAXIFS(Data_Heathrow!$E$2:$E$6886,Data_Heathrow!$B$2:$B$6886,B15)+Climate_Shift+UHI_Day_Eff -> 36.2 | G15: =IFERROR(AVERAGEIFS(Data_Heathrow!$U$2:$U$6886,Data_Heathrow!$B$2:$B$6886,B15),"") -> 0.4323948 | H15: =IFERROR(AVERAGEIFS(Data_Heathrow!$W$2:$W$6886,Data_Heathrow!$B$2:$B$6886,B15),"") -> 1.9876301 | I15: =IFERROR(AVERAGEIFS(Data_Heathrow!$W$2:$W$6886,Data_Heathrow!$B$2:$B$6886,B15,Data_Heathrow!$E$2:$E$6886,">="&T_Day),"") -> 2.8728324 | J15: =SUMIFS(Data_Heathrow!$Q$2:$Q$6886,Data_Heathrow!$B$2:$B$6886,B15) -> 10 | K15: =COUNTIF(D6:D15,">=10") -> 6
B16: 1990 | C16: =IF(AND(B16>=Train_Start,B16<=Train_End),1,0) -> 1 | D16: =COUNTIFS(Data_Heathrow!$B$2:$B$6886,B16,Data_Heathrow!$E$2:$E$6886,">="&(T_Day-Climate_Shift-UHI_Day_Eff)) -> 34 | E16: =COUNTIFS(Data_Heathrow!$B$2:$B$6886,B16,Data_Heathrow!$G$2:$G$6886,">="&(T_Night-Climate_Shift-UHI_Night_Eff)) -> 40 | F16: =_xlfn.MAXIFS(Data_Heathrow!$E$2:$E$6886,Data_Heathrow!$B$2:$B$6886,B16)+Climate_Shift+UHI_Day_Eff -> 38.5 | G16: =IFERROR(AVERAGEIFS(Data_Heathrow!$U$2:$U$6886,Data_Heathrow!$B$2:$B$6886,B16),"") -> 0.30523105 | H16: =IFERROR(AVERAGEIFS(Data_Heathrow!$W$2:$W$6886,Data_Heathrow!$B$2:$B$6886,B16),"") -> 1.8993708 | I16: =IFERROR(AVERAGEIFS(Data_Heathrow!$W$2:$W$6886,Data_Heathrow!$B$2:$B$6886,B16,Data_Heathrow!$E$2:$E$6886,">="&T_Day),"") -> 3.2794918 | J16: =SUMIFS(Data_Heathrow!$Q$2:$Q$6886,Data_Heathrow!$B$2:$B$6886,B16) -> 10 | K16: =COUNTIF(D7:D16,">=10") -> 7
B17: 1991 | C17: =IF(AND(B17>=Train_Start,B17<=Train_End),1,0) -> 1 | D17: =COUNTIFS(Data_Heathrow!$B$2:$B$6886,B17,Data_Heathrow!$E$2:$E$6886,">="&(T_Day-Climate_Shift-UHI_Day_Eff)) -> 14 | E17: =COUNTIFS(Data_Heathrow!$B$2:$B$6886,B17,Data_Heathrow!$G$2:$G$6886,">="&(T_Night-Climate_Shift-UHI_Night_Eff)) -> 44 | F17: =_xlfn.MAXIFS(Data_Heathrow!$E$2:$E$6886,Data_Heathrow!$B$2:$B$6886,B17)+Climate_Shift+UHI_Day_Eff -> 31.7 | G17: =IFERROR(AVERAGEIFS(Data_Heathrow!$U$2:$U$6886,Data_Heathrow!$B$2:$B$6886,B17),"") -> -0.015294209 | H17: =IFERROR(AVERAGEIFS(Data_Heathrow!$W$2:$W$6886,Data_Heathrow!$B$2:$B$6886,B17),"") -> 1.8458779 | I17: =IFERROR(AVERAGEIFS(Data_Heathrow!$W$2:$W$6886,Data_Heathrow!$B$2:$B$6886,B17,Data_Heathrow!$E$2:$E$6886,">="&T_Day),"") -> 3.5460943 | J17: =SUMIFS(Data_Heathrow!$Q$2:$Q$6886,Data_Heathrow!$B$2:$B$6886,B17) -> 8 | K17: =COUNTIF(D8:D17,">=10") -> 7
B18: 1992 | C18: =IF(AND(B18>=Train_Start,B18<=Train_End),1,0) -> 1 | D18: =COUNTIFS(Data_Heathrow!$B$2:$B$6886,B18,Data_Heathrow!$E$2:$E$6886,">="&(T_Day-Climate_Shift-UHI_Day_Eff)) -> 19 | E18: =COUNTIFS(Data_Heathrow!$B$2:$B$6886,B18,Data_Heathrow!$G$2:$G$6886,">="&(T_Night-Climate_Shift-UHI_Night_Eff)) -> 49 | F18: =_xlfn.MAXIFS(Data_Heathrow!$E$2:$E$6886,Data_Heathrow!$B$2:$B$6886,B18)+Climate_Shift+UHI_Day_Eff -> 32.2 | G18: =IFERROR(AVERAGEIFS(Data_Heathrow!$U$2:$U$6886,Data_Heathrow!$B$2:$B$6886,B18),"") -> 0.050526709 | H18: =IFERROR(AVERAGEIFS(Data_Heathrow!$W$2:$W$6886,Data_Heathrow!$B$2:$B$6886,B18),"") -> 1.9861222 | I18: =IFERROR(AVERAGEIFS(Data_Heathrow!$W$2:$W$6886,Data_Heathrow!$B$2:$B$6886,B18,Data_Heathrow!$E$2:$E$6886,">="&T_Day),"") -> 2.1416792 | J18: =SUMIFS(Data_Heathrow!$Q$2:$Q$6886,Data_Heathrow!$B$2:$B$6886,B18) -> 4 | K18: =COUNTIF(D9:D18,">=10") -> 7
B19: 1993 | C19: =IF(AND(B19>=Train_Start,B19<=Train_End),1,0) -> 1 | D19: =COUNTIFS(Data_Heathrow!$B$2:$B$6886,B19,Data_Heathrow!$E$2:$E$6886,">="&(T_Day-Climate_Shift-UHI_Day_Eff)) -> 9 | E19: =COUNTIFS(Data_Heathrow!$B$2:$B$6886,B19,Data_Heathrow!$G$2:$G$6886,">="&(T_Night-Climate_Shift-UHI_Night_Eff)) -> 26 | F19: =_xlfn.MAXIFS(Data_Heathrow!$E$2:$E$6886,Data_Heathrow!$B$2:$B$6886,B19)+Climate_Shift+UHI_Day_Eff -> 30.4 | G19: =IFERROR(AVERAGEIFS(Data_Heathrow!$U$2:$U$6886,Data_Heathrow!$B$2:$B$6886,B19),"") -> -0.082910195 | H19: =IFERROR(AVERAGEIFS(Data_Heathrow!$W$2:$W$6886,Data_Heathrow!$B$2:$B$6886,B19),"") -> 1.772241 | I19: =IFERROR(AVERAGEIFS(Data_Heathrow!$W$2:$W$6886,Data_Heathrow!$B$2:$B$6886,B19,Data_Heathrow!$E$2:$E$6886,">="&T_Day),"") -> 2.0026069 | J19: =SUMIFS(Data_Heathrow!$Q$2:$Q$6886,Data_Heathrow!$B$2:$B$6886,B19) -> 9 | K19: =COUNTIF(D10:D19,">=10") -> 6
B20: 1994 | C20: =IF(AND(B20>=Train_Start,B20<=Train_End),1,0) -> 1 | D20: =COUNTIFS(Data_Heathrow!$B$2:$B$6886,B20,Data_Heathrow!$E$2:$E$6886,">="&(T_Day-Climate_Shift-UHI_Day_Eff)) -> 25 | E20: =COUNTIFS(Data_Heathrow!$B$2:$B$6886,B20,Data_Heathrow!$G$2:$G$6886,">="&(T_Night-Climate_Shift-UHI_Night_Eff)) -> 41 | F20: =_xlfn.MAXIFS(Data_Heathrow!$E$2:$E$6886,Data_Heathrow!$B$2:$B$6886,B20)+Climate_Shift+UHI_Day_Eff -> 35.1 | G20: =IFERROR(AVERAGEIFS(Data_Heathrow!$U$2:$U$6886,Data_Heathrow!$B$2:$B$6886,B20),"") -> -0.026700731 | H20: =IFERROR(AVERAGEIFS(Data_Heathrow!$W$2:$W$6886,Data_Heathrow!$B$2:$B$6886,B20),"") -> 1.9724891 | I20: =IFERROR(AVERAGEIFS(Data_Heathrow!$W$2:$W$6886,Data_Heathrow!$B$2:$B$6886,B20,Data_Heathrow!$E$2:$E$6886,">="&T_Day),"") -> 3.8032996 | J20: =SUMIFS(Data_Heathrow!$Q$2:$Q$6886,Data_Heathrow!$B$2:$B$6886,B20) -> 7 | K20: =COUNTIF(D11:D20,">=10") -> 6
B21: 1995 | C21: =IF(AND(B21>=Train_Start,B21<=Train_End),1,0) -> 1 | D21: =COUNTIFS(Data_Heathrow!$B$2:$B$6886,B21,Data_Heathrow!$E$2:$E$6886,">="&(T_Day-Climate_Shift-UHI_Day_Eff)) -> 43 | E21: =COUNTIFS(Data_Heathrow!$B$2:$B$6886,B21,Data_Heathrow!$G$2:$G$6886,">="&(T_Night-Climate_Shift-UHI_Night_Eff)) -> 50 | F21: =_xlfn.MAXIFS(Data_Heathrow!$E$2:$E$6886,Data_Heathrow!$B$2:$B$6886,B21)+Climate_Shift+UHI_Day_Eff -> 36.3 | G21: =IFERROR(AVERAGEIFS(Data_Heathrow!$U$2:$U$6886,Data_Heathrow!$B$2:$B$6886,B21),"") -> 0.25003498 | H21: =IFERROR(AVERAGEIFS(Data_Heathrow!$W$2:$W$6886,Data_Heathrow!$B$2:$B$6886,B21),"") -> 1.8282074 | I21: =IFERROR(AVERAGEIFS(Data_Heathrow!$W$2:$W$6886,Data_Heathrow!$B$2:$B$6886,B21,Data_Heathrow!$E$2:$E$6886,">="&T_Day),"") -> 2.6712727 | J21: =SUMIFS(Data_Heathrow!$Q$2:$Q$6886,Data_Heathrow!$B$2:$B$6886,B21) -> 4 | K21: =COUNTIF(D12:D21,">=10") -> 7
B22: 1996 | C22: =IF(AND(B22>=Train_Start,B22<=Train_End),1,0) -> 1 | D22: =COUNTIFS(Data_Heathrow!$B$2:$B$6886,B22,Data_Heathrow!$E$2:$E$6886,">="&(T_Day-Climate_Shift-UHI_Day_Eff)) -> 20 | E22: =COUNTIFS(Data_Heathrow!$B$2:$B$6886,B22,Data_Heathrow!$G$2:$G$6886,">="&(T_Night-Climate_Shift-UHI_Night_Eff)) -> 34 | F22: =_xlfn.MAXIFS(Data_Heathrow!$E$2:$E$6886,Data_Heathrow!$B$2:$B$6886,B22)+Climate_Shift+UHI_Day_Eff -> 33.8 | G22: =IFERROR(AVERAGEIFS(Data_Heathrow!$U$2:$U$6886,Data_Heathrow!$B$2:$B$6886,B22),"") -> 0.051558004 | H22: =IFERROR(AVERAGEIFS(Data_Heathrow!$W$2:$W$6886,Data_Heathrow!$B$2:$B$6886,B22),"") -> 1.8405896 | I22: =IFERROR(AVERAGEIFS(Data_Heathrow!$W$2:$W$6886,Data_Heathrow!$B$2:$B$6886,B22,Data_Heathrow!$E$2:$E$6886,">="&T_Day),"") -> 2.7607565 | J22: =SUMIFS(Data_Heathrow!$Q$2:$Q$6886,Data_Heathrow!$B$2:$B$6886,B22) -> 6 | K22: =COUNTIF(D13:D22,">=10") -> 7
B23: 1997 | C23: =IF(AND(B23>=Train_Start,B23<=Train_End),1,0) -> 1 | D23: =COUNTIFS(Data_Heathrow!$B$2:$B$6886,B23,Data_Heathrow!$E$2:$E$6886,">="&(T_Day-Climate_Shift-UHI_Day_Eff)) -> 25 | E23: =COUNTIFS(Data_Heathrow!$B$2:$B$6886,B23,Data_Heathrow!$G$2:$G$6886,">="&(T_Night-Climate_Shift-UHI_Night_Eff)) -> 61 | F23: =_xlfn.MAXIFS(Data_Heathrow!$E$2:$E$6886,Data_Heathrow!$B$2:$B$6886,B23)+Climate_Shift+UHI_Day_Eff -> 33.5 | G23: =IFERROR(AVERAGEIFS(Data_Heathrow!$U$2:$U$6886,Data_Heathrow!$B$2:$B$6886,B23),"") -> 0.13699433 | H23: =IFERROR(AVERAGEIFS(Data_Heathrow!$W$2:$W$6886,Data_Heathrow!$B$2:$B$6886,B23),"") -> 1.6936923 | I23: =IFERROR(AVERAGEIFS(Data_Heathrow!$W$2:$W$6886,Data_Heathrow!$B$2:$B$6886,B23,Data_Heathrow!$E$2:$E$6886,">="&T_Day),"") -> 2.4200145 | J23: =SUMIFS(Data_Heathrow!$Q$2:$Q$6886,Data_Heathrow!$B$2:$B$6886,B23) -> 6 | K23: =COUNTIF(D14:D23,">=10") -> 8
B24: 1998 | C24: =IF(AND(B24>=Train_Start,B24<=Train_End),1,0) -> 1 | D24: =COUNTIFS(Data_Heathrow!$B$2:$B$6886,B24,Data_Heathrow!$E$2:$E$6886,">="&(T_Day-Climate_Shift-UHI_Day_Eff)) -> 10 | E24: =COUNTIFS(Data_Heathrow!$B$2:$B$6886,B24,Data_Heathrow!$G$2:$G$6886,">="&(T_Night-Climate_Shift-UHI_Night_Eff)) -> 40 | F24: =_xlfn.MAXIFS(Data_Heathrow!$E$2:$E$6886,Data_Heathrow!$B$2:$B$6886,B24)+Climate_Shift+UHI_Day_Eff -> 33.2 | G24: =IFERROR(AVERAGEIFS(Data_Heathrow!$U$2:$U$6886,Data_Heathrow!$B$2:$B$6886,B24),"") -> -0.012486265 | H24: =IFERROR(AVERAGEIFS(Data_Heathrow!$W$2:$W$6886,Data_Heathrow!$B$2:$B$6886,B24),"") -> 1.7426193 | I24: =IFERROR(AVERAGEIFS(Data_Heathrow!$W$2:$W$6886,Data_Heathrow!$B$2:$B$6886,B24,Data_Heathrow!$E$2:$E$6886,">="&T_Day),"") -> 2.7573938 | J24: =SUMIFS(Data_Heathrow!$Q$2:$Q$6886,Data_Heathrow!$B$2:$B$6886,B24) -> 4 | K24: =COUNTIF(D15:D24,">=10") -> 9
B25: 1999 | C25: =IF(AND(B25>=Train_Start,B25<=Train_End),1,0) -> 0 | D25: =COUNTIFS(Data_Heathrow!$B$2:$B$6886,B25,Data_Heathrow!$E$2:$E$6886,">="&(T_Day-Climate_Shift-UHI_Day_Eff)) -> 25 | E25: =COUNTIFS(Data_Heathrow!$B$2:$B$6886,B25,Data_Heathrow!$G$2:$G$6886,">="&(T_Night-Climate_Shift-UHI_Night_Eff)) -> 47 | F25: =_xlfn.MAXIFS(Data_Heathrow!$E$2:$E$6886,Data_Heathrow!$B$2:$B$6886,B25)+Climate_Shift+UHI_Day_Eff -> 34.7 | G25: =IFERROR(AVERAGEIFS(Data_Heathrow!$U$2:$U$6886,Data_Heathrow!$B$2:$B$6886,B25),"") -> 0.17267933 | H25: =IFERROR(AVERAGEIFS(Data_Heathrow!$W$2:$W$6886,Data_Heathrow!$B$2:$B$6886,B25),"") -> 1.757963 | I25: =IFERROR(AVERAGEIFS(Data_Heathrow!$W$2:$W$6886,Data_Heathrow!$B$2:$B$6886,B25,Data_Heathrow!$E$2:$E$6886,">="&T_Day),"") -> 3.0582858 | J25: =SUMIFS(Data_Heathrow!$Q$2:$Q$6886,Data_Heathrow!$B$2:$B$6886,B25) -> 8 | K25: =COUNTIF(D16:D25,">=10") -> 9
... B49: 2023 | C49: =IF(AND(B49>=Train_Start,B49<=Train_End),1,0) -> 0 | D49: =COUNTIFS(Data_Heathrow!$B$2:$B$6886,B49,Data_Heathrow!$E$2:$E$6886,">="&(T_Day-Climate_Shift-UHI_Day_Eff)) -> 31 | E49: =COUNTIFS(Data_Heathrow!$B$2:$B$6886,B49,Data_Heathrow!$G$2:$G$6886,">="&(T_Night-Climate_Shift-UHI_Night_Eff)) -> 64 | F49: =_xlfn.MAXIFS(Data_Heathrow!$E$2:$E$6886,Data_Heathrow!$B$2:$B$6886,B49)+Climate_Shift+UHI_Day_Eff -> 35 | G49: =IFERROR(AVERAGEIFS(Data_Heathrow!$U$2:$U$6886,Data_Heathrow!$B$2:$B$6886,B49),"") -> 0.32197464 | H49: =IFERROR(AVERAGEIFS(Data_Heathrow!$W$2:$W$6886,Data_Heathrow!$B$2:$B$6886,B49),"") -> 1.7855373 | I49: =IFERROR(AVERAGEIFS(Data_Heathrow!$W$2:$W$6886,Data_Heathrow!$B$2:$B$6886,B49,Data_Heathrow!$E$2:$E$6886,">="&T_Day),"") -> 2.5806811 | J49: =SUMIFS(Data_Heathrow!$Q$2:$Q$6886,Data_Heathrow!$B$2:$B$6886,B49) -> 4 | K49: =COUNTIF(D40:D49,">=10") -> 10
B52: Heatwave probability band (1–5) for selected year: | H52: =MIN(5,1+ROUNDUP(INDEX(K5:K49,SelYear-1978)/2,0)) -> 5

Sheet Student_Tasks
A1: Student_Tasks — sprint brief
A2: Work in your project team. Rotate roles each task: chair, analyst, challenger (disagreeing well), scribe, stakeholder voice.
B4: Task | C4: Focus | D4: What to do | E4: Frameworks to apply (core modules) | F4: ILOs
B5: 0 | C5: Orientation (20 min) | D5: Set year 2022, Inner London, Baseline. Read the dashboard. Find 19 July on Monitor_Control and explain the anomaly. Switch QA policy and compare outcomes. | E5: RRR: decision making under uncertainty (VUCA). DCP: systems thinking — iceberg (events → patterns → structure → mental models). | F5: 1
B6: 1 | C6: Define the monitoring system | D6: Choose and justify KRIs, thresholds and trigger rules. Which thresholds are evidence-based and which are anchored on convention? Record choices on Risk_Register (M–N). | E6: RRR: risk management (risk register, probability × impact, margin); heuristics and biases (anchoring). STEM: measures of effectiveness. | F6: 1, 2
B7: 2 | C7: Detect and diagnose algorithm drift | D7: Keep training window 1979–1998. Inspect CUSUM and Annual_Trend residuals. Then inject sensor drift (1°C/30 days from day 60). Distinguish concept drift, data drift and sensor fault. Fix the leak if the test year is in the training window. | E7: RRR: failure analysis — STAMP control loop (process model, feedback); reliability and robust design (redundancy). STEM: models throughout the lifecycle. | F7: 1, 3, 7
B8: 3 | C8: Model tipping points and thresholds | D8: Use the sweeps to find the knee in AI recall and in deaths vs climate shift. Find the climate shift at which the stock first exceeds capacity. Argue for a design margin. | E8: DCP: stock-and-flow and causal loop diagrams; complexity (rugged and dancing landscapes). RRR: margin management and attitudes to risk. | F8: 1, 3, 7
B9: 4 | C9: Equity and inclusion audit | D9: Compare representation-gap days and AI misses with and without neighbourhood sensing. Who carries the most exposure? Whose voice set the thresholds? Challenge at least two illustrative assumptions on Equity_Lens. | E9: RRR: group decision making — diversity, conflict and group performance. LEAD: bias and decision making; developing relationships with key partners. BE: stakeholders, value and business ethics. | F9: 4, 5
B10: 5 | C10: Optimise and decide | D10: Each member records at least two scenarios in Scenario_Log; between you include one that minimises deaths, one within the carbon budget and one that closes the representation gap. Agree weights, shortlist, vote and record the decision in Decision_Matrix. | E10: BE: finance (cost–benefit), procurement and negotiation (contract incentives). RRR: trade studies and decision trees. Sustainability: maladaptation. | F10: 2, 6, 7
B11: 6 | C11: Close the loop | D11: Switch to 'With interventions'. Review Req_Feedback: which change requests are raised, and are the generated 'shall' statements verifiable? Edit, prioritise (MoSCoW) and log disagreements and resolutions. Update residual risk. | E11: DCP: requirements management and change control. STEM: requirements elaboration (statement of need → user → system requirements). LEAD: communicating a compelling vision. | F11: 2, 5, 7
B12: 7 | C12: Present lessons learnt | D12: Five-minute group briefing to the programme board: one insight on data, AI, sustainability and inclusion each, and the single requirement change you would fight for. | E12: LEAD: communicating a compelling vision. RRR: understanding and responding to failure. | F12: 8, 9
B14: Project Simulation ILOs (SPCE0019 MDD)
C15: 1 Analyse data to extract key information
C16: 2 Conduct a comprehensive risk assessment, including mitigation strategies and residual risk
C17: 3 Understand optimism bias in estimation and risks of low-maturity technologies
C18: 4 Perform a stakeholder analysis in a complex environment
C19: 5 Understand team roles and exercise initiative as member and leader
C20: 6 Understand contract types and incentives for contractor performance
C21: 7 Make decisions to control risk, cost, schedule and technical performance in a time-limited context
C22: 8 Write a research report in an academic style
C23: 9 Present lessons learnt and respond to questions
B25: Deliverable (formative, upload to Moodle)
C26: This workbook with Scenario_Log, Decision_Matrix, Risk_Register (all nine risks) and Req_Feedback (MoSCoW) completed, plus a two-page recommendation to the board, a one-page monitoring-and-control plan, a causal loop diagram of the UHI–AC–emissions loop, and a five-minute briefing.

Sheet Data_Heathrow
A1: Date | B1: Year | C1: Month | D1: Season day | E1: TX max °C | F1: Q_TX | G1: TN min °C | H1: Q_TN | I1: TG mean °C | J1: Q_TG | K1: Sea-level pressure hPa | L1: Q_PP | M1: Rel. humidity % | N1: Sunshine h | O1: TX previous day | P1: PP previous day | Q1: Suspect obs (1=yes) | R1: Valid for model | S1: In training window | T1: Model prediction °C | U1: Model residual °C | V1: Prediction (numeric helper) | W1: |Residual| °C
A2: 28976 | B2: 1979 | C2: 5 | D2: 1 | E2: 8 | F2: 0 | G2: 3.8 | H2: 0 | I2: 5.6 | J2: 0 | K2: 1002.8 | L2: 0 | M2: 86 | N2: 0.3 | O2: ="" | P2: ="" | Q2: =IF(OR(F2<>0,AND(I2<>"",E2<I2)),1,0) -> 0 | R2: =0 -> 0 | S2: =R2*(B2>=Train_Start)*(B2<=Train_End) -> 0 | T2: =IF(AND(ISNUMBER(O2),ISNUMBER(P2)),Coef_A+Coef_B1*O2+Coef_B2*P2,"") | U2: =IF(AND(R2=1,ISNUMBER(T2)),E2-T2,"") | V2: =IF(ISNUMBER(T2),T2,-99) -> -99 | W2: =IF(ISNUMBER(U2),ABS(U2),"")
A3: 28977 | B3: 1979 | C3: 5 | D3: 2 | E3: 10 | F3: 0 | G3: 1.1 | H3: 0 | I3: 4.6 | J3: 0 | K3: 1004.8 | L3: 0 | M3: 82 | N3: 7.2 | O3: =IF(D3=1,"",E2) -> 8 | P3: =IF(OR(D3=1,K2=""),"",K2) -> 1002.8 | Q3: =IF(OR(F3<>0,AND(I3<>"",E3<I3)),1,0) -> 0 | R3: =IF(AND(D3>1,Q3=0,ISNUMBER(O3),ISNUMBER(P3)),IF(Q2=0,1,0),0) -> 1 | S3: =R3*(B3>=Train_Start)*(B3<=Train_End) -> 1 | T3: =IF(AND(ISNUMBER(O3),ISNUMBER(P3)),Coef_A+Coef_B1*O3+Coef_B2*P3,"") -> 10.099419 | U3: =IF(AND(R3=1,ISNUMBER(T3)),E3-T3,"") -> -0.099419305 | V3: =IF(ISNUMBER(T3),T3,-99) -> 10.099419 | W3: =IF(ISNUMBER(U3),ABS(U3),"") -> 0.099419305
A4: 28978 | B4: 1979 | C4: 5 | D4: 3 | E4: 9.1 | F4: 0 | G4: -0.9 | H4: 0 | I4: 4.6 | J4: 0 | K4: 1009.3 | L4: 0 | M4: 80 | N4: 9.4 | O4: =IF(D4=1,"",E3) -> 10 | P4: =IF(OR(D4=1,K3=""),"",K3) -> 1004.8 | Q4: =IF(OR(F4<>0,AND(I4<>"",E4<I4)),1,0) -> 0 | R4: =IF(AND(D4>1,Q4=0,ISNUMBER(O4),ISNUMBER(P4)),IF(Q3=0,1,0),0) -> 1 | S4: =R4*(B4>=Train_Start)*(B4<=Train_End) -> 1 | T4: =IF(AND(ISNUMBER(O4),ISNUMBER(P4)),Coef_A+Coef_B1*O4+Coef_B2*P4,"") -> 11.800837 | U4: =IF(AND(R4=1,ISNUMBER(T4)),E4-T4,"") -> -2.7008375 | V4: =IF(ISNUMBER(T4),T4,-99) -> 11.800837 | W4: =IF(ISNUMBER(U4),ABS(U4),"") -> 2.7008375
A5: 28979 | B5: 1979 | C5: 5 | D5: 4 | E5: 11.1 | F5: 0 | G5: -0.3 | H5: 0 | I5: 4.4 | J5: 0 | K5: 1015.9 | L5: 0 | M5: 76 | N5: 9.9 | O5: =IF(D5=1,"",E4) -> 9.1 | P5: =IF(OR(D5=1,K4=""),"",K4) -> 1009.3 | Q5: =IF(OR(F5<>0,AND(I5<>"",E5<I5)),1,0) -> 0 | R5: =IF(AND(D5>1,Q5=0,ISNUMBER(O5),ISNUMBER(P5)),IF(Q4=0,1,0),0) -> 1 | S5: =R5*(B5>=Train_Start)*(B5<=Train_End) -> 1 | T5: =IF(AND(ISNUMBER(O5),ISNUMBER(P5)),Coef_A+Coef_B1*O5+Coef_B2*P5,"") -> 11.204597 | U5: =IF(AND(R5=1,ISNUMBER(T5)),E5-T5,"") -> -0.10459673 | V5: =IF(ISNUMBER(T5),T5,-99) -> 11.204597 | W5: =IF(ISNUMBER(U5),ABS(U5),"") -> 0.10459673
A6: 28980 | B6: 1979 | C6: 5 | D6: 5 | E6: 12.4 | F6: 0 | G6: 1.7 | H6: 0 | I6: 6.4 | J6: 0 | K6: 1020.6 | L6: 0 | M6: 80 | N6: 9.1 | O6: =IF(D6=1,"",E5) -> 11.1 | P6: =IF(OR(D6=1,K5=""),"",K5) -> 1015.9 | Q6: =IF(OR(F6<>0,AND(I6<>"",E6<I6)),1,0) -> 0 | R6: =IF(AND(D6>1,Q6=0,ISNUMBER(O6),ISNUMBER(P6)),IF(Q5=0,1,0),0) -> 1 | S6: =R6*(B6>=Train_Start)*(B6<=Train_End) -> 1 | T6: =IF(AND(ISNUMBER(O6),ISNUMBER(P6)),Coef_A+Coef_B1*O6+Coef_B2*P6,"") -> 13.050316 | U6: =IF(AND(R6=1,ISNUMBER(T6)),E6-T6,"") -> -0.65031642 | V6: =IF(ISNUMBER(T6),T6,-99) -> 13.050316 | W6: =IF(ISNUMBER(U6),ABS(U6),"") -> 0.65031642
A7: 28981 | B7: 1979 | C7: 5 | D7: 6 | E7: 15 | F7: 0 | G7: 1 | H7: 0 | I7: 6.7 | J7: 0 | K7: 1023.4 | L7: 0 | M7: 73 | N7: 8.8 | O7: =IF(D7=1,"",E6) -> 12.4 | P7: =IF(OR(D7=1,K6=""),"",K6) -> 1020.6 | Q7: =IF(OR(F7<>0,AND(I7<>"",E7<I7)),1,0) -> 0 | R7: =IF(AND(D7>1,Q7=0,ISNUMBER(O7),ISNUMBER(P7)),IF(Q6=0,1,0),0) -> 1 | S7: =R7*(B7>=Train_Start)*(B7<=Train_End) -> 1 | T7: =IF(AND(ISNUMBER(O7),ISNUMBER(P7)),Coef_A+Coef_B1*O7+Coef_B2*P7,"") -> 14.262896 | U7: =IF(AND(R7=1,ISNUMBER(T7)),E7-T7,"") -> 0.73710412 | V7: =IF(ISNUMBER(T7),T7,-99) -> 14.262896 | W7: =IF(ISNUMBER(U7),ABS(U7),"") -> 0.73710412
A8: 28982 | B8: 1979 | C8: 5 | D8: 7 | E8: 16 | F8: 0 | G8: 3.9 | H8: 0 | I8: 9.4 | J8: 0 | K8: 1021.1 | L8: 0 | M8: 66 | N8: 5.9 | O8: =IF(D8=1,"",E7) -> 15 | P8: =IF(OR(D8=1,K7=""),"",K7) -> 1023.4 | Q8: =IF(OR(F8<>0,AND(I8<>"",E8<I8)),1,0) -> 0 | R8: =IF(AND(D8>1,Q8=0,ISNUMBER(O8),ISNUMBER(P8)),IF(Q7=0,1,0),0) -> 1 | S8: =R8*(B8>=Train_Start)*(B8<=Train_End) -> 1 | T8: =IF(AND(ISNUMBER(O8),ISNUMBER(P8)),Coef_A+Coef_B1*O8+Coef_B2*P8,"") -> 16.481013 | U8: =IF(AND(R8=1,ISNUMBER(T8)),E8-T8,"") -> -0.48101349 | V8: =IF(ISNUMBER(T8),T8,-99) -> 16.481013 | W8: =IF(ISNUMBER(U8),ABS(U8),"") -> 0.48101349
A9: 28983 | B9: 1979 | C9: 5 | D9: 8 | E9: 15.6 | F9: 0 | G9: 6.4 | H9: 0 | I9: 11.2 | J9: 0 | K9: 1019.6 | L9: 0 | M9: 71 | N9: 3.2 | O9: =IF(D9=1,"",E8) -> 16 | P9: =IF(OR(D9=1,K8=""),"",K8) -> 1021.1 | Q9: =IF(OR(F9<>0,AND(I9<>"",E9<I9)),1,0) -> 0 | R9: =IF(AND(D9>1,Q9=0,ISNUMBER(O9),ISNUMBER(P9)),IF(Q8=0,1,0),0) -> 1 | S9: =R9*(B9>=Train_Start)*(B9<=Train_End) -> 1 | T9: =IF(AND(ISNUMBER(O9),ISNUMBER(P9)),Coef_A+Coef_B1*O9+Coef_B2*P9,"") -> 17.228202 | U9: =IF(AND(R9=1,ISNUMBER(T9)),E9-T9,"") -> -1.6282019 | V9: =IF(ISNUMBER(T9),T9,-99) -> 17.228202 | W9: =IF(ISNUMBER(U9),ABS(U9),"") -> 1.6282019
A10: 28984 | B10: 1979 | C10: 5 | D10: 9 | E10: 13.6 | F10: 0 | G10: 4.5 | H10: 0 | I10: 10 | J10: 0 | K10: 1023 | L10: 0 | M10: 66 | N10: 8.4 | O10: =IF(D10=1,"",E9) -> 15.6 | P10: =IF(OR(D10=1,K9=""),"",K9) -> 1019.6 | Q10: =IF(OR(F10<>0,AND(I10<>"",E10<I10)),1,0) -> 0 | R10: =IF(AND(D10>1,Q10=0,ISNUMBER(O10),ISNUMBER(P10)),IF(Q9=0,1,0),0) -> 1 | S10: =R10*(B10>=Train_Start)*(B10<=Train_End) -> 1 | T10: =IF(AND(ISNUMBER(O10),ISNUMBER(P10)),Coef_A+Coef_B1*O10+Coef_B2*P10,"") -> 16.853411 | U10: =IF(AND(R10=1,ISNUMBER(T10)),E10-T10,"") -> -3.2534114 | V10: =IF(ISNUMBER(T10),T10,-99) -> 16.853411 | W10: =IF(ISNUMBER(U10),ABS(U10),"") -> 3.2534114
A11: 28985 | B11: 1979 | C11: 5 | D11: 10 | E11: 16.1 | F11: 0 | G11: 7.3 | H11: 0 | I11: 10.4 | J11: 0 | K11: 1027 | L11: 0 | M11: 73 | N11: 0.5 | O11: =IF(D11=1,"",E10) -> 13.6 | P11: =IF(OR(D11=1,K10=""),"",K10) -> 1023 | Q11: =IF(OR(F11<>0,AND(I11<>"",E11<I11)),1,0) -> 0 | R11: =IF(AND(D11>1,Q11=0,ISNUMBER(O11),ISNUMBER(P11)),IF(Q10=0,1,0),0) -> 1 | S11: =R11*(B11>=Train_Start)*(B11<=Train_End) -> 1 | T11: =IF(AND(ISNUMBER(O11),ISNUMBER(P11)),Coef_A+Coef_B1*O11+Coef_B2*P11,"") -> 15.321391 | U11: =IF(AND(R11=1,ISNUMBER(T11)),E11-T11,"") -> 0.77860934 | V11: =IF(ISNUMBER(T11),T11,-99) -> 15.321391 | W11: =IF(ISNUMBER(U11),ABS(U11),"") -> 0.77860934
A12: 28986 | B12: 1979 | C12: 5 | D12: 11 | E12: 20.8 | F12: 0 | G12: 9.2 | H12: 0 | I12: 12.6 | J12: 0 | K12: 1022.3 | L12: 0 | M12: 92 | N12: 0.1 | O12: =IF(D12=1,"",E11) -> 16.1 | P12: =IF(OR(D12=1,K11=""),"",K11) -> 1027 | Q12: =IF(OR(F12<>0,AND(I12<>"",E12<I12)),1,0) -> 0 | R12: =IF(AND(D12>1,Q12=0,ISNUMBER(O12),ISNUMBER(P12)),IF(Q11=0,1,0),0) -> 1 | S12: =R12*(B12>=Train_Start)*(B12<=Train_End) -> 1 | T12: =IF(AND(ISNUMBER(O12),ISNUMBER(P12)),Coef_A+Coef_B1*O12+Coef_B2*P12,"") -> 17.495218 | U12: =IF(AND(R12=1,ISNUMBER(T12)),E12-T12,"") -> 3.3047818 | V12: =IF(ISNUMBER(T12),T12,-99) -> 17.495218 | W12: =IF(ISNUMBER(U12),ABS(U12),"") -> 3.3047818
A13: 28987 | B13: 1979 | C13: 5 | D13: 12 | E13: 23.4 | F13: 0 | G13: 11.2 | H13: 0 | I13: 16 | J13: 0 | K13: 1030 | L13: 0 | M13: 82 | N13: 4.9 | O13: =IF(D13=1,"",E12) -> 20.8 | P13: =IF(OR(D13=1,K12=""),"",K12) -> 1022.3 | Q13: =IF(OR(F13<>0,AND(I13<>"",E13<I13)),1,0) -> 0 | R13: =IF(AND(D13>1,Q13=0,ISNUMBER(O13),ISNUMBER(P13)),IF(Q12=0,1,0),0) -> 1 | S13: =R13*(B13>=Train_Start)*(B13<=Train_End) -> 1 | T13: =IF(AND(ISNUMBER(O13),ISNUMBER(P13)),Coef_A+Coef_B1*O13+Coef_B2*P13,"") -> 21.198674 | U13: =IF(AND(R13=1,ISNUMBER(T13)),E13-T13,"") -> 2.2013261 | V13: =IF(ISNUMBER(T13),T13,-99) -> 21.198674 | W13: =IF(ISNUMBER(U13),ABS(U13),"") -> 2.2013261
A14: 28988 | B14: 1979 | C14: 5 | D14: 13 | E14: 26.1 | F14: 0 | G14: 11.5 | H14: 0 | I14: 17.4 | J14: 0 | K14: 1031.6 | L14: 0 | M14: 76 | N14: 13 | O14: =IF(D14=1,"",E13) -> 23.4 | P14: =IF(OR(D14=1,K13=""),"",K13) -> 1030 | Q14: =IF(OR(F14<>0,AND(I14<>"",E14<I14)),1,0) -> 0 | R14: =IF(AND(D14>1,Q14=0,ISNUMBER(O14),ISNUMBER(P14)),IF(Q13=0,1,0),0) -> 1 | S14: =R14*(B14>=Train_Start)*(B14<=Train_End) -> 1 | T14: =IF(AND(ISNUMBER(O14),ISNUMBER(P14)),Coef_A+Coef_B1*O14+Coef_B2*P14,"") -> 23.570504 | U14: =IF(AND(R14=1,ISNUMBER(T14)),E14-T14,"") -> 2.529496 | V14: =IF(ISNUMBER(T14),T14,-99) -> 23.570504 | W14: =IF(ISNUMBER(U14),ABS(U14),"") -> 2.529496
... A4113: 38606 | B4113: 2005 | C4113: 9 | D4113: 134 | E4113: 17.1 | F4113: 0 | G4113: 15.1 | H4113: 0 | I4113: 16.1 | J4113: 0 | K4113: 1014.6 | L4113: 0 | M4113: 90 | N4113: 0 | O4113: =IF(D4113=1,"",E4112) -> 23.4 | P4113: =IF(OR(D4113=1,K4112=""),"",K4112) -> 1009.8 | Q4113: =IF(OR(F4113<>0,AND(I4113<>"",E4113<I4113)),1,0) -> 0 | R4113: =IF(AND(D4113>1,Q4113=0,ISNUMBER(O4113),ISNUMBER(P4113)),IF(Q4112=0,1,0),0) -> 1 | S4113: =R4113*(B4113>=Train_Start)*(B4113<=Train_End) -> 0 | T4113: =IF(AND(ISNUMBER(O4113),ISNUMBER(P4113)),Coef_A+Coef_B1*O4113+Coef_B2*P4113,"") -> 22.936832 | U4113: =IF(AND(R4113=1,ISNUMBER(T4113)),E4113-T4113,"") -> -5.8368321 | V4113: =IF(ISNUMBER(T4113),T4113,-99) -> 22.936832 | W4113: =IF(ISNUMBER(U4113),ABS(U4113),"") -> 5.8368321
A4114: 38607 | B4114: 2005 | C4114: 9 | D4114: 135 | E4114: 22.2 | F4114: 0 | G4114: 14.3 | H4114: 0 | J4114: 9 | K4114: 1021.4 | L4114: 0 | M4114: 75 | N4114: 6.4 | O4114: =IF(D4114=1,"",E4113) -> 17.1 | P4114: =IF(OR(D4114=1,K4113=""),"",K4113) -> 1014.6 | Q4114: =IF(OR(F4114<>0,AND(I4114<>"",E4114<I4114)),1,0) -> 0 | R4114: =IF(AND(D4114>1,Q4114=0,ISNUMBER(O4114),ISNUMBER(P4114)),IF(Q4113=0,1,0),0) -> 1 | S4114: =R4114*(B4114>=Train_Start)*(B4114<=Train_End) -> 0 | T4114: =IF(AND(ISNUMBER(O4114),ISNUMBER(P4114)),Coef_A+Coef_B1*O4114+Coef_B2*P4114,"") -> 17.925571 | U4114: =IF(AND(R4114=1,ISNUMBER(T4114)),E4114-T4114,"") -> 4.2744293 | V4114: =IF(ISNUMBER(T4114),T4114,-99) -> 17.925571 | W4114: =IF(ISNUMBER(U4114),ABS(U4114),"") -> 4.2744293
A4115: 38608 | B4115: 2005 | C4115: 9 | D4115: 136 | E4115: 22.9 | F4115: 0 | G4115: 12 | H4115: 0 | I4115: 17.4 | J4115: 0 | K4115: 1024.5 | L4115: 0 | M4115: 75 | N4115: 9.2 | O4115: =IF(D4115=1,"",E4114) -> 22.2 | P4115: =IF(OR(D4115=1,K4114=""),"",K4114) -> 1021.4 | Q4115: =IF(OR(F4115<>0,AND(I4115<>"",E4115<I4115)),1,0) -> 0 | R4115: =IF(AND(D4115>1,Q4115=0,ISNUMBER(O4115),ISNUMBER(P4115)),IF(Q4114=0,1,0),0) -> 1 | S4115: =R4115*(B4115>=Train_Start)*(B4115<=Train_End) -> 0 | T4115: =IF(AND(ISNUMBER(O4115),ISNUMBER(P4115)),Coef_A+Coef_B1*O4115+Coef_B2*P4115,"") -> 22.317516 | U4115: =IF(AND(R4115=1,ISNUMBER(T4115)),E4115-T4115,"") -> 0.58248411 | V4115: =IF(ISNUMBER(T4115),T4115,-99) -> 22.317516 | W4115: =IF(ISNUMBER(U4115),ABS(U4115),"") -> 0.58248411
A4116: 38609 | B4116: 2005 | C4116: 9 | D4116: 137 | E4116: 24.9 | F4116: 0 | G4116: 15.8 | H4116: 0 | I4116: 20.4 | J4116: 0 | K4116: 1021.3 | L4116: 0 | M4116: 74 | N4116: 2.6 | O4116: =IF(D4116=1,"",E4115) -> 22.9 | P4116: =IF(OR(D4116=1,K4115=""),"",K4115) -> 1024.5 | Q4116: =IF(OR(F4116<>0,AND(I4116<>"",E4116<I4116)),1,0) -> 0 | R4116: =IF(AND(D4116>1,Q4116=0,ISNUMBER(O4116),ISNUMBER(P4116)),IF(Q4115=0,1,0),0) -> 1 | S4116: =R4116*(B4116>=Train_Start)*(B4116<=Train_End) -> 0 | T4116: =IF(AND(ISNUMBER(O4116),ISNUMBER(P4116)),Coef_A+Coef_B1*O4116+Coef_B2*P4116,"") -> 22.9883 | U4116: =IF(AND(R4116=1,ISNUMBER(T4116)),E4116-T4116,"") -> 1.9117 | V4116: =IF(ISNUMBER(T4116),T4116,-99) -> 22.9883 | W4116: =IF(ISNUMBER(U4116),ABS(U4116),"") -> 1.9117
A4117: 38610 | B4117: 2005 | C4117: 9 | D4117: 138 | E4117: 22 | F4117: 0 | G4117: 14.9 | H4117: 0 | I4117: 18.4 | J4117: 0 | K4117: 1014.4 | L4117: 0 | M4117: 88 | N4117: 1.2 | O4117: =IF(D4117=1,"",E4116) -> 24.9 | P4117: =IF(OR(D4117=1,K4116=""),"",K4116) -> 1021.3 | Q4117: =IF(OR(F4117<>0,AND(I4117<>"",E4117<I4117)),1,0) -> 0 | R4117: =IF(AND(D4117>1,Q4117=0,ISNUMBER(O4117),ISNUMBER(P4117)),IF(Q4116=0,1,0),0) -> 1 | S4117: =R4117*(B4117>=Train_Start)*(B4117<=Train_End) -> 0 | T4117: =IF(AND(ISNUMBER(O4117),ISNUMBER(P4117)),Coef_A+Coef_B1*O4117+Coef_B2*P4117,"") -> 24.526595 | U4117: =IF(AND(R4117=1,ISNUMBER(T4117)),E4117-T4117,"") -> -2.5265947 | V4117: =IF(ISNUMBER(T4117),T4117,-99) -> 24.526595 | W4117: =IF(ISNUMBER(U4117),ABS(U4117),"") -> 2.5265947
A4118: 38611 | B4118: 2005 | C4118: 9 | D4118: 139 | E4118: 16.2 | F4118: 0 | G4118: 10.9 | H4118: 0 | I4118: 13.6 | J4118: 0 | K4118: 1017.9 | L4118: 0 | M4118: 71 | N4118: 6.3 | O4118: =IF(D4118=1,"",E4117) -> 22 | P4118: =IF(OR(D4118=1,K4117=""),"",K4117) -> 1014.4 | Q4118: =IF(OR(F4118<>0,AND(I4118<>"",E4118<I4118)),1,0) -> 0 | R4118: =IF(AND(D4118>1,Q4118=0,ISNUMBER(O4118),ISNUMBER(P4118)),IF(Q4117=0,1,0),0) -> 1 | S4118: =R4118*(B4118>=Train_Start)*(B4118<=Train_End) -> 0 | T4118: =IF(AND(ISNUMBER(O4118),ISNUMBER(P4118)),Coef_A+Coef_B1*O4118+Coef_B2*P4118,"") -> 21.934059 | U4118: =IF(AND(R4118=1,ISNUMBER(T4118)),E4118-T4118,"") -> -5.7340588 | V4118: =IF(ISNUMBER(T4118),T4118,-99) -> 21.934059 | W4118: =IF(ISNUMBER(U4118),ABS(U4118),"") -> 5.7340588
A4119: 38612 | B4119: 2005 | C4119: 9 | D4119: 140 | E4119: 16.9 | F4119: 0 | G4119: 5.7 | H4119: 0 | I4119: 11.3 | J4119: 0 | K4119: 1026.1 | L4119: 0 | M4119: 63 | N4119: 10.3 | O4119: =IF(D4119=1,"",E4118) -> 16.2 | P4119: =IF(OR(D4119=1,K4118=""),"",K4118) -> 1017.9 | Q4119: =IF(OR(F4119<>0,AND(I4119<>"",E4119<I4119)),1,0) -> 0 | R4119: =IF(AND(D4119>1,Q4119=0,ISNUMBER(O4119),ISNUMBER(P4119)),IF(Q4118=0,1,0),0) -> 1 | S4119: =R4119*(B4119>=Train_Start)*(B4119<=Train_End) -> 0 | T4119: =IF(AND(ISNUMBER(O4119),ISNUMBER(P4119)),Coef_A+Coef_B1*O4119+Coef_B2*P4119,"") -> 17.291686 | U4119: =IF(AND(R4119=1,ISNUMBER(T4119)),E4119-T4119,"") -> -0.3916861 | V4119: =IF(ISNUMBER(T4119),T4119,-99) -> 17.291686 | W4119: =IF(ISNUMBER(U4119),ABS(U4119),"") -> 0.3916861
A4120: 38613 | B4120: 2005 | C4120: 9 | D4120: 141 | E4120: 16.5 | F4120: 0 | G4120: 7.8 | H4120: 0 | I4120: 12.2 | J4120: 0 | K4120: 1027.7 | L4120: 0 | M4120: 77 | N4120: 0.5 | O4120: =IF(D4120=1,"",E4119) -> 16.9 | P4120: =IF(OR(D4120=1,K4119=""),"",K4119) -> 1026.1 | Q4120: =IF(OR(F4120<>0,AND(I4120<>"",E4120<I4120)),1,0) -> 0 | R4120: =IF(AND(D4120>1,Q4120=0,ISNUMBER(O4120),ISNUMBER(P4120)),IF(Q4119=0,1,0),0) -> 1 | S4120: =R4120*(B4120>=Train_Start)*(B4120<=Train_End) -> 0 | T4120: =IF(AND(ISNUMBER(O4120),ISNUMBER(P4120)),Coef_A+Coef_B1*O4120+Coef_B2*P4120,"") -> 18.122457 | U4120: =IF(AND(R4120=1,ISNUMBER(T4120)),E4120-T4120,"") -> -1.6224567 | V4120: =IF(ISNUMBER(T4120),T4120,-99) -> 18.122457 | W4120: =IF(ISNUMBER(U4120),ABS(U4120),"") -> 1.6224567
A4121: 38614 | B4121: 2005 | C4121: 9 | D4121: 142 | E4121: 19.2 | F4121: 0 | G4121: 13.1 | H4121: 0 | I4121: 16.2 | J4121: 0 | K4121: 1025.8 | L4121: 0 | M4121: 71 | N4121: 1.3 | O4121: =IF(D4121=1,"",E4120) -> 16.5 | P4121: =IF(OR(D4121=1,K4120=""),"",K4120) -> 1027.7 | Q4121: =IF(OR(F4121<>0,AND(I4121<>"",E4121<I4121)),1,0) -> 0 | R4121: =IF(AND(D4121>1,Q4121=0,ISNUMBER(O4121),ISNUMBER(P4121)),IF(Q4120=0,1,0),0) -> 1 | S4121: =R4121*(B4121>=Train_Start)*(B4121<=Train_End) -> 0 | T4121: =IF(AND(ISNUMBER(O4121),ISNUMBER(P4121)),Coef_A+Coef_B1*O4121+Coef_B2*P4121,"") -> 17.844913 | U4121: =IF(AND(R4121=1,ISNUMBER(T4121)),E4121-T4121,"") -> 1.3550872 | V4121: =IF(ISNUMBER(T4121),T4121,-99) -> 17.844913 | W4121: =IF(ISNUMBER(U4121),ABS(U4121),"") -> 1.3550872
A4122: 38615 | B4122: 2005 | C4122: 9 | D4122: 143 | E4122: 21.8 | F4122: 0 | G4122: 10.7 | H4122: 0 | I4122: 16.2 | J4122: 0 | K4122: 1024.6 | L4122: 0 | M4122: 76 | N4122: 3.6 | O4122: =IF(D4122=1,"",E4121) -> 19.2 | P4122: =IF(OR(D4122=1,K4121=""),"",K4121) -> 1025.8 | Q4122: =IF(OR(F4122<>0,AND(I4122<>"",E4122<I4122)),1,0) -> 0 | R4122: =IF(AND(D4122>1,Q4122=0,ISNUMBER(O4122),ISNUMBER(P4122)),IF(Q4121=0,1,0),0) -> 1 | S4122: =R4122*(B4122>=Train_Start)*(B4122<=Train_End) -> 0 | T4122: =IF(AND(ISNUMBER(O4122),ISNUMBER(P4122)),Coef_A+Coef_B1*O4122+Coef_B2*P4122,"") -> 19.997526 | U4122: =IF(AND(R4122=1,ISNUMBER(T4122)),E4122-T4122,"") -> 1.8024742 | V4122: =IF(ISNUMBER(T4122),T4122,-99) -> 19.997526 | W4122: =IF(ISNUMBER(U4122),ABS(U4122),"") -> 1.8024742
A4123: 38616 | B4123: 2005 | C4123: 9 | D4123: 144 | E4123: 21.1 | F4123: 0 | G4123: 14 | H4123: 0 | I4123: 17.6 | J4123: 0 | K4123: 1022.6 | L4123: 0 | M4123: 79 | N4123: 0.9 | O4123: =IF(D4123=1,"",E4122) -> 21.8 | P4123: =IF(OR(D4123=1,K4122=""),"",K4122) -> 1024.6 | Q4123: =IF(OR(F4123<>0,AND(I4123<>"",E4123<I4123)),1,0) -> 0 | R4123: =IF(AND(D4123>1,Q4123=0,ISNUMBER(O4123),ISNUMBER(P4123)),IF(Q4122=0,1,0),0) -> 1 | S4123: =R4123*(B4123>=Train_Start)*(B4123<=Train_End) -> 0 | T4123: =IF(AND(ISNUMBER(O4123),ISNUMBER(P4123)),Coef_A+Coef_B1*O4123+Coef_B2*P4123,"") -> 22.090164 | U4123: =IF(AND(R4123=1,ISNUMBER(T4123)),E4123-T4123,"") -> -0.99016387 | V4123: =IF(ISNUMBER(T4123),T4123,-99) -> 22.090164 | W4123: =IF(ISNUMBER(U4123),ABS(U4123),"") -> 0.99016387
A4124: 38617 | B4124: 2005 | C4124: 9 | D4124: 145 | E4124: 21.3 | F4124: 0 | G4124: 10.9 | H4124: 0 | I4124: 16.1 | J4124: 0 | K4124: 1018.8 | L4124: 0 | M4124: 77 | N4124: 7 | O4124: =IF(D4124=1,"",E4123) -> 21.1 | P4124: =IF(OR(D4124=1,K4123=""),"",K4123) -> 1022.6 | Q4124: =IF(OR(F4124<>0,AND(I4124<>"",E4124<I4124)),1,0) -> 0 | R4124: =IF(AND(D4124>1,Q4124=0,ISNUMBER(O4124),ISNUMBER(P4124)),IF(Q4123=0,1,0),0) -> 1 | S4124: =R4124*(B4124>=Train_Start)*(B4124<=Train_End) -> 0 | T4124: =IF(AND(ISNUMBER(O4124),ISNUMBER(P4124)),Coef_A+Coef_B1*O4124+Coef_B2*P4124,"") -> 21.453887 | U4124: =IF(AND(R4124=1,ISNUMBER(T4124)),E4124-T4124,"") -> -0.15388665 | V4124: =IF(ISNUMBER(T4124),T4124,-99) -> 21.453887 | W4124: =IF(ISNUMBER(U4124),ABS(U4124),"") -> 0.15388665
A4125: 38618 | B4125: 2005 | C4125: 9 | D4125: 146 | E4125: 19.2 | F4125: 0 | G4125: 10.5 | H4125: 0 | I4125: 14.8 | J4125: 0 | K4125: 1013 | L4125: 0 | M4125: 81 | N4125: 2.2 | O4125: =IF(D4125=1,"",E4124) -> 21.3 | P4125: =IF(OR(D4125=1,K4124=""),"",K4124) -> 1018.8 | Q4125: =IF(OR(F4125<>0,AND(I4125<>"",E4125<I4125)),1,0) -> 0 | R4125: =IF(AND(D4125>1,Q4125=0,ISNUMBER(O4125),ISNUMBER(P4125)),IF(Q4124=0,1,0),0) -> 1 | S4125: =R4125*(B4125>=Train_Start)*(B4125<=Train_End) -> 0 | T4125: =IF(AND(ISNUMBER(O4125),ISNUMBER(P4125)),Coef_A+Coef_B1*O4125+Coef_B2*P4125,"") -> 21.498549 | U4125: =IF(AND(R4125=1,ISNUMBER(T4125)),E4125-T4125,"") -> -2.2985489 | V4125: =IF(ISNUMBER(T4125),T4125,-99) -> 21.498549 | W4125: =IF(ISNUMBER(U4125),ABS(U4125),"") -> 2.2985489
A4126: 38619 | B4126: 2005 | C4126: 9 | D4126: 147 | E4126: 18.1 | F4126: 0 | G4126: 6.8 | H4126: 0 | I4126: 12.4 | J4126: 0 | K4126: 1017.3 | L4126: 0 | M4126: 70 | N4126: 7.1 | O4126: =IF(D4126=1,"",E4125) -> 19.2 | P4126: =IF(OR(D4126=1,K4125=""),"",K4125) -> 1013 | Q4126: =IF(OR(F4126<>0,AND(I4126<>"",E4126<I4126)),1,0) -> 0 | R4126: =IF(AND(D4126>1,Q4126=0,ISNUMBER(O4126),ISNUMBER(P4126)),IF(Q4125=0,1,0),0) -> 1 | S4126: =R4126*(B4126>=Train_Start)*(B4126<=Train_End) -> 0 | T4126: =IF(AND(ISNUMBER(O4126),ISNUMBER(P4126)),Coef_A+Coef_B1*O4126+Coef_B2*P4126,"") -> 19.595991 | U4126: =IF(AND(R4126=1,ISNUMBER(T4126)),E4126-T4126,"") -> -1.4959912 | V4126: =IF(ISNUMBER(T4126),T4126,-99) -> 19.595991 | W4126: =IF(ISNUMBER(U4126),ABS(U4126),"") -> 1.4959912
... A4135: 38840 | B4135: 2006 | C4135: 5 | D4135: 3 | E4135: 19.3 | F4135: 0 | G4135: 7.7 | H4135: 0 | I4135: 13.5 | J4135: 0 | K4135: 1013.5 | L4135: 0 | M4135: 74 | N4135: 6.9 | O4135: =IF(D4135=1,"",E4134) -> 16.5 | P4135: =IF(OR(D4135=1,K4134=""),"",K4134) -> 1008.3 | Q4135: =IF(OR(F4135<>0,AND(I4135<>"",E4135<I4135)),1,0) -> 0 | R4135: =IF(AND(D4135>1,Q4135=0,ISNUMBER(O4135),ISNUMBER(P4135)),IF(Q4134=0,1,0),0) -> 1 | S4135: =R4135*(B4135>=Train_Start)*(B4135<=Train_End) -> 0 | T4135: =IF(AND(ISNUMBER(O4135),ISNUMBER(P4135)),Coef_A+Coef_B1*O4135+Coef_B2*P4135,"") -> 17.236337 | U4135: =IF(AND(R4135=1,ISNUMBER(T4135)),E4135-T4135,"") -> 2.0636631 | V4135: =IF(ISNUMBER(T4135),T4135,-99) -> 17.236337 | W4135: =IF(ISNUMBER(U4135),ABS(U4135),"") -> 2.0636631
A4136: 38841 | B4136: 2006 | C4136: 5 | D4136: 4 | E4136: 27.5 | F4136: 0 | G4136: 12.5 | H4136: 0 | J4136: 9 | K4136: 1013.9 | L4136: 0 | M4136: 58 | N4136: 10.6 | O4136: =IF(D4136=1,"",E4135) -> 19.3 | P4136: =IF(OR(D4136=1,K4135=""),"",K4135) -> 1013.5 | Q4136: =IF(OR(F4136<>0,AND(I4136<>"",E4136<I4136)),1,0) -> 0 | R4136: =IF(AND(D4136>1,Q4136=0,ISNUMBER(O4136),ISNUMBER(P4136)),IF(Q4135=0,1,0),0) -> 1 | S4136: =R4136*(B4136>=Train_Start)*(B4136<=Train_End) -> 0 | T4136: =IF(AND(ISNUMBER(O4136),ISNUMBER(P4136)),Coef_A+Coef_B1*O4136+Coef_B2*P4136,"") -> 19.69361 | U4136: =IF(AND(R4136=1,ISNUMBER(T4136)),E4136-T4136,"") -> 7.8063899 | V4136: =IF(ISNUMBER(T4136),T4136,-99) -> 19.69361 | W4136: =IF(ISNUMBER(U4136),ABS(U4136),"") -> 7.8063899
A4137: 38842 | B4137: 2006 | C4137: 5 | D4137: 5 | E4137: 21.5 | F4137: 0 | G4137: 11.1 | H4137: 0 | I4137: 16.3 | J4137: 0 | K4137: 1020 | L4137: 0 | M4137: 60 | N4137: 11.9 | O4137: =IF(D4137=1,"",E4136) -> 27.5 | P4137: =IF(OR(D4137=1,K4136=""),"",K4136) -> 1013.9 | Q4137: =IF(OR(F4137<>0,AND(I4137<>"",E4137<I4137)),1,0) -> 0 | R4137: =IF(AND(D4137>1,Q4137=0,ISNUMBER(O4137),ISNUMBER(P4137)),IF(Q4136=0,1,0),0) -> 1 | S4137: =R4137*(B4137>=Train_Start)*(B4137<=Train_End) -> 0 | T4137: =IF(AND(ISNUMBER(O4137),ISNUMBER(P4137)),Coef_A+Coef_B1*O4137+Coef_B2*P4137,"") -> 26.424739 | U4137: =IF(AND(R4137=1,ISNUMBER(T4137)),E4137-T4137,"") -> -4.9247394 | V4137: =IF(ISNUMBER(T4137),T4137,-99) -> 26.424739 | W4137: =IF(ISNUMBER(U4137),ABS(U4137),"") -> 4.9247394
A4138: 38843 | B4138: 2006 | C4138: 5 | D4138: 6 | E4138: 17 | F4138: 0 | G4138: 6.6 | H4138: 0 | I4138: 11.8 | J4138: 0 | K4138: 1020.6 | L4138: 0 | M4138: 75 | N4138: 1.7 | O4138: =IF(D4138=1,"",E4137) -> 21.5 | P4138: =IF(OR(D4138=1,K4137=""),"",K4137) -> 1020 | Q4138: =IF(OR(F4138<>0,AND(I4138<>"",E4138<I4138)),1,0) -> 0 | R4138: =IF(AND(D4138>1,Q4138=0,ISNUMBER(O4138),ISNUMBER(P4138)),IF(Q4137=0,1,0),0) -> 1 | S4138: =R4138*(B4138>=Train_Start)*(B4138<=Train_End) -> 0 | T4138: =IF(AND(ISNUMBER(O4138),ISNUMBER(P4138)),Coef_A+Coef_B1*O4138+Coef_B2*P4138,"") -> 21.700061 | U4138: =IF(AND(R4138=1,ISNUMBER(T4138)),E4138-T4138,"") -> -4.7000606 | V4138: =IF(ISNUMBER(T4138),T4138,-99) -> 21.700061 | W4138: =IF(ISNUMBER(U4138),ABS(U4138),"") -> 4.7000606
A4139: 38844 | B4139: 2006 | C4139: 5 | D4139: 7 | E4139: 18.5 | F4139: 0 | G4139: 11.3 | H4139: 0 | I4139: 14.9 | J4139: 0 | K4139: 1016.5 | L4139: 0 | M4139: 81 | N4139: 1.5 | O4139: =IF(D4139=1,"",E4138) -> 17 | P4139: =IF(OR(D4139=1,K4138=""),"",K4138) -> 1020.6 | Q4139: =IF(OR(F4139<>0,AND(I4139<>"",E4139<I4139)),1,0) -> 0 | R4139: =IF(AND(D4139>1,Q4139=0,ISNUMBER(O4139),ISNUMBER(P4139)),IF(Q4138=0,1,0),0) -> 1 | S4139: =R4139*(B4139>=Train_Start)*(B4139<=Train_End) -> 0 | T4139: =IF(AND(ISNUMBER(O4139),ISNUMBER(P4139)),Coef_A+Coef_B1*O4139+Coef_B2*P4139,"") -> 18.031856 | U4139: =IF(AND(R4139=1,ISNUMBER(T4139)),E4139-T4139,"") -> 0.46814383 | V4139: =IF(ISNUMBER(T4139),T4139,-99) -> 18.031856 | W4139: =IF(ISNUMBER(U4139),ABS(U4139),"") -> 0.46814383
A4140: 38845 | B4140: 2006 | C4140: 5 | D4140: 8 | E4140: 15.2 | F4140: 0 | G4140: 11.2 | H4140: 0 | I4140: 13.2 | J4140: 0 | K4140: 1011.4 | L4140: 0 | M4140: 84 | N4140: 0.4 | O4140: =IF(D4140=1,"",E4139) -> 18.5 | P4140: =IF(OR(D4140=1,K4139=""),"",K4139) -> 1016.5 | Q4140: =IF(OR(F4140<>0,AND(I4140<>"",E4140<I4140)),1,0) -> 0 | R4140: =IF(AND(D4140>1,Q4140=0,ISNUMBER(O4140),ISNUMBER(P4140)),IF(Q4139=0,1,0),0) -> 1 | S4140: =R4140*(B4140>=Train_Start)*(B4140<=Train_End) -> 0 | T4140: =IF(AND(ISNUMBER(O4140),ISNUMBER(P4140)),Coef_A+Coef_B1*O4140+Coef_B2*P4140,"") -> 19.132248 | U4140: =IF(AND(R4140=1,ISNUMBER(T4140)),E4140-T4140,"") -> -3.9322484 | V4140: =IF(ISNUMBER(T4140),T4140,-99) -> 19.132248 | W4140: =IF(ISNUMBER(U4140),ABS(U4140),"") -> 3.9322484
A4141: 38846 | B4141: 2006 | C4141: 5 | D4141: 9 | E4141: 19.2 | F4141: 0 | G4141: 8.9 | H4141: 0 | I4141: 14 | J4141: 0 | K4141: 1017.2 | L4141: 0 | M4141: 80 | N4141: 2 | O4141: =IF(D4141=1,"",E4140) -> 15.2 | P4141: =IF(OR(D4141=1,K4140=""),"",K4140) -> 1011.4 | Q4141: =IF(OR(F4141<>0,AND(I4141<>"",E4141<I4141)),1,0) -> 0 | R4141: =IF(AND(D4141>1,Q4141=0,ISNUMBER(O4141),ISNUMBER(P4141)),IF(Q4140=0,1,0),0) -> 1 | S4141: =R4141*(B4141>=Train_Start)*(B4141<=Train_End) -> 0 | T4141: =IF(AND(ISNUMBER(O4141),ISNUMBER(P4141)),Coef_A+Coef_B1*O4141+Coef_B2*P4141,"") -> 16.268443 | U4141: =IF(AND(R4141=1,ISNUMBER(T4141)),E4141-T4141,"") -> 2.9315574 | V4141: =IF(ISNUMBER(T4141),T4141,-99) -> 16.268443 | W4141: =IF(ISNUMBER(U4141),ABS(U4141),"") -> 2.9315574
